Workbook
Name DatosExternos_1: IndicadoresPIIP!#REF!
Name PERIODO: Parametros!$A$2:$A$4

Sheet CriteriosCruce
A1: Definicion de acto_admon y objeto_reg en compromisos
A2: acto_admon → a través de qué modalidad se comprometen los recursos (contrato, resolución, orden de pago…).
A3: OBJETO_REG → con qué objeto / para qué se comprometen.
A5: Diferencias entre acto_admon (en compromisos) y tipo orden de gasto (en obligaciones)
A6: La única diferencia: el acto_admon trae el número del acto específico (…SALUD 285), y el tipo_orden_gasto es la categoría limpia, sin número (…SALUD).
A7: Es la misma modalidad, en dos momentos:
A8: acto_admon → en el compromiso (RP), texto libre con el número del acto. Sirve para trazar al documento exacto.
A9: tipo_orden_gasto → en la obligación, ya normalizado en catálogo (la dimensión OrdenGasto), sin número. Sirve para agrupar/clasificar.
A10: Piénsalo así: el tipo_orden_gasto es el acto_admon sin el número — SIIFWEB lo estandariza en una categoría cuando llegas a la obligación
A12: relacion entre historico_orden_orden_gasto_2 y orden de gasto por fecha
A13: Llave del contrato: tipo_contrato + nro_contrato + fecha_firma + NIT
A14: Identifican un contrato de forma única — verificado sobre el histórico: 9.789 grupos = 9.789 contratos reales, 0 colisiones de duración. Cada campo aporta:
... A19: Por qué se incluye el tipo (caso real): el contrato N.º 12 de M3 Soluciones Integrales SAS, firmado el 2023-11-03 (objeto: apoyo logístico), aparece con el mismo número, fecha y NIT pero dos tipos distintos — CONTRATO ADICIONAL LP ($90.000.000) y CONTRATO ADICIONAL MENOR CUANTIA ($320.000.000). Son dos adiciones al mismo contrato registradas con modalidad diferente. Sin el tipo, se fusionarían en un solo registro y perderías una. Es el único caso en ~9.800, pero justifica dejar el tipo en la llave.

Sheet Notas
A1: PASOS PARA CONSOLIDACIÓN
A2: PASO | B2: DESCRIPCION | C2: NOTA
A3: 1 | B3: Descargar reporte de cuipo de ejecución de gastos de datos abiertos: https://www.datos.gov.co/Gastos-Gubernamentales/OVCF-CUIPO-Ejecuci-n-de-Gastos/4f7r-epif/about_data | C3: Se excluyen reservas (obligaciones realizadas en una vigencia posterior)
A4: 2 | B4: Descargar reporte de ejecución acumulada de productos PIIP | C4: Se recomienda descargar de forma mensual porque PIIP no genera un reporte de ejecución trimestral. Toca tomar el reporte del ultimo mes del trimestre para tener el dato acumulado hasta ese corte
A5: 3 | B5: En el archivo Carga masiva IP - 70 - 20260805 las columnas de totales de presupuesto ordinario deben de modificarse para que no incluyan la formula. Power query no las lee cuando la columna tiene referencia a una formula
A7: Calculo
A8: 1 | B8: El cruce entre sispt, piip y cuipo se hace a traves del codigo de producto
A9: 2 | B9: Ellos realizan una agrupación a nivel de producto agregando mediante suma la programación fisica de la vigencia que vayan a evaluar. De esa forma, si un plan tiene un indicador duplicado, la agrupación asegura un unico producto con una unica programación en el plan
A10: 3 | B10: Para la ejecución física, se agrupan los productos de los proyectos que hayan registrado ejecución en el periodo y se agregan mediante suma.
A11: 4 | B11: Para la ejecución financiera, se agrupan los productos de los proyectos que hayan registrado obligaciones en el periodo (excluyendo reservas) y se agregan mediante suma.
A12: 5 | B12: Solo se considaran para el calculo los productos del índice de Eficacia base que tengan programación fisica, ejecución fisica y obligaciones en la vigencia. El resto se excluye

Sheet Reporte
A1: PERIODO | B1: 20260601 | C1: COMPROMISOS PERIODO | D1: =SUMIFS(CUIPO_datos_abiertos[COMPROMISOS],CUIPO_datos_abiertos[ES_PRODUCTO_VALIDO],"VALIDO",CUIPO_datos_abiertos[PERIODO],'Reporte'!$B$1) -> 641956722135 | E1: EFICACIA | F1: {=SUM(_xlfn._xlws.FILTER(Reporte[Aporte],Reporte[Aporte]<>""))} -> 0.023014005
A3: ="INDICE DE EFICACIA BASE " & INDEX(TablaPeriodos[],MATCH('Reporte'!$B$1,TablaPeriodos[Periodo],0),3) -> INDICE DE EFICACIA BASE SEGUNDO TRIMESTRE 2026
A5: Cód. Prod. | B5: Producto | C5: Cód. Ind. | D5: Indicador | E5: Programación Física de la Meta | F5: Ejecución Física PIIP | G5: Eje. Fís. SISPT | H5: Ver. Eje. Fís | I5: Proyectos Reporte PIIP | J5: Compromisos (CUIPO) | K5: Obligaciones (CUIPO) | L5: ¿Se tiene en cuenta para el calculo? | M5: Avance físico (%) | N5: Avance ajustado (%) | O5: Ponderador (wi) | P5: Aporte
A6: 2201071 | B6: Servicio educativo | C6: 220107100 | D6: Establecimientos educativos en operación | E6: {=_xlfn._xlws.FILTER(PI_SISPT_ProgramacionFisica[Prog. Fís.],(PI_SISPT_ProgramacionFisica[Cód. Prod.]=Reporte[[#This Row],[Cód. Prod.]])*(PI_SISPT_ProgramacionFisica[Vigencia]=LEFT('Reporte'!$B$1,4)))} -> 265 | F6: =SUMIFS(EjecucionPIIP[AvanceEjecutado],EjecucionPIIP[CodigoProducto],Reporte[[#This Row],[Cód. Prod.]],EjecucionPIIP[Periodo],$B$1,EjecucionPIIP[AvanceEjecutado],"<>0") -> 0 | G6: {=_xlfn._xlws.FILTER(ReporteEficacia[Meta ejecutada],(ReporteEficacia[Código producto]=Reporte[[#This Row],[Cód. Prod.]])*(ReporteEficacia[Periodo]='Reporte'!$B$1))} -> #VALUE! | H6: =IF(Reporte[[#This Row],[Ejecución Física PIIP]]=Reporte[[#This Row],[Eje. Fís. SISPT]],"Coincide","No coincide") -> #VALUE! | I6: {=_xlfn.TEXTJOIN(", ",TRUE,_xlfn._xlws.FILTER(EjecucionPIIP[Bpin],(EjecucionPIIP[Periodo]='Reporte'!$B$1)*(EjecucionPIIP[CodigoProducto]=Reporte[[#This Row],[Cód. Prod.]]),""))} -> 202500000049907 | J6: =SUMIFS(CUIPO_datos_abiertos[COMPROMISOS],CUIPO_datos_abiertos[COD_PROGRAMATICO_MGA],Reporte[[#This Row],[Cód. Prod.]],CUIPO_datos_abiertos[PERIODO],$B$1) -> 393505224553 | K6: =SUMIFS(CUIPO_datos_abiertos[OBLIGACIONES],CUIPO_datos_abiertos[COD_PROGRAMATICO_MGA],Reporte[[#This Row],[Cód. Prod.]],CUIPO_datos_abiertos[PERIODO],$B$1) -> 367702338497 | L6: =IF(AND(Reporte[[#This Row],[Programación Física de la Meta]]=0,Reporte[[#This Row],[Ejecución Física PIIP]]<>0,Reporte[[#This Row],[Obligaciones (CUIPO)]]<>0),"Excluidos",IF(AND(Reporte[[#This Row],[Programación Física de la Meta]]<>0,Reporte[[#This Row],[Ejecución Física PIIP]]<>0,Reporte[[#This Row],[Obligaciones (CUIPO)]]<>0),"Aporta al calculo","")) | M6: =IF(Reporte[[#This Row],[¿Se tiene en cuenta para el calculo?]]="Aporta al calculo",Reporte[[#This Row],[Ejecución Física PIIP]]/Reporte[[#This Row],[Programación Física de la Meta]],"") | N6: =IF(Reporte[[#This Row],[¿Se tiene en cuenta para el calculo?]]="Aporta al calculo",IF(Reporte[[#This Row],[Avance físico (%)]]>1,1,Reporte[[#This Row],[Avance físico (%)]]),"") | O6: =IF(Reporte[[#This Row],[¿Se tiene en cuenta para el calculo?]]="Aporta al calculo",Reporte[[#This Row],[Obligaciones (CUIPO)]]/$D$1,"") | P6: =IF(Reporte[[#This Row],[¿Se tiene en cuenta para el calculo?]]="Aporta al calculo",Reporte[[#This Row],[Avance ajustado (%)]]*Reporte[[#This Row],[Ponderador (wi)]],"")
A7: 2402018 | B7: Vía secundaria rehabilitada | C7: 240201800 | D7: Vía secundaria rehabilitada | E7: {=_xlfn._xlws.FILTER(PI_SISPT_ProgramacionFisica[Prog. Fís.],(PI_SISPT_ProgramacionFisica[Cód. Prod.]=Reporte[[#This Row],[Cód. Prod.]])*(PI_SISPT_ProgramacionFisica[Vigencia]=LEFT('Reporte'!$B$1,4)))} -> 8.7 | F7: =SUMIFS(EjecucionPIIP[AvanceEjecutado],EjecucionPIIP[CodigoProducto],Reporte[[#This Row],[Cód. Prod.]],EjecucionPIIP[Periodo],$B$1,EjecucionPIIP[AvanceEjecutado],"<>0") -> 0 | G7: {=_xlfn._xlws.FILTER(ReporteEficacia[Meta ejecutada],(ReporteEficacia[Código producto]=Reporte[[#This Row],[Cód. Prod.]])*(ReporteEficacia[Periodo]='Reporte'!$B$1))} -> #VALUE! | H7: =IF(Reporte[[#This Row],[Ejecución Física PIIP]]=Reporte[[#This Row],[Eje. Fís. SISPT]],"Coincide","No coincide") -> #VALUE! | I7: {=_xlfn.TEXTJOIN(", ",TRUE,_xlfn._xlws.FILTER(EjecucionPIIP[Bpin],(EjecucionPIIP[Periodo]='Reporte'!$B$1)*(EjecucionPIIP[CodigoProducto]=Reporte[[#This Row],[Cód. Prod.]]),""))} | J7: =SUMIFS(CUIPO_datos_abiertos[COMPROMISOS],CUIPO_datos_abiertos[COD_PROGRAMATICO_MGA],Reporte[[#This Row],[Cód. Prod.]],CUIPO_datos_abiertos[PERIODO],$B$1) -> 33431816466 | K7: =SUMIFS(CUIPO_datos_abiertos[OBLIGACIONES],CUIPO_datos_abiertos[COD_PROGRAMATICO_MGA],Reporte[[#This Row],[Cód. Prod.]],CUIPO_datos_abiertos[PERIODO],$B$1) -> 15280589499 | L7: =IF(AND(Reporte[[#This Row],[Programación Física de la Meta]]=0,Reporte[[#This Row],[Ejecución Física PIIP]]<>0,Reporte[[#This Row],[Obligaciones (CUIPO)]]<>0),"Excluidos",IF(AND(Reporte[[#This Row],[Programación Física de la Meta]]<>0,Reporte[[#This Row],[Ejecución Física PIIP]]<>0,Reporte[[#This Row],[Obligaciones (CUIPO)]]<>0),"Aporta al calculo","")) | M7: =IF(Reporte[[#This Row],[¿Se tiene en cuenta para el calculo?]]="Aporta al calculo",Reporte[[#This Row],[Ejecución Física PIIP]]/Reporte[[#This Row],[Programación Física de la Meta]],"") | N7: =IF(Reporte[[#This Row],[¿Se tiene en cuenta para el calculo?]]="Aporta al calculo",IF(Reporte[[#This Row],[Avance físico (%)]]>1,1,Reporte[[#This Row],[Avance físico (%)]]),"") | O7: =IF(Reporte[[#This Row],[¿Se tiene en cuenta para el calculo?]]="Aporta al calculo",Reporte[[#This Row],[Obligaciones (CUIPO)]]/$D$1,"") | P7: =IF(Reporte[[#This Row],[¿Se tiene en cuenta para el calculo?]]="Aporta al calculo",Reporte[[#This Row],[Avance ajustado (%)]]*Reporte[[#This Row],[Ponderador (wi)]],"")
A8: 4599003 | B8: Servicio de reeestructuracion de pasivos | C8: 459900300 | D8: Acuerdo de reestructuración de pasivos ejecutado | E8: {=_xlfn._xlws.FILTER(PI_SISPT_ProgramacionFisica[Prog. Fís.],(PI_SISPT_ProgramacionFisica[Cód. Prod.]=Reporte[[#This Row],[Cód. Prod.]])*(PI_SISPT_ProgramacionFisica[Vigencia]=LEFT('Reporte'!$B$1,4)))} -> 0.13 | F8: =SUMIFS(EjecucionPIIP[AvanceEjecutado],EjecucionPIIP[CodigoProducto],Reporte[[#This Row],[Cód. Prod.]],EjecucionPIIP[Periodo],$B$1,EjecucionPIIP[AvanceEjecutado],"<>0") -> 0 | G8: {=_xlfn._xlws.FILTER(ReporteEficacia[Meta ejecutada],(ReporteEficacia[Código producto]=Reporte[[#This Row],[Cód. Prod.]])*(ReporteEficacia[Periodo]='Reporte'!$B$1))} -> #VALUE! | H8: =IF(Reporte[[#This Row],[Ejecución Física PIIP]]=Reporte[[#This Row],[Eje. Fís. SISPT]],"Coincide","No coincide") -> #VALUE! | I8: {=_xlfn.TEXTJOIN(", ",TRUE,_xlfn._xlws.FILTER(EjecucionPIIP[Bpin],(EjecucionPIIP[Periodo]='Reporte'!$B$1)*(EjecucionPIIP[CodigoProducto]=Reporte[[#This Row],[Cód. Prod.]]),""))} | J8: =SUMIFS(CUIPO_datos_abiertos[COMPROMISOS],CUIPO_datos_abiertos[COD_PROGRAMATICO_MGA],Reporte[[#This Row],[Cód. Prod.]],CUIPO_datos_abiertos[PERIODO],$B$1) -> 12909544680 | K8: =SUMIFS(CUIPO_datos_abiertos[OBLIGACIONES],CUIPO_datos_abiertos[COD_PROGRAMATICO_MGA],Reporte[[#This Row],[Cód. Prod.]],CUIPO_datos_abiertos[PERIODO],$B$1) -> 12532668173 | L8: =IF(AND(Reporte[[#This Row],[Programación Física de la Meta]]=0,Reporte[[#This Row],[Ejecución Física PIIP]]<>0,Reporte[[#This Row],[Obligaciones (CUIPO)]]<>0),"Excluidos",IF(AND(Reporte[[#This Row],[Programación Física de la Meta]]<>0,Reporte[[#This Row],[Ejecución Física PIIP]]<>0,Reporte[[#This Row],[Obligaciones (CUIPO)]]<>0),"Aporta al calculo","")) | M8: =IF(Reporte[[#This Row],[¿Se tiene en cuenta para el calculo?]]="Aporta al calculo",Reporte[[#This Row],[Ejecución Física PIIP]]/Reporte[[#This Row],[Programación Física de la Meta]],"") | N8: =IF(Reporte[[#This Row],[¿Se tiene en cuenta para el calculo?]]="Aporta al calculo",IF(Reporte[[#This Row],[Avance físico (%)]]>1,1,Reporte[[#This Row],[Avance físico (%)]]),"") | O8: =IF(Reporte[[#This Row],[¿Se tiene en cuenta para el calculo?]]="Aporta al calculo",Reporte[[#This Row],[Obligaciones (CUIPO)]]/$D$1,"") | P8: =IF(Reporte[[#This Row],[¿Se tiene en cuenta para el calculo?]]="Aporta al calculo",Reporte[[#This Row],[Avance ajustado (%)]]*Reporte[[#This Row],[Ponderador (wi)]],"")
A9: 2201028 | B9: Servicio de apoyo a la permanencia con alimentación escolar | C9: 220102800 | D9: Raciones contratadas | E9: {=_xlfn._xlws.FILTER(PI_SISPT_ProgramacionFisica[Prog. Fís.],(PI_SISPT_ProgramacionFisica[Cód. Prod.]=Reporte[[#This Row],[Cód. Prod.]])*(PI_SISPT_ProgramacionFisica[Vigencia]=LEFT('Reporte'!$B$1,4)))} -> 8000000 | F9: =SUMIFS(EjecucionPIIP[AvanceEjecutado],EjecucionPIIP[CodigoProducto],Reporte[[#This Row],[Cód. Prod.]],EjecucionPIIP[Periodo],$B$1,EjecucionPIIP[AvanceEjecutado],"<>0") -> 1740449 | G9: {=_xlfn._xlws.FILTER(ReporteEficacia[Meta ejecutada],(ReporteEficacia[Código producto]=Reporte[[#This Row],[Cód. Prod.]])*(ReporteEficacia[Periodo]='Reporte'!$B$1))} -> #VALUE! | H9: =IF(Reporte[[#This Row],[Ejecución Física PIIP]]=Reporte[[#This Row],[Eje. Fís. SISPT]],"Coincide","No coincide") -> #VALUE! | I9: {=_xlfn.TEXTJOIN(", ",TRUE,_xlfn._xlws.FILTER(EjecucionPIIP[Bpin],(EjecucionPIIP[Periodo]='Reporte'!$B$1)*(EjecucionPIIP[CodigoProducto]=Reporte[[#This Row],[Cód. Prod.]]),""))} -> 202500000035386, 202500000042419 | J9: =SUMIFS(CUIPO_datos_abiertos[COMPROMISOS],CUIPO_datos_abiertos[COD_PROGRAMATICO_MGA],Reporte[[#This Row],[Cód. Prod.]],CUIPO_datos_abiertos[PERIODO],$B$1) -> 29734014223 | K9: =SUMIFS(CUIPO_datos_abiertos[OBLIGACIONES],CUIPO_datos_abiertos[COD_PROGRAMATICO_MGA],Reporte[[#This Row],[Cód. Prod.]],CUIPO_datos_abiertos[PERIODO],$B$1) -> 12363581024 | L9: =IF(AND(Reporte[[#This Row],[Programación Física de la Meta]]=0,Reporte[[#This Row],[Ejecución Física PIIP]]<>0,Reporte[[#This Row],[Obligaciones (CUIPO)]]<>0),"Excluidos",IF(AND(Reporte[[#This Row],[Programación Física de la Meta]]<>0,Reporte[[#This Row],[Ejecución Física PIIP]]<>0,Reporte[[#This Row],[Obligaciones (CUIPO)]]<>0),"Aporta al calculo","")) -> Aporta al calculo | M9: =IF(Reporte[[#This Row],[¿Se tiene en cuenta para el calculo?]]="Aporta al calculo",Reporte[[#This Row],[Ejecución Física PIIP]]/Reporte[[#This Row],[Programación Física de la Meta]],"") -> 0.21755612 | N9: =IF(Reporte[[#This Row],[¿Se tiene en cuenta para el calculo?]]="Aporta al calculo",IF(Reporte[[#This Row],[Avance físico (%)]]>1,1,Reporte[[#This Row],[Avance físico (%)]]),"") -> 0.21755612 | O9: =IF(Reporte[[#This Row],[¿Se tiene en cuenta para el calculo?]]="Aporta al calculo",Reporte[[#This Row],[Obligaciones (CUIPO)]]/$D$1,"") -> 0.019259213 | P9: =IF(Reporte[[#This Row],[¿Se tiene en cuenta para el calculo?]]="Aporta al calculo",Reporte[[#This Row],[Avance ajustado (%)]]*Reporte[[#This Row],[Ponderador (wi)]],"") -> 0.0041899597
A10: 1906030 | B10: Hospitales de primer nivel de atención construidos y dotados | C10: 190603000 | D10: Hospitales de primer nivel de atención construidos y dotados | E10: {=_xlfn._xlws.FILTER(PI_SISPT_ProgramacionFisica[Prog. Fís.],(PI_SISPT_ProgramacionFisica[Cód. Prod.]=Reporte[[#This Row],[Cód. Prod.]])*(PI_SISPT_ProgramacionFisica[Vigencia]=LEFT('Reporte'!$B$1,4)))} -> 0 | F10: =SUMIFS(EjecucionPIIP[AvanceEjecutado],EjecucionPIIP[CodigoProducto],Reporte[[#This Row],[Cód. Prod.]],EjecucionPIIP[Periodo],$B$1,EjecucionPIIP[AvanceEjecutado],"<>0") -> 0 | G10: {=_xlfn._xlws.FILTER(ReporteEficacia[Meta ejecutada],(ReporteEficacia[Código producto]=Reporte[[#This Row],[Cód. Prod.]])*(ReporteEficacia[Periodo]='Reporte'!$B$1))} -> #VALUE! | H10: =IF(Reporte[[#This Row],[Ejecución Física PIIP]]=Reporte[[#This Row],[Eje. Fís. SISPT]],"Coincide","No coincide") -> #VALUE! | I10: {=_xlfn.TEXTJOIN(", ",TRUE,_xlfn._xlws.FILTER(EjecucionPIIP[Bpin],(EjecucionPIIP[Periodo]='Reporte'!$B$1)*(EjecucionPIIP[CodigoProducto]=Reporte[[#This Row],[Cód. Prod.]]),""))} -> 2023002700021 | J10: =SUMIFS(CUIPO_datos_abiertos[COMPROMISOS],CUIPO_datos_abiertos[COD_PROGRAMATICO_MGA],Reporte[[#This Row],[Cód. Prod.]],CUIPO_datos_abiertos[PERIODO],$B$1) -> 22295459973 | K10: =SUMIFS(CUIPO_datos_abiertos[OBLIGACIONES],CUIPO_datos_abiertos[COD_PROGRAMATICO_MGA],Reporte[[#This Row],[Cód. Prod.]],CUIPO_datos_abiertos[PERIODO],$B$1) -> 9991793731 | L10: =IF(AND(Reporte[[#This Row],[Programación Física de la Meta]]=0,Reporte[[#This Row],[Ejecución Física PIIP]]<>0,Reporte[[#This Row],[Obligaciones (CUIPO)]]<>0),"Excluidos",IF(AND(Reporte[[#This Row],[Programación Física de la Meta]]<>0,Reporte[[#This Row],[Ejecución Física PIIP]]<>0,Reporte[[#This Row],[Obligaciones (CUIPO)]]<>0),"Aporta al calculo","")) | M10: =IF(Reporte[[#This Row],[¿Se tiene en cuenta para el calculo?]]="Aporta al calculo",Reporte[[#This Row],[Ejecución Física PIIP]]/Reporte[[#This Row],[Programación Física de la Meta]],"") | N10: =IF(Reporte[[#This Row],[¿Se tiene en cuenta para el calculo?]]="Aporta al calculo",IF(Reporte[[#This Row],[Avance físico (%)]]>1,1,Reporte[[#This Row],[Avance físico (%)]]),"") | O10: =IF(Reporte[[#This Row],[¿Se tiene en cuenta para el calculo?]]="Aporta al calculo",Reporte[[#This Row],[Obligaciones (CUIPO)]]/$D$1,"") | P10: =IF(Reporte[[#This Row],[¿Se tiene en cuenta para el calculo?]]="Aporta al calculo",Reporte[[#This Row],[Avance ajustado (%)]]*Reporte[[#This Row],[Ponderador (wi)]],"")
A11: 4501079 | B11: Servicio de dotación para la movilidad operacional y el apoyo logístico | C11: 450107900 | D11: Unidades dotadas | E11: {=_xlfn._xlws.FILTER(PI_SISPT_ProgramacionFisica[Prog. Fís.],(PI_SISPT_ProgramacionFisica[Cód. Prod.]=Reporte[[#This Row],[Cód. Prod.]])*(PI_SISPT_ProgramacionFisica[Vigencia]=LEFT('Reporte'!$B$1,4)))} -> 9 | F11: =SUMIFS(EjecucionPIIP[AvanceEjecutado],EjecucionPIIP[CodigoProducto],Reporte[[#This Row],[Cód. Prod.]],EjecucionPIIP[Periodo],$B$1,EjecucionPIIP[AvanceEjecutado],"<>0") -> 0 | G11: {=_xlfn._xlws.FILTER(ReporteEficacia[Meta ejecutada],(ReporteEficacia[Código producto]=Reporte[[#This Row],[Cód. Prod.]])*(ReporteEficacia[Periodo]='Reporte'!$B$1))} -> #VALUE! | H11: =IF(Reporte[[#This Row],[Ejecución Física PIIP]]=Reporte[[#This Row],[Eje. Fís. SISPT]],"Coincide","No coincide") -> #VALUE! | I11: {=_xlfn.TEXTJOIN(", ",TRUE,_xlfn._xlws.FILTER(EjecucionPIIP[Bpin],(EjecucionPIIP[Periodo]='Reporte'!$B$1)*(EjecucionPIIP[CodigoProducto]=Reporte[[#This Row],[Cód. Prod.]]),""))} | J11: =SUMIFS(CUIPO_datos_abiertos[COMPROMISOS],CUIPO_datos_abiertos[COD_PROGRAMATICO_MGA],Reporte[[#This Row],[Cód. Prod.]],CUIPO_datos_abiertos[PERIODO],$B$1) -> 7718197813 | K11: =SUMIFS(CUIPO_datos_abiertos[OBLIGACIONES],CUIPO_datos_abiertos[COD_PROGRAMATICO_MGA],Reporte[[#This Row],[Cód. Prod.]],CUIPO_datos_abiertos[PERIODO],$B$1) -> 7718197813 | L11: =IF(AND(Reporte[[#This Row],[Programación Física de la Meta]]=0,Reporte[[#This Row],[Ejecución Física PIIP]]<>0,Reporte[[#This Row],[Obligaciones (CUIPO)]]<>0),"Excluidos",IF(AND(Reporte[[#This Row],[Programación Física de la Meta]]<>0,Reporte[[#This Row],[Ejecución Física PIIP]]<>0,Reporte[[#This Row],[Obligaciones (CUIPO)]]<>0),"Aporta al calculo","")) | M11: =IF(Reporte[[#This Row],[¿Se tiene en cuenta para el calculo?]]="Aporta al calculo",Reporte[[#This Row],[Ejecución Física PIIP]]/Reporte[[#This Row],[Programación Física de la Meta]],"") | N11: =IF(Reporte[[#This Row],[¿Se tiene en cuenta para el calculo?]]="Aporta al calculo",IF(Reporte[[#This Row],[Avance físico (%)]]>1,1,Reporte[[#This Row],[Avance físico (%)]]),"") | O11: =IF(Reporte[[#This Row],[¿Se tiene en cuenta para el calculo?]]="Aporta al calculo",Reporte[[#This Row],[Obligaciones (CUIPO)]]/$D$1,"") | P11: =IF(Reporte[[#This Row],[¿Se tiene en cuenta para el calculo?]]="Aporta al calculo",Reporte[[#This Row],[Avance ajustado (%)]]*Reporte[[#This Row],[Ponderador (wi)]],"")
A12: 4599031 | B12: Servicio de asistencia técnica | C12: 459903100 | D12: Entidades, organismos y dependencias asistidos técnicamente | E12: {=_xlfn._xlws.FILTER(PI_SISPT_ProgramacionFisica[Prog. Fís.],(PI_SISPT_ProgramacionFisica[Cód. Prod.]=Reporte[[#This Row],[Cód. Prod.]])*(PI_SISPT_ProgramacionFisica[Vigencia]=LEFT('Reporte'!$B$1,4)))} -> 14 | F12: =SUMIFS(EjecucionPIIP[AvanceEjecutado],EjecucionPIIP[CodigoProducto],Reporte[[#This Row],[Cód. Prod.]],EjecucionPIIP[Periodo],$B$1,EjecucionPIIP[AvanceEjecutado],"<>0") -> 1 | G12: {=_xlfn._xlws.FILTER(ReporteEficacia[Meta ejecutada],(ReporteEficacia[Código producto]=Reporte[[#This Row],[Cód. Prod.]])*(ReporteEficacia[Periodo]='Reporte'!$B$1))} -> #VALUE! | H12: =IF(Reporte[[#This Row],[Ejecución Física PIIP]]=Reporte[[#This Row],[Eje. Fís. SISPT]],"Coincide","No coincide") -> #VALUE! | I12: {=_xlfn.TEXTJOIN(", ",TRUE,_xlfn._xlws.FILTER(EjecucionPIIP[Bpin],(EjecucionPIIP[Periodo]='Reporte'!$B$1)*(EjecucionPIIP[CodigoProducto]=Reporte[[#This Row],[Cód. Prod.]]),""))} -> 202500000025321, 202500000050078, 202600000005933 | J12: =SUMIFS(CUIPO_datos_abiertos[COMPROMISOS],CUIPO_datos_abiertos[COD_PROGRAMATICO_MGA],Reporte[[#This Row],[Cód. Prod.]],CUIPO_datos_abiertos[PERIODO],$B$1) -> 6527729587 | K12: =SUMIFS(CUIPO_datos_abiertos[OBLIGACIONES],CUIPO_datos_abiertos[COD_PROGRAMATICO_MGA],Reporte[[#This Row],[Cód. Prod.]],CUIPO_datos_abiertos[PERIODO],$B$1) -> 5864726020 | L12: =IF(AND(Reporte[[#This Row],[Programación Física de la Meta]]=0,Reporte[[#This Row],[Ejecución Física PIIP]]<>0,Reporte[[#This Row],[Obligaciones (CUIPO)]]<>0),"Excluidos",IF(AND(Reporte[[#This Row],[Programación Física de la Meta]]<>0,Reporte[[#This Row],[Ejecución Física PIIP]]<>0,Reporte[[#This Row],[Obligaciones (CUIPO)]]<>0),"Aporta al calculo","")) -> Aporta al calculo | M12: =IF(Reporte[[#This Row],[¿Se tiene en cuenta para el calculo?]]="Aporta al calculo",Reporte[[#This Row],[Ejecución Física PIIP]]/Reporte[[#This Row],[Programación Física de la Meta]],"") -> 0.071428571 | N12: =IF(Reporte[[#This Row],[¿Se tiene en cuenta para el calculo?]]="Aporta al calculo",IF(Reporte[[#This Row],[Avance físico (%)]]>1,1,Reporte[[#This Row],[Avance físico (%)]]),"") -> 0.071428571 | O12: =IF(Reporte[[#This Row],[¿Se tiene en cuenta para el calculo?]]="Aporta al calculo",Reporte[[#This Row],[Obligaciones (CUIPO)]]/$D$1,"") -> 0.0091357031 | P12: =IF(Reporte[[#This Row],[¿Se tiene en cuenta para el calculo?]]="Aporta al calculo",Reporte[[#This Row],[Avance ajustado (%)]]*Reporte[[#This Row],[Ponderador (wi)]],"") -> 0.00065255022
A13: 1903035 | B13: Servicio de inspección, vigilancia y control de los factores del riesgo del ambiente que afectan la salud humana | C13: 190303500 | D13: Distritos con acciones de Inspección Vigilancia y Control reales y efectivas de los factores del riesgo del ambiente que afectan la salud humana realizados | E13: {=_xlfn._xlws.FILTER(PI_SISPT_ProgramacionFisica[Prog. Fís.],(PI_SISPT_ProgramacionFisica[Cód. Prod.]=Reporte[[#This Row],[Cód. Prod.]])*(PI_SISPT_ProgramacionFisica[Vigencia]=LEFT('Reporte'!$B$1,4)))} -> 3 | F13: =SUMIFS(EjecucionPIIP[AvanceEjecutado],EjecucionPIIP[CodigoProducto],Reporte[[#This Row],[Cód. Prod.]],EjecucionPIIP[Periodo],$B$1,EjecucionPIIP[AvanceEjecutado],"<>0") -> 0.5 | G13: {=_xlfn._xlws.FILTER(ReporteEficacia[Meta ejecutada],(ReporteEficacia[Código producto]=Reporte[[#This Row],[Cód. Prod.]])*(ReporteEficacia[Periodo]='Reporte'!$B$1))} -> #VALUE! | H13: =IF(Reporte[[#This Row],[Ejecución Física PIIP]]=Reporte[[#This Row],[Eje. Fís. SISPT]],"Coincide","No coincide") -> #VALUE! | I13: {=_xlfn.TEXTJOIN(", ",TRUE,_xlfn._xlws.FILTER(EjecucionPIIP[Bpin],(EjecucionPIIP[Periodo]='Reporte'!$B$1)*(EjecucionPIIP[CodigoProducto]=Reporte[[#This Row],[Cód. Prod.]]),""))} -> 202500000047955 | J13: =SUMIFS(CUIPO_datos_abiertos[COMPROMISOS],CUIPO_datos_abiertos[COD_PROGRAMATICO_MGA],Reporte[[#This Row],[Cód. Prod.]],CUIPO_datos_abiertos[PERIODO],$B$1) -> 7164506229 | K13: =SUMIFS(CUIPO_datos_abiertos[OBLIGACIONES],CUIPO_datos_abiertos[COD_PROGRAMATICO_MGA],Reporte[[#This Row],[Cód. Prod.]],CUIPO_datos_abiertos[PERIODO],$B$1) -> 4450475298 | L13: =IF(AND(Reporte[[#This Row],[Programación Física de la Meta]]=0,Reporte[[#This Row],[Ejecución Física PIIP]]<>0,Reporte[[#This Row],[Obligaciones (CUIPO)]]<>0),"Excluidos",IF(AND(Reporte[[#This Row],[Programación Física de la Meta]]<>0,Reporte[[#This Row],[Ejecución Física PIIP]]<>0,Reporte[[#This Row],[Obligaciones (CUIPO)]]<>0),"Aporta al calculo","")) -> Aporta al calculo | M13: =IF(Reporte[[#This Row],[¿Se tiene en cuenta para el calculo?]]="Aporta al calculo",Reporte[[#This Row],[Ejecución Física PIIP]]/Reporte[[#This Row],[Programación Física de la Meta]],"") -> 0.16666667 | N13: =IF(Reporte[[#This Row],[¿Se tiene en cuenta para el calculo?]]="Aporta al calculo",IF(Reporte[[#This Row],[Avance físico (%)]]>1,1,Reporte[[#This Row],[Avance físico (%)]]),"") -> 0.16666667 | O13: =IF(Reporte[[#This Row],[¿Se tiene en cuenta para el calculo?]]="Aporta al calculo",Reporte[[#This Row],[Obligaciones (CUIPO)]]/$D$1,"") -> 0.0069326719 | P13: =IF(Reporte[[#This Row],[¿Se tiene en cuenta para el calculo?]]="Aporta al calculo",Reporte[[#This Row],[Avance ajustado (%)]]*Reporte[[#This Row],[Ponderador (wi)]],"") -> 0.0011554453
A14: 4301001 | B14: Servicio de apoyo a la actividad física, la recreación y el deporte | C14: 430100100 | D14: Personas beneficiadas | E14: {=_xlfn._xlws.FILTER(PI_SISPT_ProgramacionFisica[Prog. Fís.],(PI_SISPT_ProgramacionFisica[Cód. Prod.]=Reporte[[#This Row],[Cód. Prod.]])*(PI_SISPT_ProgramacionFisica[Vigencia]=LEFT('Reporte'!$B$1,4)))} -> 17500 | F14: =SUMIFS(EjecucionPIIP[AvanceEjecutado],EjecucionPIIP[CodigoProducto],Reporte[[#This Row],[Cód. Prod.]],EjecucionPIIP[Periodo],$B$1,EjecucionPIIP[AvanceEjecutado],"<>0") -> 953324 | G14: {=_xlfn._xlws.FILTER(ReporteEficacia[Meta ejecutada],(ReporteEficacia[Código producto]=Reporte[[#This Row],[Cód. Prod.]])*(ReporteEficacia[Periodo]='Reporte'!$B$1))} -> #VALUE! | H14: =IF(Reporte[[#This Row],[Ejecución Física PIIP]]=Reporte[[#This Row],[Eje. Fís. SISPT]],"Coincide","No coincide") -> #VALUE! | I14: {=_xlfn.TEXTJOIN(", ",TRUE,_xlfn._xlws.FILTER(EjecucionPIIP[Bpin],(EjecucionPIIP[Periodo]='Reporte'!$B$1)*(EjecucionPIIP[CodigoProducto]=Reporte[[#This Row],[Cód. Prod.]]),""))} -> 202500000050554, 202600000000593, 202600000007861, 202600000008787, 202600000012764 | J14: =SUMIFS(CUIPO_datos_abiertos[COMPROMISOS],CUIPO_datos_abiertos[COD_PROGRAMATICO_MGA],Reporte[[#This Row],[Cód. Prod.]],CUIPO_datos_abiertos[PERIODO],$B$1) -> 4414341532 | K14: =SUMIFS(CUIPO_datos_abiertos[OBLIGACIONES],CUIPO_datos_abiertos[COD_PROGRAMATICO_MGA],Reporte[[#This Row],[Cód. Prod.]],CUIPO_datos_abiertos[PERIODO],$B$1) -> 4414341532 | L14: =IF(AND(Reporte[[#This Row],[Programación Física de la Meta]]=0,Reporte[[#This Row],[Ejecución Física PIIP]]<>0,Reporte[[#This Row],[Obligaciones (CUIPO)]]<>0),"Excluidos",IF(AND(Reporte[[#This Row],[Programación Física de la Meta]]<>0,Reporte[[#This Row],[Ejecución Física PIIP]]<>0,Reporte[[#This Row],[Obligaciones (CUIPO)]]<>0),"Aporta al calculo","")) -> Aporta al calculo | M14: =IF(Reporte[[#This Row],[¿Se tiene en cuenta para el calculo?]]="Aporta al calculo",Reporte[[#This Row],[Ejecución Física PIIP]]/Reporte[[#This Row],[Programación Física de la Meta]],"") -> 54.475657 | N14: =IF(Reporte[[#This Row],[¿Se tiene en cuenta para el calculo?]]="Aporta al calculo",IF(Reporte[[#This Row],[Avance físico (%)]]>1,1,Reporte[[#This Row],[Avance físico (%)]]),"") -> 1 | O14: =IF(Reporte[[#This Row],[¿Se tiene en cuenta para el calculo?]]="Aporta al calculo",Reporte[[#This Row],[Obligaciones (CUIPO)]]/$D$1,"") -> 0.0068763849 | P14: =IF(Reporte[[#This Row],[¿Se tiene en cuenta para el calculo?]]="Aporta al calculo",Reporte[[#This Row],[Avance ajustado (%)]]*Reporte[[#This Row],[Ponderador (wi)]],"") -> 0.0068763849
A15: 4599002 | B15: Servicio de saneamiento fiscal y financiero | C15: 459900200 | D15: Programa de sanemiento fiscal y financiero ejecutado | E15: {=_xlfn._xlws.FILTER(PI_SISPT_ProgramacionFisica[Prog. Fís.],(PI_SISPT_ProgramacionFisica[Cód. Prod.]=Reporte[[#This Row],[Cód. Prod.]])*(PI_SISPT_ProgramacionFisica[Vigencia]=LEFT('Reporte'!$B$1,4)))} -> 1 | F15: =SUMIFS(EjecucionPIIP[AvanceEjecutado],EjecucionPIIP[CodigoProducto],Reporte[[#This Row],[Cód. Prod.]],EjecucionPIIP[Periodo],$B$1,EjecucionPIIP[AvanceEjecutado],"<>0") -> 61.71 | G15: {=_xlfn._xlws.FILTER(ReporteEficacia[Meta ejecutada],(ReporteEficacia[Código producto]=Reporte[[#This Row],[Cód. Prod.]])*(ReporteEficacia[Periodo]='Reporte'!$B$1))} -> #VALUE! | H15: =IF(Reporte[[#This Row],[Ejecución Física PIIP]]=Reporte[[#This Row],[Eje. Fís. SISPT]],"Coincide","No coincide") -> #VALUE! | I15: {=_xlfn.TEXTJOIN(", ",TRUE,_xlfn._xlws.FILTER(EjecucionPIIP[Bpin],(EjecucionPIIP[Periodo]='Reporte'!$B$1)*(EjecucionPIIP[CodigoProducto]=Reporte[[#This Row],[Cód. Prod.]]),""))} -> 202500000032612, 202500000038150 | J15: =SUMIFS(CUIPO_datos_abiertos[COMPROMISOS],CUIPO_datos_abiertos[COD_PROGRAMATICO_MGA],Reporte[[#This Row],[Cód. Prod.]],CUIPO_datos_abiertos[PERIODO],$B$1) -> 3810249058 | K15: =SUMIFS(CUIPO_datos_abiertos[OBLIGACIONES],CUIPO_datos_abiertos[COD_PROGRAMATICO_MGA],Reporte[[#This Row],[Cód. Prod.]],CUIPO_datos_abiertos[PERIODO],$B$1) -> 3582249058 | L15: =IF(AND(Reporte[[#This Row],[Programación Física de la Meta]]=0,Reporte[[#This Row],[Ejecución Física PIIP]]<>0,Reporte[[#This Row],[Obligaciones (CUIPO)]]<>0),"Excluidos",IF(AND(Reporte[[#This Row],[Programación Física de la Meta]]<>0,Reporte[[#This Row],[Ejecución Física PIIP]]<>0,Reporte[[#This Row],[Obligaciones (CUIPO)]]<>0),"Aporta al calculo","")) -> Aporta al calculo | M15: =IF(Reporte[[#This Row],[¿Se tiene en cuenta para el calculo?]]="Aporta al calculo",Reporte[[#This Row],[Ejecución Física PIIP]]/Reporte[[#This Row],[Programación Física de la Meta]],"") -> 61.71 | N15: =IF(Reporte[[#This Row],[¿Se tiene en cuenta para el calculo?]]="Aporta al calculo",IF(Reporte[[#This Row],[Avance físico (%)]]>1,1,Reporte[[#This Row],[Avance físico (%)]]),"") -> 1 | O15: =IF(Reporte[[#This Row],[¿Se tiene en cuenta para el calculo?]]="Aporta al calculo",Reporte[[#This Row],[Obligaciones (CUIPO)]]/$D$1,"") -> 0.0055802034 | P15: =IF(Reporte[[#This Row],[¿Se tiene en cuenta para el calculo?]]="Aporta al calculo",Reporte[[#This Row],[Avance ajustado (%)]]*Reporte[[#This Row],[Ponderador (wi)]],"") -> 0.0055802034
A16: 2102058 | B16: Unidades de generación fotovoltaica de energía eléctrica instaladas | C16: 210205800 | D16: Unidades de generación fotovoltaica de energía eléctrica instaladas | E16: {=_xlfn._xlws.FILTER(PI_SISPT_ProgramacionFisica[Prog. Fís.],(PI_SISPT_ProgramacionFisica[Cód. Prod.]=Reporte[[#This Row],[Cód. Prod.]])*(PI_SISPT_ProgramacionFisica[Vigencia]=LEFT('Reporte'!$B$1,4)))} -> 470 | F16: =SUMIFS(EjecucionPIIP[AvanceEjecutado],EjecucionPIIP[CodigoProducto],Reporte[[#This Row],[Cód. Prod.]],EjecucionPIIP[Periodo],$B$1,EjecucionPIIP[AvanceEjecutado],"<>0") -> 60 | G16: {=_xlfn._xlws.FILTER(ReporteEficacia[Meta ejecutada],(ReporteEficacia[Código producto]=Reporte[[#This Row],[Cód. Prod.]])*(ReporteEficacia[Periodo]='Reporte'!$B$1))} -> #VALUE! | H16: =IF(Reporte[[#This Row],[Ejecución Física PIIP]]=Reporte[[#This Row],[Eje. Fís. SISPT]],"Coincide","No coincide") -> #VALUE! | I16: {=_xlfn.TEXTJOIN(", ",TRUE,_xlfn._xlws.FILTER(EjecucionPIIP[Bpin],(EjecucionPIIP[Periodo]='Reporte'!$B$1)*(EjecucionPIIP[CodigoProducto]=Reporte[[#This Row],[Cód. Prod.]]),""))} -> 2024002700131, 202500000034777 | J16: =SUMIFS(CUIPO_datos_abiertos[COMPROMISOS],CUIPO_datos_abiertos[COD_PROGRAMATICO_MGA],Reporte[[#This Row],[Cód. Prod.]],CUIPO_datos_abiertos[PERIODO],$B$1) -> 3548957101 | K16: =SUMIFS(CUIPO_datos_abiertos[OBLIGACIONES],CUIPO_datos_abiertos[COD_PROGRAMATICO_MGA],Reporte[[#This Row],[Cód. Prod.]],CUIPO_datos_abiertos[PERIODO],$B$1) -> 3120331456 | L16: =IF(AND(Reporte[[#This Row],[Programación Física de la Meta]]=0,Reporte[[#This Row],[Ejecución Física PIIP]]<>0,Reporte[[#This Row],[Obligaciones (CUIPO)]]<>0),"Excluidos",IF(AND(Reporte[[#This Row],[Programación Física de la Meta]]<>0,Reporte[[#This Row],[Ejecución Física PIIP]]<>0,Reporte[[#This Row],[Obligaciones (CUIPO)]]<>0),"Aporta al calculo","")) -> Aporta al calculo | M16: =IF(Reporte[[#This Row],[¿Se tiene en cuenta para el calculo?]]="Aporta al calculo",Reporte[[#This Row],[Ejecución Física PIIP]]/Reporte[[#This Row],[Programación Física de la Meta]],"") -> 0.12765957 | N16: =IF(Reporte[[#This Row],[¿Se tiene en cuenta para el calculo?]]="Aporta al calculo",IF(Reporte[[#This Row],[Avance físico (%)]]>1,1,Reporte[[#This Row],[Avance físico (%)]]),"") -> 0.12765957 | O16: =IF(Reporte[[#This Row],[¿Se tiene en cuenta para el calculo?]]="Aporta al calculo",Reporte[[#This Row],[Obligaciones (CUIPO)]]/$D$1,"") -> 0.004860657 | P16: =IF(Reporte[[#This Row],[¿Se tiene en cuenta para el calculo?]]="Aporta al calculo",Reporte[[#This Row],[Avance ajustado (%)]]*Reporte[[#This Row],[Ponderador (wi)]],"") -> 0.00062050941
A17: 3301053 | B17: Servicio de promoción de actividades culturales | C17: 330105300 | D17: Eventos de promoción de actividades culturales realizados | E17: {=_xlfn._xlws.FILTER(PI_SISPT_ProgramacionFisica[Prog. Fís.],(PI_SISPT_ProgramacionFisica[Cód. Prod.]=Reporte[[#This Row],[Cód. Prod.]])*(PI_SISPT_ProgramacionFisica[Vigencia]=LEFT('Reporte'!$B$1,4)))} -> 43 | F17: =SUMIFS(EjecucionPIIP[AvanceEjecutado],EjecucionPIIP[CodigoProducto],Reporte[[#This Row],[Cód. Prod.]],EjecucionPIIP[Periodo],$B$1,EjecucionPIIP[AvanceEjecutado],"<>0") -> 5 | G17: {=_xlfn._xlws.FILTER(ReporteEficacia[Meta ejecutada],(ReporteEficacia[Código producto]=Reporte[[#This Row],[Cód. Prod.]])*(ReporteEficacia[Periodo]='Reporte'!$B$1))} -> #VALUE! | H17: =IF(Reporte[[#This Row],[Ejecución Física PIIP]]=Reporte[[#This Row],[Eje. Fís. SISPT]],"Coincide","No coincide") -> #VALUE! | I17: {=_xlfn.TEXTJOIN(", ",TRUE,_xlfn._xlws.FILTER(EjecucionPIIP[Bpin],(EjecucionPIIP[Periodo]='Reporte'!$B$1)*(EjecucionPIIP[CodigoProducto]=Reporte[[#This Row],[Cód. Prod.]]),""))} -> 202600000001594 | J17: =SUMIFS(CUIPO_datos_abiertos[COMPROMISOS],CUIPO_datos_abiertos[COD_PROGRAMATICO_MGA],Reporte[[#This Row],[Cód. Prod.]],CUIPO_datos_abiertos[PERIODO],$B$1) -> 2589826566 | K17: =SUMIFS(CUIPO_datos_abiertos[OBLIGACIONES],CUIPO_datos_abiertos[COD_PROGRAMATICO_MGA],Reporte[[#This Row],[Cód. Prod.]],CUIPO_datos_abiertos[PERIODO],$B$1) -> 2589826566 | L17: =IF(AND(Reporte[[#This Row],[Programación Física de la Meta]]=0,Reporte[[#This Row],[Ejecución Física PIIP]]<>0,Reporte[[#This Row],[Obligaciones (CUIPO)]]<>0),"Excluidos",IF(AND(Reporte[[#This Row],[Programación Física de la Meta]]<>0,Reporte[[#This Row],[Ejecución Física PIIP]]<>0,Reporte[[#This Row],[Obligaciones (CUIPO)]]<>0),"Aporta al calculo","")) -> Aporta al calculo | M17: =IF(Reporte[[#This Row],[¿Se tiene en cuenta para el calculo?]]="Aporta al calculo",Reporte[[#This Row],[Ejecución Física PIIP]]/Reporte[[#This Row],[Programación Física de la Meta]],"") -> 0.11627907 | N17: =IF(Reporte[[#This Row],[¿Se tiene en cuenta para el calculo?]]="Aporta al calculo",IF(Reporte[[#This Row],[Avance físico (%)]]>1,1,Reporte[[#This Row],[Avance físico (%)]]),"") -> 0.11627907 | O17: =IF(Reporte[[#This Row],[¿Se tiene en cuenta para el calculo?]]="Aporta al calculo",Reporte[[#This Row],[Obligaciones (CUIPO)]]/$D$1,"") -> 0.0040342697 | P17: =IF(Reporte[[#This Row],[¿Se tiene en cuenta para el calculo?]]="Aporta al calculo",Reporte[[#This Row],[Avance ajustado (%)]]*Reporte[[#This Row],[Ponderador (wi)]],"") -> 0.00046910113
... A291: 1702007 | B291: Servicio de apoyo financiero para proyectos productivos | C291: 170200700 | D291: Proyectos productivos cofinanciados | E291: {=_xlfn._xlws.FILTER(PI_SISPT_ProgramacionFisica[Prog. Fís.],(PI_SISPT_ProgramacionFisica[Cód. Prod.]=Reporte[[#This Row],[Cód. Prod.]])*(PI_SISPT_ProgramacionFisica[Vigencia]=LEFT('Reporte'!$B$1,4)))} -> 4 | F291: =SUMIFS(EjecucionPIIP[AvanceEjecutado],EjecucionPIIP[CodigoProducto],Reporte[[#This Row],[Cód. Prod.]],EjecucionPIIP[Periodo],$B$1,EjecucionPIIP[AvanceEjecutado],"<>0") -> 0 | G291: {=_xlfn._xlws.FILTER(ReporteEficacia[Meta ejecutada],(ReporteEficacia[Código producto]=Reporte[[#This Row],[Cód. Prod.]])*(ReporteEficacia[Periodo]='Reporte'!$B$1))} -> #VALUE! | H291: =IF(Reporte[[#This Row],[Ejecución Física PIIP]]=Reporte[[#This Row],[Eje. Fís. SISPT]],"Coincide","No coincide") -> #VALUE! | I291: {=_xlfn.TEXTJOIN(", ",TRUE,_xlfn._xlws.FILTER(EjecucionPIIP[Bpin],(EjecucionPIIP[Periodo]='Reporte'!$B$1)*(EjecucionPIIP[CodigoProducto]=Reporte[[#This Row],[Cód. Prod.]]),""))} | J291: =SUMIFS(CUIPO_datos_abiertos[COMPROMISOS],CUIPO_datos_abiertos[COD_PROGRAMATICO_MGA],Reporte[[#This Row],[Cód. Prod.]],CUIPO_datos_abiertos[PERIODO],$B$1) -> 0 | K291: =SUMIFS(CUIPO_datos_abiertos[OBLIGACIONES],CUIPO_datos_abiertos[COD_PROGRAMATICO_MGA],Reporte[[#This Row],[Cód. Prod.]],CUIPO_datos_abiertos[PERIODO],$B$1) -> 0 | L291: =IF(AND(Reporte[[#This Row],[Programación Física de la Meta]]=0,Reporte[[#This Row],[Ejecución Física PIIP]]<>0,Reporte[[#This Row],[Obligaciones (CUIPO)]]<>0),"Excluidos",IF(AND(Reporte[[#This Row],[Programación Física de la Meta]]<>0,Reporte[[#This Row],[Ejecución Física PIIP]]<>0,Reporte[[#This Row],[Obligaciones (CUIPO)]]<>0),"Aporta al calculo","")) | M291: =IF(Reporte[[#This Row],[¿Se tiene en cuenta para el calculo?]]="Aporta al calculo",Reporte[[#This Row],[Ejecución Física PIIP]]/Reporte[[#This Row],[Programación Física de la Meta]],"") | N291: =IF(Reporte[[#This Row],[¿Se tiene en cuenta para el calculo?]]="Aporta al calculo",IF(Reporte[[#This Row],[Avance físico (%)]]>1,1,Reporte[[#This Row],[Avance físico (%)]]),"") | O291: =IF(Reporte[[#This Row],[¿Se tiene en cuenta para el calculo?]]="Aporta al calculo",Reporte[[#This Row],[Obligaciones (CUIPO)]]/$D$1,"") | P291: =IF(Reporte[[#This Row],[¿Se tiene en cuenta para el calculo?]]="Aporta al calculo",Reporte[[#This Row],[Avance ajustado (%)]]*Reporte[[#This Row],[Ponderador (wi)]],"")

Sheet Parametros
A1: PERIODO | C1: Periodo | D1: Nombre | E1: En mayuscula
A2: 20251201 | C2: 20250301 | D2: Primer trimestre 2025 | E2: =UPPER(TablaPeriodos[[#This Row],[Nombre]]) -> PRIMER TRIMESTRE 2025
A3: 20260301 | C3: 20250601 | D3: Segundo trimestre 2025 | E3: =UPPER(TablaPeriodos[[#This Row],[Nombre]]) -> SEGUNDO TRIMESTRE 2025
A4: 20260601 | C4: 20250901 | D4: Tercer trimestre 2025 | E4: =UPPER(TablaPeriodos[[#This Row],[Nombre]]) -> TERCER TRIMESTRE 2025
C5: 20251201 | D5: Cuarto trimestre 2025 | E5: =UPPER(TablaPeriodos[[#This Row],[Nombre]]) -> CUARTO TRIMESTRE 2025
C6: 20260301 | D6: Primer trimestre 2026 | E6: =UPPER(TablaPeriodos[[#This Row],[Nombre]]) -> PRIMER TRIMESTRE 2026
C7: 20260601 | D7: Segundo trimestre 2026 | E7: =UPPER(TablaPeriodos[[#This Row],[Nombre]]) -> SEGUNDO TRIMESTRE 2026
C8: 20260901 | D8: Tercer trimestre 2026 | E8: =UPPER(TablaPeriodos[[#This Row],[Nombre]]) -> TERCER TRIMESTRE 2026
C9: 20261201 | D9: Cuarto trimestre 2026 | E9: =UPPER(TablaPeriodos[[#This Row],[Nombre]]) -> CUARTO TRIMESTRE 2026
C10: 20270301 | D10: Primer trimestre 2027 | E10: =UPPER(TablaPeriodos[[#This Row],[Nombre]]) -> PRIMER TRIMESTRE 2027
C11: 20270601 | D11: Segundo trimestre 2027 | E11: =UPPER(TablaPeriodos[[#This Row],[Nombre]]) -> SEGUNDO TRIMESTRE 2027
C12: 20270901 | D12: Tercer trimestre 2027 | E12: =UPPER(TablaPeriodos[[#This Row],[Nombre]]) -> TERCER TRIMESTRE 2027
C13: 20271201 | D13: Cuarto trimestre 2027 | E13: =UPPER(TablaPeriodos[[#This Row],[Nombre]]) -> CUARTO TRIMESTRE 2027

Sheet Bono_1
A1: Código Programa presupuestal | B1: Programa Presupuestal | C1: Programación Financiera | D1: Obligaciones | E1: Mínimo | F1: Máximo | G1: Razón (Mínimo/Máximo) | H1: Ponderación (w) | I1: Aporte
A2: 2201 | B2: Calidad, cobertura y fortalecimiento de la educación inicial, prescolar, básica y media | C2: =SUMIFS(PPI_cuerpo_colegiado[Programación Financiera],PPI_cuerpo_colegiado[Código Programa presupuestal],Tabla15[[#This Row],[Código Programa presupuestal]],PPI_cuerpo_colegiado[Vigencia],LEFT('Reporte'!$B$1,4)) -> 7.2983306e+11 | D2: =SUMIFS(CUIPO_datos_abiertos[OBLIGACIONES],CUIPO_datos_abiertos[COD_PROGAMA_MGA],Tabla15[[#This Row],[Código Programa presupuestal]],CUIPO_datos_abiertos[PERIODO],'Reporte'!$B$1) -> 381728805073 | E2: =MIN(Tabla15[[#This Row],[Programación Financiera]:[Obligaciones]]) -> 381728805073 | F2: =MAX(Tabla15[[#This Row],[Programación Financiera]:[Obligaciones]]) -> 7.2983306e+11 | G2: =IFERROR(Tabla15[[#This Row],[Mínimo]]/Tabla15[[#This Row],[Máximo]],0) -> 0.52303578 | H2: =IF(Tabla15[[#This Row],[Razón (Mínimo/Máximo)]]>=0.5,Tabla15[[#This Row],[Obligaciones]]/'Reporte'!$D$1,"") -> 0.59463324 | I2: =IF(ISNUMBER(Tabla15[[#This Row],[Ponderación (w)]]),Tabla15[[#This Row],[Razón (Mínimo/Máximo)]]*Tabla15[[#This Row],[Ponderación (w)]],"") -> 0.31101446
A3: 4599 | B3: Fortalecimiento a la gestión y dirección de la administración pública territorial | C3: =SUMIFS(PPI_cuerpo_colegiado[Programación Financiera],PPI_cuerpo_colegiado[Código Programa presupuestal],Tabla15[[#This Row],[Código Programa presupuestal]],PPI_cuerpo_colegiado[Vigencia],LEFT('Reporte'!$B$1,4)) -> 3.4582773e+10 | D3: =SUMIFS(CUIPO_datos_abiertos[OBLIGACIONES],CUIPO_datos_abiertos[COD_PROGAMA_MGA],Tabla15[[#This Row],[Código Programa presupuestal]],CUIPO_datos_abiertos[PERIODO],'Reporte'!$B$1) -> 23874162737 | E3: =MIN(Tabla15[[#This Row],[Programación Financiera]:[Obligaciones]]) -> 23874162737 | F3: =MAX(Tabla15[[#This Row],[Programación Financiera]:[Obligaciones]]) -> 3.4582773e+10 | G3: =IFERROR(Tabla15[[#This Row],[Mínimo]]/Tabla15[[#This Row],[Máximo]],0) -> 0.69034841 | H3: =IF(Tabla15[[#This Row],[Razón (Mínimo/Máximo)]]>=0.5,Tabla15[[#This Row],[Obligaciones]]/'Reporte'!$D$1,"") -> 0.037189676 | I3: =IF(ISNUMBER(Tabla15[[#This Row],[Ponderación (w)]]),Tabla15[[#This Row],[Razón (Mínimo/Máximo)]]*Tabla15[[#This Row],[Ponderación (w)]],"") -> 0.025673834
A4: 3502 | B4: Productividad y competitividad de las empresas colombianas | C4: =SUMIFS(PPI_cuerpo_colegiado[Programación Financiera],PPI_cuerpo_colegiado[Código Programa presupuestal],Tabla15[[#This Row],[Código Programa presupuestal]],PPI_cuerpo_colegiado[Vigencia],LEFT('Reporte'!$B$1,4)) -> 27942000000 | D4: =SUMIFS(CUIPO_datos_abiertos[OBLIGACIONES],CUIPO_datos_abiertos[COD_PROGAMA_MGA],Tabla15[[#This Row],[Código Programa presupuestal]],CUIPO_datos_abiertos[PERIODO],'Reporte'!$B$1) -> 2448642029 | E4: =MIN(Tabla15[[#This Row],[Programación Financiera]:[Obligaciones]]) -> 2448642029 | F4: =MAX(Tabla15[[#This Row],[Programación Financiera]:[Obligaciones]]) -> 27942000000 | G4: =IFERROR(Tabla15[[#This Row],[Mínimo]]/Tabla15[[#This Row],[Máximo]],0) -> 0.087633027 | H4: =IF(Tabla15[[#This Row],[Razón (Mínimo/Máximo)]]>=0.5,Tabla15[[#This Row],[Obligaciones]]/'Reporte'!$D$1,"") | I4: =IF(ISNUMBER(Tabla15[[#This Row],[Ponderación (w)]]),Tabla15[[#This Row],[Razón (Mínimo/Máximo)]]*Tabla15[[#This Row],[Ponderación (w)]],"")
A5: 4301 | B5: Fomento a la recreación, la actividad física y el deporte para desarrollar entornos de convivencia y paz | C5: =SUMIFS(PPI_cuerpo_colegiado[Programación Financiera],PPI_cuerpo_colegiado[Código Programa presupuestal],Tabla15[[#This Row],[Código Programa presupuestal]],PPI_cuerpo_colegiado[Vigencia],LEFT('Reporte'!$B$1,4)) -> 5760125000 | D5: =SUMIFS(CUIPO_datos_abiertos[OBLIGACIONES],CUIPO_datos_abiertos[COD_PROGAMA_MGA],Tabla15[[#This Row],[Código Programa presupuestal]],CUIPO_datos_abiertos[PERIODO],'Reporte'!$B$1) -> 6733146035 | E5: =MIN(Tabla15[[#This Row],[Programación Financiera]:[Obligaciones]]) -> 5760125000 | F5: =MAX(Tabla15[[#This Row],[Programación Financiera]:[Obligaciones]]) -> 6733146035 | G5: =IFERROR(Tabla15[[#This Row],[Mínimo]]/Tabla15[[#This Row],[Máximo]],0) -> 0.85548791 | H5: =IF(Tabla15[[#This Row],[Razón (Mínimo/Máximo)]]>=0.5,Tabla15[[#This Row],[Obligaciones]]/'Reporte'!$D$1,"") -> 0.010488473 | I5: =IF(ISNUMBER(Tabla15[[#This Row],[Ponderación (w)]]),Tabla15[[#This Row],[Razón (Mínimo/Máximo)]]*Tabla15[[#This Row],[Ponderación (w)]],"") -> 0.0089727622
A6: 1905 | B6: Salud pública | C6: =SUMIFS(PPI_cuerpo_colegiado[Programación Financiera],PPI_cuerpo_colegiado[Código Programa presupuestal],Tabla15[[#This Row],[Código Programa presupuestal]],PPI_cuerpo_colegiado[Vigencia],LEFT('Reporte'!$B$1,4)) -> 7.4058745e+09 | D6: =SUMIFS(CUIPO_datos_abiertos[OBLIGACIONES],CUIPO_datos_abiertos[COD_PROGAMA_MGA],Tabla15[[#This Row],[Código Programa presupuestal]],CUIPO_datos_abiertos[PERIODO],'Reporte'!$B$1) -> 1844794471 | E6: =MIN(Tabla15[[#This Row],[Programación Financiera]:[Obligaciones]]) -> 1844794471 | F6: =MAX(Tabla15[[#This Row],[Programación Financiera]:[Obligaciones]]) -> 7.4058745e+09 | G6: =IFERROR(Tabla15[[#This Row],[Mínimo]]/Tabla15[[#This Row],[Máximo]],0) -> 0.2490988 | H6: =IF(Tabla15[[#This Row],[Razón (Mínimo/Máximo)]]>=0.5,Tabla15[[#This Row],[Obligaciones]]/'Reporte'!$D$1,"") | I6: =IF(ISNUMBER(Tabla15[[#This Row],[Ponderación (w)]]),Tabla15[[#This Row],[Razón (Mínimo/Máximo)]]*Tabla15[[#This Row],[Ponderación (w)]],"")
A7: 4101 | B7: Atención, asistencia y reparación integral a las víctimas | C7: =SUMIFS(PPI_cuerpo_colegiado[Programación Financiera],PPI_cuerpo_colegiado[Código Programa presupuestal],Tabla15[[#This Row],[Código Programa presupuestal]],PPI_cuerpo_colegiado[Vigencia],LEFT('Reporte'!$B$1,4)) -> 718000000 | D7: =SUMIFS(CUIPO_datos_abiertos[OBLIGACIONES],CUIPO_datos_abiertos[COD_PROGAMA_MGA],Tabla15[[#This Row],[Código Programa presupuestal]],CUIPO_datos_abiertos[PERIODO],'Reporte'!$B$1) -> 80459466 | E7: =MIN(Tabla15[[#This Row],[Programación Financiera]:[Obligaciones]]) -> 80459466 | F7: =MAX(Tabla15[[#This Row],[Programación Financiera]:[Obligaciones]]) -> 718000000 | G7: =IFERROR(Tabla15[[#This Row],[Mínimo]]/Tabla15[[#This Row],[Máximo]],0) -> 0.11206054 | H7: =IF(Tabla15[[#This Row],[Razón (Mínimo/Máximo)]]>=0.5,Tabla15[[#This Row],[Obligaciones]]/'Reporte'!$D$1,"") | I7: =IF(ISNUMBER(Tabla15[[#This Row],[Ponderación (w)]]),Tabla15[[#This Row],[Razón (Mínimo/Máximo)]]*Tabla15[[#This Row],[Ponderación (w)]],"")
A8: 0401 | B8: Levantamiento y actualización de información estadística de calidad | C8: =SUMIFS(PPI_cuerpo_colegiado[Programación Financiera],PPI_cuerpo_colegiado[Código Programa presupuestal],Tabla15[[#This Row],[Código Programa presupuestal]],PPI_cuerpo_colegiado[Vigencia],LEFT('Reporte'!$B$1,4)) -> 300000000 | D8: =SUMIFS(CUIPO_datos_abiertos[OBLIGACIONES],CUIPO_datos_abiertos[COD_PROGAMA_MGA],Tabla15[[#This Row],[Código Programa presupuestal]],CUIPO_datos_abiertos[PERIODO],'Reporte'!$B$1) -> 164000000 | E8: =MIN(Tabla15[[#This Row],[Programación Financiera]:[Obligaciones]]) -> 164000000 | F8: =MAX(Tabla15[[#This Row],[Programación Financiera]:[Obligaciones]]) -> 300000000 | G8: =IFERROR(Tabla15[[#This Row],[Mínimo]]/Tabla15[[#This Row],[Máximo]],0) -> 0.54666667 | H8: =IF(Tabla15[[#This Row],[Razón (Mínimo/Máximo)]]>=0.5,Tabla15[[#This Row],[Obligaciones]]/'Reporte'!$D$1,"") -> 0.00025546893 | I8: =IF(ISNUMBER(Tabla15[[#This Row],[Ponderación (w)]]),Tabla15[[#This Row],[Razón (Mínimo/Máximo)]]*Tabla15[[#This Row],[Ponderación (w)]],"") -> 0.00013965635
A9: 2102 | B9: Consolidación productiva del sector de energía eléctrica | C9: =SUMIFS(PPI_cuerpo_colegiado[Programación Financiera],PPI_cuerpo_colegiado[Código Programa presupuestal],Tabla15[[#This Row],[Código Programa presupuestal]],PPI_cuerpo_colegiado[Vigencia],LEFT('Reporte'!$B$1,4)) -> 29696000000 | D9: =SUMIFS(CUIPO_datos_abiertos[OBLIGACIONES],CUIPO_datos_abiertos[COD_PROGAMA_MGA],Tabla15[[#This Row],[Código Programa presupuestal]],CUIPO_datos_abiertos[PERIODO],'Reporte'!$B$1) -> 3120331456 | E9: =MIN(Tabla15[[#This Row],[Programación Financiera]:[Obligaciones]]) -> 3120331456 | F9: =MAX(Tabla15[[#This Row],[Programación Financiera]:[Obligaciones]]) -> 29696000000 | G9: =IFERROR(Tabla15[[#This Row],[Mínimo]]/Tabla15[[#This Row],[Máximo]],0) -> 0.10507582 | H9: =IF(Tabla15[[#This Row],[Razón (Mínimo/Máximo)]]>=0.5,Tabla15[[#This Row],[Obligaciones]]/'Reporte'!$D$1,"") | I9: =IF(ISNUMBER(Tabla15[[#This Row],[Ponderación (w)]]),Tabla15[[#This Row],[Razón (Mínimo/Máximo)]]*Tabla15[[#This Row],[Ponderación (w)]],"")
A10: 1906 | B10: Aseguramiento y prestación integral de servicios de salud | C10: =SUMIFS(PPI_cuerpo_colegiado[Programación Financiera],PPI_cuerpo_colegiado[Código Programa presupuestal],Tabla15[[#This Row],[Código Programa presupuestal]],PPI_cuerpo_colegiado[Vigencia],LEFT('Reporte'!$B$1,4)) -> 9.9032769e+10 | D10: =SUMIFS(CUIPO_datos_abiertos[OBLIGACIONES],CUIPO_datos_abiertos[COD_PROGAMA_MGA],Tabla15[[#This Row],[Código Programa presupuestal]],CUIPO_datos_abiertos[PERIODO],'Reporte'!$B$1) -> 31066371199 | E10: =MIN(Tabla15[[#This Row],[Programación Financiera]:[Obligaciones]]) -> 31066371199 | F10: =MAX(Tabla15[[#This Row],[Programación Financiera]:[Obligaciones]]) -> 9.9032769e+10 | G10: =IFERROR(Tabla15[[#This Row],[Mínimo]]/Tabla15[[#This Row],[Máximo]],0) -> 0.31369789 | H10: =IF(Tabla15[[#This Row],[Razón (Mínimo/Máximo)]]>=0.5,Tabla15[[#This Row],[Obligaciones]]/'Reporte'!$D$1,"") | I10: =IF(ISNUMBER(Tabla15[[#This Row],[Ponderación (w)]]),Tabla15[[#This Row],[Razón (Mínimo/Máximo)]]*Tabla15[[#This Row],[Ponderación (w)]],"")
A11: 4003 | B11: Acceso de la población a los servicios de agua potable y saneamiento básico | C11: =SUMIFS(PPI_cuerpo_colegiado[Programación Financiera],PPI_cuerpo_colegiado[Código Programa presupuestal],Tabla15[[#This Row],[Código Programa presupuestal]],PPI_cuerpo_colegiado[Vigencia],LEFT('Reporte'!$B$1,4)) -> 1.4796347e+10 | D11: =SUMIFS(CUIPO_datos_abiertos[OBLIGACIONES],CUIPO_datos_abiertos[COD_PROGAMA_MGA],Tabla15[[#This Row],[Código Programa presupuestal]],CUIPO_datos_abiertos[PERIODO],'Reporte'!$B$1) -> 2185764639 | E11: =MIN(Tabla15[[#This Row],[Programación Financiera]:[Obligaciones]]) -> 2185764639 | F11: =MAX(Tabla15[[#This Row],[Programación Financiera]:[Obligaciones]]) -> 1.4796347e+10 | G11: =IFERROR(Tabla15[[#This Row],[Mínimo]]/Tabla15[[#This Row],[Máximo]],0) -> 0.14772326 | H11: =IF(Tabla15[[#This Row],[Razón (Mínimo/Máximo)]]>=0.5,Tabla15[[#This Row],[Obligaciones]]/'Reporte'!$D$1,"") | I11: =IF(ISNUMBER(Tabla15[[#This Row],[Ponderación (w)]]),Tabla15[[#This Row],[Razón (Mínimo/Máximo)]]*Tabla15[[#This Row],[Ponderación (w)]],"")
A12: 2402 | B12: Infraestructura red vial regional | C12: =SUMIFS(PPI_cuerpo_colegiado[Programación Financiera],PPI_cuerpo_colegiado[Código Programa presupuestal],Tabla15[[#This Row],[Código Programa presupuestal]],PPI_cuerpo_colegiado[Vigencia],LEFT('Reporte'!$B$1,4)) -> 23940000000 | D12: =SUMIFS(CUIPO_datos_abiertos[OBLIGACIONES],CUIPO_datos_abiertos[COD_PROGAMA_MGA],Tabla15[[#This Row],[Código Programa presupuestal]],CUIPO_datos_abiertos[PERIODO],'Reporte'!$B$1) -> 25640135713 | E12: =MIN(Tabla15[[#This Row],[Programación Financiera]:[Obligaciones]]) -> 23940000000 | F12: =MAX(Tabla15[[#This Row],[Programación Financiera]:[Obligaciones]]) -> 25640135713 | G12: =IFERROR(Tabla15[[#This Row],[Mínimo]]/Tabla15[[#This Row],[Máximo]],0) -> 0.93369241 | H12: =IF(Tabla15[[#This Row],[Razón (Mínimo/Máximo)]]>=0.5,Tabla15[[#This Row],[Obligaciones]]/'Reporte'!$D$1,"") -> 0.039940599 | I12: =IF(ISNUMBER(Tabla15[[#This Row],[Ponderación (w)]]),Tabla15[[#This Row],[Razón (Mínimo/Máximo)]]*Tabla15[[#This Row],[Ponderación (w)]],"") -> 0.037292234
A13: 4501 | B13: Fortalecimiento de la convivencia y la seguridad ciudadana | C13: =SUMIFS(PPI_cuerpo_colegiado[Programación Financiera],PPI_cuerpo_colegiado[Código Programa presupuestal],Tabla15[[#This Row],[Código Programa presupuestal]],PPI_cuerpo_colegiado[Vigencia],LEFT('Reporte'!$B$1,4)) -> 5661500000 | D13: =SUMIFS(CUIPO_datos_abiertos[OBLIGACIONES],CUIPO_datos_abiertos[COD_PROGAMA_MGA],Tabla15[[#This Row],[Código Programa presupuestal]],CUIPO_datos_abiertos[PERIODO],'Reporte'!$B$1) -> 7825133773 | E13: =MIN(Tabla15[[#This Row],[Programación Financiera]:[Obligaciones]]) -> 5661500000 | F13: =MAX(Tabla15[[#This Row],[Programación Financiera]:[Obligaciones]]) -> 7825133773 | G13: =IFERROR(Tabla15[[#This Row],[Mínimo]]/Tabla15[[#This Row],[Máximo]],0) -> 0.72350201 | H13: =IF(Tabla15[[#This Row],[Razón (Mínimo/Máximo)]]>=0.5,Tabla15[[#This Row],[Obligaciones]]/'Reporte'!$D$1,"") -> 0.012189504 | I13: =IF(ISNUMBER(Tabla15[[#This Row],[Ponderación (w)]]),Tabla15[[#This Row],[Razón (Mínimo/Máximo)]]*Tabla15[[#This Row],[Ponderación (w)]],"") -> 0.0088191303
... A55: 4002 | B55: Ordenamiento territorial y desarrollo urbano | C55: =SUMIFS(PPI_cuerpo_colegiado[Programación Financiera],PPI_cuerpo_colegiado[Código Programa presupuestal],Tabla15[[#This Row],[Código Programa presupuestal]],PPI_cuerpo_colegiado[Vigencia],LEFT('Reporte'!$B$1,4)) -> 0 | D55: =SUMIFS(CUIPO_datos_abiertos[OBLIGACIONES],CUIPO_datos_abiertos[COD_PROGAMA_MGA],Tabla15[[#This Row],[Código Programa presupuestal]],CUIPO_datos_abiertos[PERIODO],'Reporte'!$B$1) -> 0 | E55: =MIN(Tabla15[[#This Row],[Programación Financiera]:[Obligaciones]]) -> 0 | F55: =MAX(Tabla15[[#This Row],[Programación Financiera]:[Obligaciones]]) -> 0 | G55: =IFERROR(Tabla15[[#This Row],[Mínimo]]/Tabla15[[#This Row],[Máximo]],0) -> 0 | H55: =IF(Tabla15[[#This Row],[Razón (Mínimo/Máximo)]]>=0.5,Tabla15[[#This Row],[Obligaciones]]/'Reporte'!$D$1,"") | I55: =IF(ISNUMBER(Tabla15[[#This Row],[Ponderación (w)]]),Tabla15[[#This Row],[Razón (Mínimo/Máximo)]]*Tabla15[[#This Row],[Ponderación (w)]],"")

Sheet Bono_2
B1: Se contabilizan todos los productos de PI cargado en SISPT, independiente de si estan programados o no en la vigencia
B2: Cuipo obligaciones diferentes a cero
B3: Piip productos con reporte de ejecución en la vigencia
B4: Cód. Prod. | C4: Está en SISPT | D4: Está en PIIP | E4: Esta en CUIPO | F4: Aplicabilidad bono 4 | V4: Región | W4: Conteo
B5: {=_xlfn.LET(_xlpm.productos_cuipo,_xlfn.UNIQUE(_xlfn._xlws.FILTER(CUIPO_datos_abiertos[COD_PROGRAMATICO_MGA],(CUIPO_datos_abiertos[ES_PRODUCTO_VALIDO]="VALIDO")*(CUIPO_datos_abiertos[PERIODO]='Reporte'!$B$1))),_xlpm.productos_pisistpt,_xlfn.UNIQUE(PI_SISPT_ProgramacionFisica[Cód. Prod.]),_xlpm.productos_piip,_xlfn.UNIQUE(_xlfn._xlws.FILTER(EjecucionPIIP[CodigoProducto],(EjecucionPIIP[Vigencia]=LEFT('Reporte'!$B$1,4))*(EjecucionPIIP[AvanceEjecutado]<>0))),_xlpm.apilado,_xlfn.UNIQUE(_xlfn.VSTACK(_xlpm.productos_cuipo,_xlpm.productos_piip,_xlpm.productos_pisistpt)),_xlpm.apilado)} -> 1903001 | C5: {=IF(ISNUMBER(VALUE(_xlfn.UNIQUE(_xlfn._xlws.FILTER(PI_SISPT_ProgramacionFisica[Cód. Prod.],PI_SISPT_ProgramacionFisica[Cód. Prod.]=Bono_2!B5,"")))),1,"")} | D5: {=IF(ISNUMBER(VALUE(_xlfn.UNIQUE(_xlfn._xlws.FILTER(EjecucionPIIP[CodigoProducto],(EjecucionPIIP[CodigoProducto]=Bono_2!B5)*(EjecucionPIIP[Vigencia]=LEFT('Reporte'!$B$1,4))*(EjecucionPIIP[AvanceEjecutado]<>0),"")))),1,"")} | E5: {=IF(ISNUMBER(VALUE(_xlfn.UNIQUE(_xlfn._xlws.FILTER(CUIPO_datos_abiertos[COD_PROGRAMATICO_MGA],(CUIPO_datos_abiertos[COD_PROGRAMATICO_MGA]=Bono_2!B5)*(CUIPO_datos_abiertos[PERIODO]='Reporte'!$B$1)*(CUIPO_datos_abiertos[OBLIGACIONES]<>0),"")))),1,"")} -> 1 | F5: =IF(SUM(C5:E5)=3,"Aplica","") | V5: Solo SISPT | W5: {=SUMPRODUCT(($C$5:$C$322=1)*($D$5:$D$322<>1)*($E$5:$E$322<>1))} -> 234
B6: 4599023 | C6: {=IF(ISNUMBER(VALUE(_xlfn.UNIQUE(_xlfn._xlws.FILTER(PI_SISPT_ProgramacionFisica[Cód. Prod.],PI_SISPT_ProgramacionFisica[Cód. Prod.]=Bono_2!B6,"")))),1,"")} -> 1 | D6: {=IF(ISNUMBER(VALUE(_xlfn.UNIQUE(_xlfn._xlws.FILTER(EjecucionPIIP[CodigoProducto],(EjecucionPIIP[CodigoProducto]=Bono_2!B6)*(EjecucionPIIP[Vigencia]=LEFT('Reporte'!$B$1,4))*(EjecucionPIIP[AvanceEjecutado]<>0),"")))),1,"")} -> 1 | E6: {=IF(ISNUMBER(VALUE(_xlfn.UNIQUE(_xlfn._xlws.FILTER(CUIPO_datos_abiertos[COD_PROGRAMATICO_MGA],(CUIPO_datos_abiertos[COD_PROGRAMATICO_MGA]=Bono_2!B6)*(CUIPO_datos_abiertos[PERIODO]='Reporte'!$B$1)*(CUIPO_datos_abiertos[OBLIGACIONES]<>0),"")))),1,"")} -> 1 | F6: =IF(SUM(C6:E6)=3,"Aplica","") -> Aplica | V6: Solo PIIP | W6: {=SUMPRODUCT(($C$5:$C$322<>1)*($D$5:$D$322=1)*($E$5:$E$322<>1))} -> 3
B7: 4104020 | C7: {=IF(ISNUMBER(VALUE(_xlfn.UNIQUE(_xlfn._xlws.FILTER(PI_SISPT_ProgramacionFisica[Cód. Prod.],PI_SISPT_ProgramacionFisica[Cód. Prod.]=Bono_2!B7,"")))),1,"")} -> 1 | D7: {=IF(ISNUMBER(VALUE(_xlfn.UNIQUE(_xlfn._xlws.FILTER(EjecucionPIIP[CodigoProducto],(EjecucionPIIP[CodigoProducto]=Bono_2!B7)*(EjecucionPIIP[Vigencia]=LEFT('Reporte'!$B$1,4))*(EjecucionPIIP[AvanceEjecutado]<>0),"")))),1,"")} -> 1 | E7: {=IF(ISNUMBER(VALUE(_xlfn.UNIQUE(_xlfn._xlws.FILTER(CUIPO_datos_abiertos[COD_PROGRAMATICO_MGA],(CUIPO_datos_abiertos[COD_PROGRAMATICO_MGA]=Bono_2!B7)*(CUIPO_datos_abiertos[PERIODO]='Reporte'!$B$1)*(CUIPO_datos_abiertos[OBLIGACIONES]<>0),"")))),1,"")} -> 1 | F7: =IF(SUM(C7:E7)=3,"Aplica","") -> Aplica | V7: Solo CUIPO | W7: {=SUMPRODUCT(($C$5:$C$322<>1)*($D$5:$D$322<>1)*($E$5:$E$322=1))} -> 24
B8: 4599002 | C8: {=IF(ISNUMBER(VALUE(_xlfn.UNIQUE(_xlfn._xlws.FILTER(PI_SISPT_ProgramacionFisica[Cód. Prod.],PI_SISPT_ProgramacionFisica[Cód. Prod.]=Bono_2!B8,"")))),1,"")} -> 1 | D8: {=IF(ISNUMBER(VALUE(_xlfn.UNIQUE(_xlfn._xlws.FILTER(EjecucionPIIP[CodigoProducto],(EjecucionPIIP[CodigoProducto]=Bono_2!B8)*(EjecucionPIIP[Vigencia]=LEFT('Reporte'!$B$1,4))*(EjecucionPIIP[AvanceEjecutado]<>0),"")))),1,"")} -> 1 | E8: {=IF(ISNUMBER(VALUE(_xlfn.UNIQUE(_xlfn._xlws.FILTER(CUIPO_datos_abiertos[COD_PROGRAMATICO_MGA],(CUIPO_datos_abiertos[COD_PROGRAMATICO_MGA]=Bono_2!B8)*(CUIPO_datos_abiertos[PERIODO]='Reporte'!$B$1)*(CUIPO_datos_abiertos[OBLIGACIONES]<>0),"")))),1,"")} -> 1 | F8: =IF(SUM(C8:E8)=3,"Aplica","") -> Aplica | V8: SISPT ∩ PIIP (sin CUIPO) | W8: {=SUMPRODUCT(($C$5:$C$322=1)*($D$5:$D$322=1)*($E$5:$E$322<>1))} -> 10
B9: 1906039 | C9: {=IF(ISNUMBER(VALUE(_xlfn.UNIQUE(_xlfn._xlws.FILTER(PI_SISPT_ProgramacionFisica[Cód. Prod.],PI_SISPT_ProgramacionFisica[Cód. Prod.]=Bono_2!B9,"")))),1,"")} | D9: {=IF(ISNUMBER(VALUE(_xlfn.UNIQUE(_xlfn._xlws.FILTER(EjecucionPIIP[CodigoProducto],(EjecucionPIIP[CodigoProducto]=Bono_2!B9)*(EjecucionPIIP[Vigencia]=LEFT('Reporte'!$B$1,4))*(EjecucionPIIP[AvanceEjecutado]<>0),"")))),1,"")} | E9: {=IF(ISNUMBER(VALUE(_xlfn.UNIQUE(_xlfn._xlws.FILTER(CUIPO_datos_abiertos[COD_PROGRAMATICO_MGA],(CUIPO_datos_abiertos[COD_PROGRAMATICO_MGA]=Bono_2!B9)*(CUIPO_datos_abiertos[PERIODO]='Reporte'!$B$1)*(CUIPO_datos_abiertos[OBLIGACIONES]<>0),"")))),1,"")} -> 1 | F9: =IF(SUM(C9:E9)=3,"Aplica","") | V9: SISPT ∩ CUIPO (sin PIIP) | W9: {=SUMPRODUCT(($C$5:$C$322=1)*($D$5:$D$322<>1)*($E$5:$E$322=1))} -> 23
B10: 2201071 | C10: {=IF(ISNUMBER(VALUE(_xlfn.UNIQUE(_xlfn._xlws.FILTER(PI_SISPT_ProgramacionFisica[Cód. Prod.],PI_SISPT_ProgramacionFisica[Cód. Prod.]=Bono_2!B10,"")))),1,"")} -> 1 | D10: {=IF(ISNUMBER(VALUE(_xlfn.UNIQUE(_xlfn._xlws.FILTER(EjecucionPIIP[CodigoProducto],(EjecucionPIIP[CodigoProducto]=Bono_2!B10)*(EjecucionPIIP[Vigencia]=LEFT('Reporte'!$B$1,4))*(EjecucionPIIP[AvanceEjecutado]<>0),"")))),1,"")} | E10: {=IF(ISNUMBER(VALUE(_xlfn.UNIQUE(_xlfn._xlws.FILTER(CUIPO_datos_abiertos[COD_PROGRAMATICO_MGA],(CUIPO_datos_abiertos[COD_PROGRAMATICO_MGA]=Bono_2!B10)*(CUIPO_datos_abiertos[PERIODO]='Reporte'!$B$1)*(CUIPO_datos_abiertos[OBLIGACIONES]<>0),"")))),1,"")} -> 1 | F10: =IF(SUM(C10:E10)=3,"Aplica","") | V10: PIIP ∩ CUIPO (sin SISPT) | W10: {=SUMPRODUCT(($C$5:$C$322<>1)*($D$5:$D$322=1)*($E$5:$E$322=1))} -> 0
B11: 4599025 | C11: {=IF(ISNUMBER(VALUE(_xlfn.UNIQUE(_xlfn._xlws.FILTER(PI_SISPT_ProgramacionFisica[Cód. Prod.],PI_SISPT_ProgramacionFisica[Cód. Prod.]=Bono_2!B11,"")))),1,"")} -> 1 | D11: {=IF(ISNUMBER(VALUE(_xlfn.UNIQUE(_xlfn._xlws.FILTER(EjecucionPIIP[CodigoProducto],(EjecucionPIIP[CodigoProducto]=Bono_2!B11)*(EjecucionPIIP[Vigencia]=LEFT('Reporte'!$B$1,4))*(EjecucionPIIP[AvanceEjecutado]<>0),"")))),1,"")} | E11: {=IF(ISNUMBER(VALUE(_xlfn.UNIQUE(_xlfn._xlws.FILTER(CUIPO_datos_abiertos[COD_PROGRAMATICO_MGA],(CUIPO_datos_abiertos[COD_PROGRAMATICO_MGA]=Bono_2!B11)*(CUIPO_datos_abiertos[PERIODO]='Reporte'!$B$1)*(CUIPO_datos_abiertos[OBLIGACIONES]<>0),"")))),1,"")} -> 1 | F11: =IF(SUM(C11:E11)=3,"Aplica","") | V11: Los tres | W11: {=SUMPRODUCT(($C$5:$C$322=1)*($D$5:$D$322=1)*($E$5:$E$322=1))} -> 19
B12: 1903035 | C12: {=IF(ISNUMBER(VALUE(_xlfn.UNIQUE(_xlfn._xlws.FILTER(PI_SISPT_ProgramacionFisica[Cód. Prod.],PI_SISPT_ProgramacionFisica[Cód. Prod.]=Bono_2!B12,"")))),1,"")} -> 1 | D12: {=IF(ISNUMBER(VALUE(_xlfn.UNIQUE(_xlfn._xlws.FILTER(EjecucionPIIP[CodigoProducto],(EjecucionPIIP[CodigoProducto]=Bono_2!B12)*(EjecucionPIIP[Vigencia]=LEFT('Reporte'!$B$1,4))*(EjecucionPIIP[AvanceEjecutado]<>0),"")))),1,"")} -> 1 | E12: {=IF(ISNUMBER(VALUE(_xlfn.UNIQUE(_xlfn._xlws.FILTER(CUIPO_datos_abiertos[COD_PROGRAMATICO_MGA],(CUIPO_datos_abiertos[COD_PROGRAMATICO_MGA]=Bono_2!B12)*(CUIPO_datos_abiertos[PERIODO]='Reporte'!$B$1)*(CUIPO_datos_abiertos[OBLIGACIONES]<>0),"")))),1,"")} -> 1 | F12: =IF(SUM(C12:E12)=3,"Aplica","") -> Aplica | V12: Total productos únicos | W12: {=SUMPRODUCT(($B$5:$B$322<>"")*1)} -> 313
B13: 4502024 | C13: {=IF(ISNUMBER(VALUE(_xlfn.UNIQUE(_xlfn._xlws.FILTER(PI_SISPT_ProgramacionFisica[Cód. Prod.],PI_SISPT_ProgramacionFisica[Cód. Prod.]=Bono_2!B13,"")))),1,"")} -> 1 | D13: {=IF(ISNUMBER(VALUE(_xlfn.UNIQUE(_xlfn._xlws.FILTER(EjecucionPIIP[CodigoProducto],(EjecucionPIIP[CodigoProducto]=Bono_2!B13)*(EjecucionPIIP[Vigencia]=LEFT('Reporte'!$B$1,4))*(EjecucionPIIP[AvanceEjecutado]<>0),"")))),1,"")} -> 1 | E13: {=IF(ISNUMBER(VALUE(_xlfn.UNIQUE(_xlfn._xlws.FILTER(CUIPO_datos_abiertos[COD_PROGRAMATICO_MGA],(CUIPO_datos_abiertos[COD_PROGRAMATICO_MGA]=Bono_2!B13)*(CUIPO_datos_abiertos[PERIODO]='Reporte'!$B$1)*(CUIPO_datos_abiertos[OBLIGACIONES]<>0),"")))),1,"")} -> 1 | F13: =IF(SUM(C13:E13)=3,"Aplica","") -> Aplica | V13: Suma regiones (control) | W13: =SUM(W5:W11) -> 313
B14: 4502030 | C14: {=IF(ISNUMBER(VALUE(_xlfn.UNIQUE(_xlfn._xlws.FILTER(PI_SISPT_ProgramacionFisica[Cód. Prod.],PI_SISPT_ProgramacionFisica[Cód. Prod.]=Bono_2!B14,"")))),1,"")} | D14: {=IF(ISNUMBER(VALUE(_xlfn.UNIQUE(_xlfn._xlws.FILTER(EjecucionPIIP[CodigoProducto],(EjecucionPIIP[CodigoProducto]=Bono_2!B14)*(EjecucionPIIP[Vigencia]=LEFT('Reporte'!$B$1,4))*(EjecucionPIIP[AvanceEjecutado]<>0),"")))),1,"")} | E14: {=IF(ISNUMBER(VALUE(_xlfn.UNIQUE(_xlfn._xlws.FILTER(CUIPO_datos_abiertos[COD_PROGRAMATICO_MGA],(CUIPO_datos_abiertos[COD_PROGRAMATICO_MGA]=Bono_2!B14)*(CUIPO_datos_abiertos[PERIODO]='Reporte'!$B$1)*(CUIPO_datos_abiertos[OBLIGACIONES]<>0),"")))),1,"")} -> 1 | F14: =IF(SUM(C14:E14)=3,"Aplica","") | V14: Total SISPT | W14: =COUNTIF($C$5:$C$322,1) -> 286
B15: 4503023 | C15: {=IF(ISNUMBER(VALUE(_xlfn.UNIQUE(_xlfn._xlws.FILTER(PI_SISPT_ProgramacionFisica[Cód. Prod.],PI_SISPT_ProgramacionFisica[Cód. Prod.]=Bono_2!B15,"")))),1,"")} -> 1 | D15: {=IF(ISNUMBER(VALUE(_xlfn.UNIQUE(_xlfn._xlws.FILTER(EjecucionPIIP[CodigoProducto],(EjecucionPIIP[CodigoProducto]=Bono_2!B15)*(EjecucionPIIP[Vigencia]=LEFT('Reporte'!$B$1,4))*(EjecucionPIIP[AvanceEjecutado]<>0),"")))),1,"")} | E15: {=IF(ISNUMBER(VALUE(_xlfn.UNIQUE(_xlfn._xlws.FILTER(CUIPO_datos_abiertos[COD_PROGRAMATICO_MGA],(CUIPO_datos_abiertos[COD_PROGRAMATICO_MGA]=Bono_2!B15)*(CUIPO_datos_abiertos[PERIODO]='Reporte'!$B$1)*(CUIPO_datos_abiertos[OBLIGACIONES]<>0),"")))),1,"")} -> 1 | F15: =IF(SUM(C15:E15)=3,"Aplica","") | H15: Diagrama de venn | V15: Total PIIP | W15: =COUNTIF($D$5:$D$322,1) -> 32
B16: 1905050 | C16: {=IF(ISNUMBER(VALUE(_xlfn.UNIQUE(_xlfn._xlws.FILTER(PI_SISPT_ProgramacionFisica[Cód. Prod.],PI_SISPT_ProgramacionFisica[Cód. Prod.]=Bono_2!B16,"")))),1,"")} -> 1 | D16: {=IF(ISNUMBER(VALUE(_xlfn.UNIQUE(_xlfn._xlws.FILTER(EjecucionPIIP[CodigoProducto],(EjecucionPIIP[CodigoProducto]=Bono_2!B16)*(EjecucionPIIP[Vigencia]=LEFT('Reporte'!$B$1,4))*(EjecucionPIIP[AvanceEjecutado]<>0),"")))),1,"")} -> 1 | E16: {=IF(ISNUMBER(VALUE(_xlfn.UNIQUE(_xlfn._xlws.FILTER(CUIPO_datos_abiertos[COD_PROGRAMATICO_MGA],(CUIPO_datos_abiertos[COD_PROGRAMATICO_MGA]=Bono_2!B16)*(CUIPO_datos_abiertos[PERIODO]='Reporte'!$B$1)*(CUIPO_datos_abiertos[OBLIGACIONES]<>0),"")))),1,"")} -> 1 | F16: =IF(SUM(C16:E16)=3,"Aplica","") -> Aplica | V16: Total CUIPO | W16: =COUNTIF($E$5:$E$322,1) -> 66
B17: 4599003 | C17: {=IF(ISNUMBER(VALUE(_xlfn.UNIQUE(_xlfn._xlws.FILTER(PI_SISPT_ProgramacionFisica[Cód. Prod.],PI_SISPT_ProgramacionFisica[Cód. Prod.]=Bono_2!B17,"")))),1,"")} -> 1 | D17: {=IF(ISNUMBER(VALUE(_xlfn.UNIQUE(_xlfn._xlws.FILTER(EjecucionPIIP[CodigoProducto],(EjecucionPIIP[CodigoProducto]=Bono_2!B17)*(EjecucionPIIP[Vigencia]=LEFT('Reporte'!$B$1,4))*(EjecucionPIIP[AvanceEjecutado]<>0),"")))),1,"")} | E17: {=IF(ISNUMBER(VALUE(_xlfn.UNIQUE(_xlfn._xlws.FILTER(CUIPO_datos_abiertos[COD_PROGRAMATICO_MGA],(CUIPO_datos_abiertos[COD_PROGRAMATICO_MGA]=Bono_2!B17)*(CUIPO_datos_abiertos[PERIODO]='Reporte'!$B$1)*(CUIPO_datos_abiertos[OBLIGACIONES]<>0),"")))),1,"")} -> 1 | F17: =IF(SUM(C17:E17)=3,"Aplica","")
B18: 1901007 | C18: {=IF(ISNUMBER(VALUE(_xlfn.UNIQUE(_xlfn._xlws.FILTER(PI_SISPT_ProgramacionFisica[Cód. Prod.],PI_SISPT_ProgramacionFisica[Cód. Prod.]=Bono_2!B18,"")))),1,"")} | D18: {=IF(ISNUMBER(VALUE(_xlfn.UNIQUE(_xlfn._xlws.FILTER(EjecucionPIIP[CodigoProducto],(EjecucionPIIP[CodigoProducto]=Bono_2!B18)*(EjecucionPIIP[Vigencia]=LEFT('Reporte'!$B$1,4))*(EjecucionPIIP[AvanceEjecutado]<>0),"")))),1,"")} | E18: {=IF(ISNUMBER(VALUE(_xlfn.UNIQUE(_xlfn._xlws.FILTER(CUIPO_datos_abiertos[COD_PROGRAMATICO_MGA],(CUIPO_datos_abiertos[COD_PROGRAMATICO_MGA]=Bono_2!B18)*(CUIPO_datos_abiertos[PERIODO]='Reporte'!$B$1)*(CUIPO_datos_abiertos[OBLIGACIONES]<>0),"")))),1,"")} -> 1 | F18: =IF(SUM(C18:E18)=3,"Aplica","")
B19: 4301001 | C19: {=IF(ISNUMBER(VALUE(_xlfn.UNIQUE(_xlfn._xlws.FILTER(PI_SISPT_ProgramacionFisica[Cód. Prod.],PI_SISPT_ProgramacionFisica[Cód. Prod.]=Bono_2!B19,"")))),1,"")} -> 1 | D19: {=IF(ISNUMBER(VALUE(_xlfn.UNIQUE(_xlfn._xlws.FILTER(EjecucionPIIP[CodigoProducto],(EjecucionPIIP[CodigoProducto]=Bono_2!B19)*(EjecucionPIIP[Vigencia]=LEFT('Reporte'!$B$1,4))*(EjecucionPIIP[AvanceEjecutado]<>0),"")))),1,"")} -> 1 | E19: {=IF(ISNUMBER(VALUE(_xlfn.UNIQUE(_xlfn._xlws.FILTER(CUIPO_datos_abiertos[COD_PROGRAMATICO_MGA],(CUIPO_datos_abiertos[COD_PROGRAMATICO_MGA]=Bono_2!B19)*(CUIPO_datos_abiertos[PERIODO]='Reporte'!$B$1)*(CUIPO_datos_abiertos[OBLIGACIONES]<>0),"")))),1,"")} -> 1 | F19: =IF(SUM(C19:E19)=3,"Aplica","") -> Aplica
B20: 2201028 | C20: {=IF(ISNUMBER(VALUE(_xlfn.UNIQUE(_xlfn._xlws.FILTER(PI_SISPT_ProgramacionFisica[Cód. Prod.],PI_SISPT_ProgramacionFisica[Cód. Prod.]=Bono_2!B20,"")))),1,"")} -> 1 | D20: {=IF(ISNUMBER(VALUE(_xlfn.UNIQUE(_xlfn._xlws.FILTER(EjecucionPIIP[CodigoProducto],(EjecucionPIIP[CodigoProducto]=Bono_2!B20)*(EjecucionPIIP[Vigencia]=LEFT('Reporte'!$B$1,4))*(EjecucionPIIP[AvanceEjecutado]<>0),"")))),1,"")} -> 1 | E20: {=IF(ISNUMBER(VALUE(_xlfn.UNIQUE(_xlfn._xlws.FILTER(CUIPO_datos_abiertos[COD_PROGRAMATICO_MGA],(CUIPO_datos_abiertos[COD_PROGRAMATICO_MGA]=Bono_2!B20)*(CUIPO_datos_abiertos[PERIODO]='Reporte'!$B$1)*(CUIPO_datos_abiertos[OBLIGACIONES]<>0),"")))),1,"")} -> 1 | F20: =IF(SUM(C20:E20)=3,"Aplica","") -> Aplica | J20: SISPT | R20: PIIP
B21: 2402001 | C21: {=IF(ISNUMBER(VALUE(_xlfn.UNIQUE(_xlfn._xlws.FILTER(PI_SISPT_ProgramacionFisica[Cód. Prod.],PI_SISPT_ProgramacionFisica[Cód. Prod.]=Bono_2!B21,"")))),1,"")} | D21: {=IF(ISNUMBER(VALUE(_xlfn.UNIQUE(_xlfn._xlws.FILTER(EjecucionPIIP[CodigoProducto],(EjecucionPIIP[CodigoProducto]=Bono_2!B21)*(EjecucionPIIP[Vigencia]=LEFT('Reporte'!$B$1,4))*(EjecucionPIIP[AvanceEjecutado]<>0),"")))),1,"")} | E21: {=IF(ISNUMBER(VALUE(_xlfn.UNIQUE(_xlfn._xlws.FILTER(CUIPO_datos_abiertos[COD_PROGRAMATICO_MGA],(CUIPO_datos_abiertos[COD_PROGRAMATICO_MGA]=Bono_2!B21)*(CUIPO_datos_abiertos[PERIODO]='Reporte'!$B$1)*(CUIPO_datos_abiertos[OBLIGACIONES]<>0),"")))),1,"")} -> 1 | F21: =IF(SUM(C21:E21)=3,"Aplica","")
B22: 4501029 | C22: {=IF(ISNUMBER(VALUE(_xlfn.UNIQUE(_xlfn._xlws.FILTER(PI_SISPT_ProgramacionFisica[Cód. Prod.],PI_SISPT_ProgramacionFisica[Cód. Prod.]=Bono_2!B22,"")))),1,"")} -> 1 | D22: {=IF(ISNUMBER(VALUE(_xlfn.UNIQUE(_xlfn._xlws.FILTER(EjecucionPIIP[CodigoProducto],(EjecucionPIIP[CodigoProducto]=Bono_2!B22)*(EjecucionPIIP[Vigencia]=LEFT('Reporte'!$B$1,4))*(EjecucionPIIP[AvanceEjecutado]<>0),"")))),1,"")} -> 1 | E22: {=IF(ISNUMBER(VALUE(_xlfn.UNIQUE(_xlfn._xlws.FILTER(CUIPO_datos_abiertos[COD_PROGRAMATICO_MGA],(CUIPO_datos_abiertos[COD_PROGRAMATICO_MGA]=Bono_2!B22)*(CUIPO_datos_abiertos[PERIODO]='Reporte'!$B$1)*(CUIPO_datos_abiertos[OBLIGACIONES]<>0),"")))),1,"")} -> 1 | F22: =IF(SUM(C22:E22)=3,"Aplica","") -> Aplica | J22: =W5 -> 234 | N22: =W8 -> 10 | R22: =W6 -> 3
B23: 1903038 | C23: {=IF(ISNUMBER(VALUE(_xlfn.UNIQUE(_xlfn._xlws.FILTER(PI_SISPT_ProgramacionFisica[Cód. Prod.],PI_SISPT_ProgramacionFisica[Cód. Prod.]=Bono_2!B23,"")))),1,"")} | D23: {=IF(ISNUMBER(VALUE(_xlfn.UNIQUE(_xlfn._xlws.FILTER(EjecucionPIIP[CodigoProducto],(EjecucionPIIP[CodigoProducto]=Bono_2!B23)*(EjecucionPIIP[Vigencia]=LEFT('Reporte'!$B$1,4))*(EjecucionPIIP[AvanceEjecutado]<>0),"")))),1,"")} | E23: {=IF(ISNUMBER(VALUE(_xlfn.UNIQUE(_xlfn._xlws.FILTER(CUIPO_datos_abiertos[COD_PROGRAMATICO_MGA],(CUIPO_datos_abiertos[COD_PROGRAMATICO_MGA]=Bono_2!B23)*(CUIPO_datos_abiertos[PERIODO]='Reporte'!$B$1)*(CUIPO_datos_abiertos[OBLIGACIONES]<>0),"")))),1,"")} -> 1 | F23: =IF(SUM(C23:E23)=3,"Aplica","")
B24: 4599031 | C24: {=IF(ISNUMBER(VALUE(_xlfn.UNIQUE(_xlfn._xlws.FILTER(PI_SISPT_ProgramacionFisica[Cód. Prod.],PI_SISPT_ProgramacionFisica[Cód. Prod.]=Bono_2!B24,"")))),1,"")} -> 1 | D24: {=IF(ISNUMBER(VALUE(_xlfn.UNIQUE(_xlfn._xlws.FILTER(EjecucionPIIP[CodigoProducto],(EjecucionPIIP[CodigoProducto]=Bono_2!B24)*(EjecucionPIIP[Vigencia]=LEFT('Reporte'!$B$1,4))*(EjecucionPIIP[AvanceEjecutado]<>0),"")))),1,"")} -> 1 | E24: {=IF(ISNUMBER(VALUE(_xlfn.UNIQUE(_xlfn._xlws.FILTER(CUIPO_datos_abiertos[COD_PROGRAMATICO_MGA],(CUIPO_datos_abiertos[COD_PROGRAMATICO_MGA]=Bono_2!B24)*(CUIPO_datos_abiertos[PERIODO]='Reporte'!$B$1)*(CUIPO_datos_abiertos[OBLIGACIONES]<>0),"")))),1,"")} -> 1 | F24: =IF(SUM(C24:E24)=3,"Aplica","") -> Aplica
B25: 4502038 | C25: {=IF(ISNUMBER(VALUE(_xlfn.UNIQUE(_xlfn._xlws.FILTER(PI_SISPT_ProgramacionFisica[Cód. Prod.],PI_SISPT_ProgramacionFisica[Cód. Prod.]=Bono_2!B25,"")))),1,"")} -> 1 | D25: {=IF(ISNUMBER(VALUE(_xlfn.UNIQUE(_xlfn._xlws.FILTER(EjecucionPIIP[CodigoProducto],(EjecucionPIIP[CodigoProducto]=Bono_2!B25)*(EjecucionPIIP[Vigencia]=LEFT('Reporte'!$B$1,4))*(EjecucionPIIP[AvanceEjecutado]<>0),"")))),1,"")} -> 1 | E25: {=IF(ISNUMBER(VALUE(_xlfn.UNIQUE(_xlfn._xlws.FILTER(CUIPO_datos_abiertos[COD_PROGRAMATICO_MGA],(CUIPO_datos_abiertos[COD_PROGRAMATICO_MGA]=Bono_2!B25)*(CUIPO_datos_abiertos[PERIODO]='Reporte'!$B$1)*(CUIPO_datos_abiertos[OBLIGACIONES]<>0),"")))),1,"")} -> 1 | F25: =IF(SUM(C25:E25)=3,"Aplica","") -> Aplica
B26: 2201084 | C26: {=IF(ISNUMBER(VALUE(_xlfn.UNIQUE(_xlfn._xlws.FILTER(PI_SISPT_ProgramacionFisica[Cód. Prod.],PI_SISPT_ProgramacionFisica[Cód. Prod.]=Bono_2!B26,"")))),1,"")} -> 1 | D26: {=IF(ISNUMBER(VALUE(_xlfn.UNIQUE(_xlfn._xlws.FILTER(EjecucionPIIP[CodigoProducto],(EjecucionPIIP[CodigoProducto]=Bono_2!B26)*(EjecucionPIIP[Vigencia]=LEFT('Reporte'!$B$1,4))*(EjecucionPIIP[AvanceEjecutado]<>0),"")))),1,"")} | E26: {=IF(ISNUMBER(VALUE(_xlfn.UNIQUE(_xlfn._xlws.FILTER(CUIPO_datos_abiertos[COD_PROGRAMATICO_MGA],(CUIPO_datos_abiertos[COD_PROGRAMATICO_MGA]=Bono_2!B26)*(CUIPO_datos_abiertos[PERIODO]='Reporte'!$B$1)*(CUIPO_datos_abiertos[OBLIGACIONES]<>0),"")))),1,"")} -> 1 | F26: =IF(SUM(C26:E26)=3,"Aplica","") | N26: =W11 -> 19
B27: 3301053 | C27: {=IF(ISNUMBER(VALUE(_xlfn.UNIQUE(_xlfn._xlws.FILTER(PI_SISPT_ProgramacionFisica[Cód. Prod.],PI_SISPT_ProgramacionFisica[Cód. Prod.]=Bono_2!B27,"")))),1,"")} -> 1 | D27: {=IF(ISNUMBER(VALUE(_xlfn.UNIQUE(_xlfn._xlws.FILTER(EjecucionPIIP[CodigoProducto],(EjecucionPIIP[CodigoProducto]=Bono_2!B27)*(EjecucionPIIP[Vigencia]=LEFT('Reporte'!$B$1,4))*(EjecucionPIIP[AvanceEjecutado]<>0),"")))),1,"")} -> 1 | E27: {=IF(ISNUMBER(VALUE(_xlfn.UNIQUE(_xlfn._xlws.FILTER(CUIPO_datos_abiertos[COD_PROGRAMATICO_MGA],(CUIPO_datos_abiertos[COD_PROGRAMATICO_MGA]=Bono_2!B27)*(CUIPO_datos_abiertos[PERIODO]='Reporte'!$B$1)*(CUIPO_datos_abiertos[OBLIGACIONES]<>0),"")))),1,"")} -> 1 | F27: =IF(SUM(C27:E27)=3,"Aplica","") -> Aplica
B28: 4502039 | C28: {=IF(ISNUMBER(VALUE(_xlfn.UNIQUE(_xlfn._xlws.FILTER(PI_SISPT_ProgramacionFisica[Cód. Prod.],PI_SISPT_ProgramacionFisica[Cód. Prod.]=Bono_2!B28,"")))),1,"")} -> 1 | D28: {=IF(ISNUMBER(VALUE(_xlfn.UNIQUE(_xlfn._xlws.FILTER(EjecucionPIIP[CodigoProducto],(EjecucionPIIP[CodigoProducto]=Bono_2!B28)*(EjecucionPIIP[Vigencia]=LEFT('Reporte'!$B$1,4))*(EjecucionPIIP[AvanceEjecutado]<>0),"")))),1,"")} -> 1 | E28: {=IF(ISNUMBER(VALUE(_xlfn.UNIQUE(_xlfn._xlws.FILTER(CUIPO_datos_abiertos[COD_PROGRAMATICO_MGA],(CUIPO_datos_abiertos[COD_PROGRAMATICO_MGA]=Bono_2!B28)*(CUIPO_datos_abiertos[PERIODO]='Reporte'!$B$1)*(CUIPO_datos_abiertos[OBLIGACIONES]<>0),"")))),1,"")} -> 1 | F28: =IF(SUM(C28:E28)=3,"Aplica","") -> Aplica | L28: =W9 -> 23 | Q28: =W10 -> 0
B29: 2201049 | C29: {=IF(ISNUMBER(VALUE(_xlfn.UNIQUE(_xlfn._xlws.FILTER(PI_SISPT_ProgramacionFisica[Cód. Prod.],PI_SISPT_ProgramacionFisica[Cód. Prod.]=Bono_2!B29,"")))),1,"")} -> 1 | D29: {=IF(ISNUMBER(VALUE(_xlfn.UNIQUE(_xlfn._xlws.FILTER(EjecucionPIIP[CodigoProducto],(EjecucionPIIP[CodigoProducto]=Bono_2!B29)*(EjecucionPIIP[Vigencia]=LEFT('Reporte'!$B$1,4))*(EjecucionPIIP[AvanceEjecutado]<>0),"")))),1,"")} | E29: {=IF(ISNUMBER(VALUE(_xlfn.UNIQUE(_xlfn._xlws.FILTER(CUIPO_datos_abiertos[COD_PROGRAMATICO_MGA],(CUIPO_datos_abiertos[COD_PROGRAMATICO_MGA]=Bono_2!B29)*(CUIPO_datos_abiertos[PERIODO]='Reporte'!$B$1)*(CUIPO_datos_abiertos[OBLIGACIONES]<>0),"")))),1,"")} -> 1 | F29: =IF(SUM(C29:E29)=3,"Aplica","")
B30: 1905026 | C30: {=IF(ISNUMBER(VALUE(_xlfn.UNIQUE(_xlfn._xlws.FILTER(PI_SISPT_ProgramacionFisica[Cód. Prod.],PI_SISPT_ProgramacionFisica[Cód. Prod.]=Bono_2!B30,"")))),1,"")} | D30: {=IF(ISNUMBER(VALUE(_xlfn.UNIQUE(_xlfn._xlws.FILTER(EjecucionPIIP[CodigoProducto],(EjecucionPIIP[CodigoProducto]=Bono_2!B30)*(EjecucionPIIP[Vigencia]=LEFT('Reporte'!$B$1,4))*(EjecucionPIIP[AvanceEjecutado]<>0),"")))),1,"")} | E30: {=IF(ISNUMBER(VALUE(_xlfn.UNIQUE(_xlfn._xlws.FILTER(CUIPO_datos_abiertos[COD_PROGRAMATICO_MGA],(CUIPO_datos_abiertos[COD_PROGRAMATICO_MGA]=Bono_2!B30)*(CUIPO_datos_abiertos[PERIODO]='Reporte'!$B$1)*(CUIPO_datos_abiertos[OBLIGACIONES]<>0),"")))),1,"")} -> 1 | F30: =IF(SUM(C30:E30)=3,"Aplica","")
B31: 2301015 | C31: {=IF(ISNUMBER(VALUE(_xlfn.UNIQUE(_xlfn._xlws.FILTER(PI_SISPT_ProgramacionFisica[Cód. Prod.],PI_SISPT_ProgramacionFisica[Cód. Prod.]=Bono_2!B31,"")))),1,"")} | D31: {=IF(ISNUMBER(VALUE(_xlfn.UNIQUE(_xlfn._xlws.FILTER(EjecucionPIIP[CodigoProducto],(EjecucionPIIP[CodigoProducto]=Bono_2!B31)*(EjecucionPIIP[Vigencia]=LEFT('Reporte'!$B$1,4))*(EjecucionPIIP[AvanceEjecutado]<>0),"")))),1,"")} | E31: {=IF(ISNUMBER(VALUE(_xlfn.UNIQUE(_xlfn._xlws.FILTER(CUIPO_datos_abiertos[COD_PROGRAMATICO_MGA],(CUIPO_datos_abiertos[COD_PROGRAMATICO_MGA]=Bono_2!B31)*(CUIPO_datos_abiertos[PERIODO]='Reporte'!$B$1)*(CUIPO_datos_abiertos[OBLIGACIONES]<>0),"")))),1,"")} -> 1 | F31: =IF(SUM(C31:E31)=3,"Aplica","")
B32: 2102058 | C32: {=IF(ISNUMBER(VALUE(_xlfn.UNIQUE(_xlfn._xlws.FILTER(PI_SISPT_ProgramacionFisica[Cód. Prod.],PI_SISPT_ProgramacionFisica[Cód. Prod.]=Bono_2!B32,"")))),1,"")} -> 1 | D32: {=IF(ISNUMBER(VALUE(_xlfn.UNIQUE(_xlfn._xlws.FILTER(EjecucionPIIP[CodigoProducto],(EjecucionPIIP[CodigoProducto]=Bono_2!B32)*(EjecucionPIIP[Vigencia]=LEFT('Reporte'!$B$1,4))*(EjecucionPIIP[AvanceEjecutado]<>0),"")))),1,"")} -> 1 | E32: {=IF(ISNUMBER(VALUE(_xlfn.UNIQUE(_xlfn._xlws.FILTER(CUIPO_datos_abiertos[COD_PROGRAMATICO_MGA],(CUIPO_datos_abiertos[COD_PROGRAMATICO_MGA]=Bono_2!B32)*(CUIPO_datos_abiertos[PERIODO]='Reporte'!$B$1)*(CUIPO_datos_abiertos[OBLIGACIONES]<>0),"")))),1,"")} -> 1 | F32: =IF(SUM(C32:E32)=3,"Aplica","") -> Aplica
B33: 4102001 | C33: {=IF(ISNUMBER(VALUE(_xlfn.UNIQUE(_xlfn._xlws.FILTER(PI_SISPT_ProgramacionFisica[Cód. Prod.],PI_SISPT_ProgramacionFisica[Cód. Prod.]=Bono_2!B33,"")))),1,"")} -> 1 | D33: {=IF(ISNUMBER(VALUE(_xlfn.UNIQUE(_xlfn._xlws.FILTER(EjecucionPIIP[CodigoProducto],(EjecucionPIIP[CodigoProducto]=Bono_2!B33)*(EjecucionPIIP[Vigencia]=LEFT('Reporte'!$B$1,4))*(EjecucionPIIP[AvanceEjecutado]<>0),"")))),1,"")} -> 1 | E33: {=IF(ISNUMBER(VALUE(_xlfn.UNIQUE(_xlfn._xlws.FILTER(CUIPO_datos_abiertos[COD_PROGRAMATICO_MGA],(CUIPO_datos_abiertos[COD_PROGRAMATICO_MGA]=Bono_2!B33)*(CUIPO_datos_abiertos[PERIODO]='Reporte'!$B$1)*(CUIPO_datos_abiertos[OBLIGACIONES]<>0),"")))),1,"")} -> 1 | F33: =IF(SUM(C33:E33)=3,"Aplica","") -> Aplica | N33: =W7 -> 24
B34: 1901131 | C34: {=IF(ISNUMBER(VALUE(_xlfn.UNIQUE(_xlfn._xlws.FILTER(PI_SISPT_ProgramacionFisica[Cód. Prod.],PI_SISPT_ProgramacionFisica[Cód. Prod.]=Bono_2!B34,"")))),1,"")} | D34: {=IF(ISNUMBER(VALUE(_xlfn.UNIQUE(_xlfn._xlws.FILTER(EjecucionPIIP[CodigoProducto],(EjecucionPIIP[CodigoProducto]=Bono_2!B34)*(EjecucionPIIP[Vigencia]=LEFT('Reporte'!$B$1,4))*(EjecucionPIIP[AvanceEjecutado]<>0),"")))),1,"")} | E34: {=IF(ISNUMBER(VALUE(_xlfn.UNIQUE(_xlfn._xlws.FILTER(CUIPO_datos_abiertos[COD_PROGRAMATICO_MGA],(CUIPO_datos_abiertos[COD_PROGRAMATICO_MGA]=Bono_2!B34)*(CUIPO_datos_abiertos[PERIODO]='Reporte'!$B$1)*(CUIPO_datos_abiertos[OBLIGACIONES]<>0),"")))),1,"")} -> 1 | F34: =IF(SUM(C34:E34)=3,"Aplica","")
B35: 3502043 | C35: {=IF(ISNUMBER(VALUE(_xlfn.UNIQUE(_xlfn._xlws.FILTER(PI_SISPT_ProgramacionFisica[Cód. Prod.],PI_SISPT_ProgramacionFisica[Cód. Prod.]=Bono_2!B35,"")))),1,"")} | D35: {=IF(ISNUMBER(VALUE(_xlfn.UNIQUE(_xlfn._xlws.FILTER(EjecucionPIIP[CodigoProducto],(EjecucionPIIP[CodigoProducto]=Bono_2!B35)*(EjecucionPIIP[Vigencia]=LEFT('Reporte'!$B$1,4))*(EjecucionPIIP[AvanceEjecutado]<>0),"")))),1,"")} | E35: {=IF(ISNUMBER(VALUE(_xlfn.UNIQUE(_xlfn._xlws.FILTER(CUIPO_datos_abiertos[COD_PROGRAMATICO_MGA],(CUIPO_datos_abiertos[COD_PROGRAMATICO_MGA]=Bono_2!B35)*(CUIPO_datos_abiertos[PERIODO]='Reporte'!$B$1)*(CUIPO_datos_abiertos[OBLIGACIONES]<>0),"")))),1,"")} -> 1 | F35: =IF(SUM(C35:E35)=3,"Aplica","") | N35: CUIPO
B36: 3502006 | C36: {=IF(ISNUMBER(VALUE(_xlfn.UNIQUE(_xlfn._xlws.FILTER(PI_SISPT_ProgramacionFisica[Cód. Prod.],PI_SISPT_ProgramacionFisica[Cód. Prod.]=Bono_2!B36,"")))),1,"")} -> 1 | D36: {=IF(ISNUMBER(VALUE(_xlfn.UNIQUE(_xlfn._xlws.FILTER(EjecucionPIIP[CodigoProducto],(EjecucionPIIP[CodigoProducto]=Bono_2!B36)*(EjecucionPIIP[Vigencia]=LEFT('Reporte'!$B$1,4))*(EjecucionPIIP[AvanceEjecutado]<>0),"")))),1,"")} | E36: {=IF(ISNUMBER(VALUE(_xlfn.UNIQUE(_xlfn._xlws.FILTER(CUIPO_datos_abiertos[COD_PROGRAMATICO_MGA],(CUIPO_datos_abiertos[COD_PROGRAMATICO_MGA]=Bono_2!B36)*(CUIPO_datos_abiertos[PERIODO]='Reporte'!$B$1)*(CUIPO_datos_abiertos[OBLIGACIONES]<>0),"")))),1,"")} -> 1 | F36: =IF(SUM(C36:E36)=3,"Aplica","")
B37: 4599019 | C37: {=IF(ISNUMBER(VALUE(_xlfn.UNIQUE(_xlfn._xlws.FILTER(PI_SISPT_ProgramacionFisica[Cód. Prod.],PI_SISPT_ProgramacionFisica[Cód. Prod.]=Bono_2!B37,"")))),1,"")} | D37: {=IF(ISNUMBER(VALUE(_xlfn.UNIQUE(_xlfn._xlws.FILTER(EjecucionPIIP[CodigoProducto],(EjecucionPIIP[CodigoProducto]=Bono_2!B37)*(EjecucionPIIP[Vigencia]=LEFT('Reporte'!$B$1,4))*(EjecucionPIIP[AvanceEjecutado]<>0),"")))),1,"")} | E37: {=IF(ISNUMBER(VALUE(_xlfn.UNIQUE(_xlfn._xlws.FILTER(CUIPO_datos_abiertos[COD_PROGRAMATICO_MGA],(CUIPO_datos_abiertos[COD_PROGRAMATICO_MGA]=Bono_2!B37)*(CUIPO_datos_abiertos[PERIODO]='Reporte'!$B$1)*(CUIPO_datos_abiertos[OBLIGACIONES]<>0),"")))),1,"")} -> 1 | F37: =IF(SUM(C37:E37)=3,"Aplica","")
B38: 3708009 | C38: {=IF(ISNUMBER(VALUE(_xlfn.UNIQUE(_xlfn._xlws.FILTER(PI_SISPT_ProgramacionFisica[Cód. Prod.],PI_SISPT_ProgramacionFisica[Cód. Prod.]=Bono_2!B38,"")))),1,"")} | D38: {=IF(ISNUMBER(VALUE(_xlfn.UNIQUE(_xlfn._xlws.FILTER(EjecucionPIIP[CodigoProducto],(EjecucionPIIP[CodigoProducto]=Bono_2!B38)*(EjecucionPIIP[Vigencia]=LEFT('Reporte'!$B$1,4))*(EjecucionPIIP[AvanceEjecutado]<>0),"")))),1,"")} | E38: {=IF(ISNUMBER(VALUE(_xlfn.UNIQUE(_xlfn._xlws.FILTER(CUIPO_datos_abiertos[COD_PROGRAMATICO_MGA],(CUIPO_datos_abiertos[COD_PROGRAMATICO_MGA]=Bono_2!B38)*(CUIPO_datos_abiertos[PERIODO]='Reporte'!$B$1)*(CUIPO_datos_abiertos[OBLIGACIONES]<>0),"")))),1,"")} -> 1 | F38: =IF(SUM(C38:E38)=3,"Aplica","")
B39: 1906030 | C39: {=IF(ISNUMBER(VALUE(_xlfn.UNIQUE(_xlfn._xlws.FILTER(PI_SISPT_ProgramacionFisica[Cód. Prod.],PI_SISPT_ProgramacionFisica[Cód. Prod.]=Bono_2!B39,"")))),1,"")} -> 1 | D39: {=IF(ISNUMBER(VALUE(_xlfn.UNIQUE(_xlfn._xlws.FILTER(EjecucionPIIP[CodigoProducto],(EjecucionPIIP[CodigoProducto]=Bono_2!B39)*(EjecucionPIIP[Vigencia]=LEFT('Reporte'!$B$1,4))*(EjecucionPIIP[AvanceEjecutado]<>0),"")))),1,"")} | E39: {=IF(ISNUMBER(VALUE(_xlfn.UNIQUE(_xlfn._xlws.FILTER(CUIPO_datos_abiertos[COD_PROGRAMATICO_MGA],(CUIPO_datos_abiertos[COD_PROGRAMATICO_MGA]=Bono_2!B39)*(CUIPO_datos_abiertos[PERIODO]='Reporte'!$B$1)*(CUIPO_datos_abiertos[OBLIGACIONES]<>0),"")))),1,"")} -> 1 | F39: =IF(SUM(C39:E39)=3,"Aplica","")
B40: 2302024 | C40: {=IF(ISNUMBER(VALUE(_xlfn.UNIQUE(_xlfn._xlws.FILTER(PI_SISPT_ProgramacionFisica[Cód. Prod.],PI_SISPT_ProgramacionFisica[Cód. Prod.]=Bono_2!B40,"")))),1,"")} -> 1 | D40: {=IF(ISNUMBER(VALUE(_xlfn.UNIQUE(_xlfn._xlws.FILTER(EjecucionPIIP[CodigoProducto],(EjecucionPIIP[CodigoProducto]=Bono_2!B40)*(EjecucionPIIP[Vigencia]=LEFT('Reporte'!$B$1,4))*(EjecucionPIIP[AvanceEjecutado]<>0),"")))),1,"")} | E40: {=IF(ISNUMBER(VALUE(_xlfn.UNIQUE(_xlfn._xlws.FILTER(CUIPO_datos_abiertos[COD_PROGRAMATICO_MGA],(CUIPO_datos_abiertos[COD_PROGRAMATICO_MGA]=Bono_2!B40)*(CUIPO_datos_abiertos[PERIODO]='Reporte'!$B$1)*(CUIPO_datos_abiertos[OBLIGACIONES]<>0),"")))),1,"")} -> 1 | F40: =IF(SUM(C40:E40)=3,"Aplica","")
B41: 4501079 | C41: {=IF(ISNUMBER(VALUE(_xlfn.UNIQUE(_xlfn._xlws.FILTER(PI_SISPT_ProgramacionFisica[Cód. Prod.],PI_SISPT_ProgramacionFisica[Cód. Prod.]=Bono_2!B41,"")))),1,"")} -> 1 | D41: {=IF(ISNUMBER(VALUE(_xlfn.UNIQUE(_xlfn._xlws.FILTER(EjecucionPIIP[CodigoProducto],(EjecucionPIIP[CodigoProducto]=Bono_2!B41)*(EjecucionPIIP[Vigencia]=LEFT('Reporte'!$B$1,4))*(EjecucionPIIP[AvanceEjecutado]<>0),"")))),1,"")} | E41: {=IF(ISNUMBER(VALUE(_xlfn.UNIQUE(_xlfn._xlws.FILTER(CUIPO_datos_abiertos[COD_PROGRAMATICO_MGA],(CUIPO_datos_abiertos[COD_PROGRAMATICO_MGA]=Bono_2!B41)*(CUIPO_datos_abiertos[PERIODO]='Reporte'!$B$1)*(CUIPO_datos_abiertos[OBLIGACIONES]<>0),"")))),1,"")} -> 1 | F41: =IF(SUM(C41:E41)=3,"Aplica","")
B42: 3301054 | C42: {=IF(ISNUMBER(VALUE(_xlfn.UNIQUE(_xlfn._xlws.FILTER(PI_SISPT_ProgramacionFisica[Cód. Prod.],PI_SISPT_ProgramacionFisica[Cód. Prod.]=Bono_2!B42,"")))),1,"")} -> 1 | D42: {=IF(ISNUMBER(VALUE(_xlfn.UNIQUE(_xlfn._xlws.FILTER(EjecucionPIIP[CodigoProducto],(EjecucionPIIP[CodigoProducto]=Bono_2!B42)*(EjecucionPIIP[Vigencia]=LEFT('Reporte'!$B$1,4))*(EjecucionPIIP[AvanceEjecutado]<>0),"")))),1,"")} | E42: {=IF(ISNUMBER(VALUE(_xlfn.UNIQUE(_xlfn._xlws.FILTER(CUIPO_datos_abiertos[COD_PROGRAMATICO_MGA],(CUIPO_datos_abiertos[COD_PROGRAMATICO_MGA]=Bono_2!B42)*(CUIPO_datos_abiertos[PERIODO]='Reporte'!$B$1)*(CUIPO_datos_abiertos[OBLIGACIONES]<>0),"")))),1,"")} -> 1 | F42: =IF(SUM(C42:E42)=3,"Aplica","")
B43: 4102041 | C43: {=IF(ISNUMBER(VALUE(_xlfn.UNIQUE(_xlfn._xlws.FILTER(PI_SISPT_ProgramacionFisica[Cód. Prod.],PI_SISPT_ProgramacionFisica[Cód. Prod.]=Bono_2!B43,"")))),1,"")} -> 1 | D43: {=IF(ISNUMBER(VALUE(_xlfn.UNIQUE(_xlfn._xlws.FILTER(EjecucionPIIP[CodigoProducto],(EjecucionPIIP[CodigoProducto]=Bono_2!B43)*(EjecucionPIIP[Vigencia]=LEFT('Reporte'!$B$1,4))*(EjecucionPIIP[AvanceEjecutado]<>0),"")))),1,"")} | E43: {=IF(ISNUMBER(VALUE(_xlfn.UNIQUE(_xlfn._xlws.FILTER(CUIPO_datos_abiertos[COD_PROGRAMATICO_MGA],(CUIPO_datos_abiertos[COD_PROGRAMATICO_MGA]=Bono_2!B43)*(CUIPO_datos_abiertos[PERIODO]='Reporte'!$B$1)*(CUIPO_datos_abiertos[OBLIGACIONES]<>0),"")))),1,"")} -> 1 | F43: =IF(SUM(C43:E43)=3,"Aplica","")
B44: 1905028 | C44: {=IF(ISNUMBER(VALUE(_xlfn.UNIQUE(_xlfn._xlws.FILTER(PI_SISPT_ProgramacionFisica[Cód. Prod.],PI_SISPT_ProgramacionFisica[Cód. Prod.]=Bono_2!B44,"")))),1,"")} | D44: {=IF(ISNUMBER(VALUE(_xlfn.UNIQUE(_xlfn._xlws.FILTER(EjecucionPIIP[CodigoProducto],(EjecucionPIIP[CodigoProducto]=Bono_2!B44)*(EjecucionPIIP[Vigencia]=LEFT('Reporte'!$B$1,4))*(EjecucionPIIP[AvanceEjecutado]<>0),"")))),1,"")} | E44: {=IF(ISNUMBER(VALUE(_xlfn.UNIQUE(_xlfn._xlws.FILTER(CUIPO_datos_abiertos[COD_PROGRAMATICO_MGA],(CUIPO_datos_abiertos[COD_PROGRAMATICO_MGA]=Bono_2!B44)*(CUIPO_datos_abiertos[PERIODO]='Reporte'!$B$1)*(CUIPO_datos_abiertos[OBLIGACIONES]<>0),"")))),1,"")} -> 1 | F44: =IF(SUM(C44:E44)=3,"Aplica","")
B45: 1905027 | C45: {=IF(ISNUMBER(VALUE(_xlfn.UNIQUE(_xlfn._xlws.FILTER(PI_SISPT_ProgramacionFisica[Cód. Prod.],PI_SISPT_ProgramacionFisica[Cód. Prod.]=Bono_2!B45,"")))),1,"")} | D45: {=IF(ISNUMBER(VALUE(_xlfn.UNIQUE(_xlfn._xlws.FILTER(EjecucionPIIP[CodigoProducto],(EjecucionPIIP[CodigoProducto]=Bono_2!B45)*(EjecucionPIIP[Vigencia]=LEFT('Reporte'!$B$1,4))*(EjecucionPIIP[AvanceEjecutado]<>0),"")))),1,"")} | E45: {=IF(ISNUMBER(VALUE(_xlfn.UNIQUE(_xlfn._xlws.FILTER(CUIPO_datos_abiertos[COD_PROGRAMATICO_MGA],(CUIPO_datos_abiertos[COD_PROGRAMATICO_MGA]=Bono_2!B45)*(CUIPO_datos_abiertos[PERIODO]='Reporte'!$B$1)*(CUIPO_datos_abiertos[OBLIGACIONES]<>0),"")))),1,"")} -> 1 | F45: =IF(SUM(C45:E45)=3,"Aplica","")
B46: 1702009 | C46: {=IF(ISNUMBER(VALUE(_xlfn.UNIQUE(_xlfn._xlws.FILTER(PI_SISPT_ProgramacionFisica[Cód. Prod.],PI_SISPT_ProgramacionFisica[Cód. Prod.]=Bono_2!B46,"")))),1,"")} -> 1 | D46: {=IF(ISNUMBER(VALUE(_xlfn.UNIQUE(_xlfn._xlws.FILTER(EjecucionPIIP[CodigoProducto],(EjecucionPIIP[CodigoProducto]=Bono_2!B46)*(EjecucionPIIP[Vigencia]=LEFT('Reporte'!$B$1,4))*(EjecucionPIIP[AvanceEjecutado]<>0),"")))),1,"")} | E46: {=IF(ISNUMBER(VALUE(_xlfn.UNIQUE(_xlfn._xlws.FILTER(CUIPO_datos_abiertos[COD_PROGRAMATICO_MGA],(CUIPO_datos_abiertos[COD_PROGRAMATICO_MGA]=Bono_2!B46)*(CUIPO_datos_abiertos[PERIODO]='Reporte'!$B$1)*(CUIPO_datos_abiertos[OBLIGACIONES]<>0),"")))),1,"")} -> 1 | F46: =IF(SUM(C46:E46)=3,"Aplica","")
B47: 3602003 | C47: {=IF(ISNUMBER(VALUE(_xlfn.UNIQUE(_xlfn._xlws.FILTER(PI_SISPT_ProgramacionFisica[Cód. Prod.],PI_SISPT_ProgramacionFisica[Cód. Prod.]=Bono_2!B47,"")))),1,"")} -> 1 | D47: {=IF(ISNUMBER(VALUE(_xlfn.UNIQUE(_xlfn._xlws.FILTER(EjecucionPIIP[CodigoProducto],(EjecucionPIIP[CodigoProducto]=Bono_2!B47)*(EjecucionPIIP[Vigencia]=LEFT('Reporte'!$B$1,4))*(EjecucionPIIP[AvanceEjecutado]<>0),"")))),1,"")} | E47: {=IF(ISNUMBER(VALUE(_xlfn.UNIQUE(_xlfn._xlws.FILTER(CUIPO_datos_abiertos[COD_PROGRAMATICO_MGA],(CUIPO_datos_abiertos[COD_PROGRAMATICO_MGA]=Bono_2!B47)*(CUIPO_datos_abiertos[PERIODO]='Reporte'!$B$1)*(CUIPO_datos_abiertos[OBLIGACIONES]<>0),"")))),1,"")} -> 1 | F47: =IF(SUM(C47:E47)=3,"Aplica","")
... B317: 1702007 | C317: {=IF(ISNUMBER(VALUE(_xlfn.UNIQUE(_xlfn._xlws.FILTER(PI_SISPT_ProgramacionFisica[Cód. Prod.],PI_SISPT_ProgramacionFisica[Cód. Prod.]=Bono_2!B317,"")))),1,"")} -> 1 | D317: {=IF(ISNUMBER(VALUE(_xlfn.UNIQUE(_xlfn._xlws.FILTER(EjecucionPIIP[CodigoProducto],(EjecucionPIIP[CodigoProducto]=Bono_2!B317)*(EjecucionPIIP[Vigencia]=LEFT('Reporte'!$B$1,4))*(EjecucionPIIP[AvanceEjecutado]<>0),"")))),1,"")} | E317: {=IF(ISNUMBER(VALUE(_xlfn.UNIQUE(_xlfn._xlws.FILTER(CUIPO_datos_abiertos[COD_PROGRAMATICO_MGA],(CUIPO_datos_abiertos[COD_PROGRAMATICO_MGA]=Bono_2!B317)*(CUIPO_datos_abiertos[PERIODO]='Reporte'!$B$1)*(CUIPO_datos_abiertos[OBLIGACIONES]<>0),"")))),1,"")} | F317: =IF(SUM(C317:E317)=3,"Aplica","")
C318: {=IF(ISNUMBER(VALUE(_xlfn.UNIQUE(_xlfn._xlws.FILTER(PI_SISPT_ProgramacionFisica[Cód. Prod.],PI_SISPT_ProgramacionFisica[Cód. Prod.]=Bono_2!B318,"")))),1,"")} | D318: {=IF(ISNUMBER(VALUE(_xlfn.UNIQUE(_xlfn._xlws.FILTER(EjecucionPIIP[CodigoProducto],(EjecucionPIIP[CodigoProducto]=Bono_2!B318)*(EjecucionPIIP[Vigencia]=LEFT('Reporte'!$B$1,4))*(EjecucionPIIP[AvanceEjecutado]<>0),"")))),1,"")} | E318: {=IF(ISNUMBER(VALUE(_xlfn.UNIQUE(_xlfn._xlws.FILTER(CUIPO_datos_abiertos[COD_PROGRAMATICO_MGA],(CUIPO_datos_abiertos[COD_PROGRAMATICO_MGA]=Bono_2!B318)*(CUIPO_datos_abiertos[PERIODO]='Reporte'!$B$1)*(CUIPO_datos_abiertos[OBLIGACIONES]<>0),"")))),1,"")} | F318: =IF(SUM(C318:E318)=3,"Aplica","")
C319: {=IF(ISNUMBER(VALUE(_xlfn.UNIQUE(_xlfn._xlws.FILTER(PI_SISPT_ProgramacionFisica[Cód. Prod.],PI_SISPT_ProgramacionFisica[Cód. Prod.]=Bono_2!B319,"")))),1,"")} | D319: {=IF(ISNUMBER(VALUE(_xlfn.UNIQUE(_xlfn._xlws.FILTER(EjecucionPIIP[CodigoProducto],(EjecucionPIIP[CodigoProducto]=Bono_2!B319)*(EjecucionPIIP[Vigencia]=LEFT('Reporte'!$B$1,4))*(EjecucionPIIP[AvanceEjecutado]<>0),"")))),1,"")} | E319: {=IF(ISNUMBER(VALUE(_xlfn.UNIQUE(_xlfn._xlws.FILTER(CUIPO_datos_abiertos[COD_PROGRAMATICO_MGA],(CUIPO_datos_abiertos[COD_PROGRAMATICO_MGA]=Bono_2!B319)*(CUIPO_datos_abiertos[PERIODO]='Reporte'!$B$1)*(CUIPO_datos_abiertos[OBLIGACIONES]<>0),"")))),1,"")} | F319: =IF(SUM(C319:E319)=3,"Aplica","")
C320: {=IF(ISNUMBER(VALUE(_xlfn.UNIQUE(_xlfn._xlws.FILTER(PI_SISPT_ProgramacionFisica[Cód. Prod.],PI_SISPT_ProgramacionFisica[Cód. Prod.]=Bono_2!B320,"")))),1,"")} | D320: {=IF(ISNUMBER(VALUE(_xlfn.UNIQUE(_xlfn._xlws.FILTER(EjecucionPIIP[CodigoProducto],(EjecucionPIIP[CodigoProducto]=Bono_2!B320)*(EjecucionPIIP[Vigencia]=LEFT('Reporte'!$B$1,4))*(EjecucionPIIP[AvanceEjecutado]<>0),"")))),1,"")} | E320: {=IF(ISNUMBER(VALUE(_xlfn.UNIQUE(_xlfn._xlws.FILTER(CUIPO_datos_abiertos[COD_PROGRAMATICO_MGA],(CUIPO_datos_abiertos[COD_PROGRAMATICO_MGA]=Bono_2!B320)*(CUIPO_datos_abiertos[PERIODO]='Reporte'!$B$1)*(CUIPO_datos_abiertos[OBLIGACIONES]<>0),"")))),1,"")} | F320: =IF(SUM(C320:E320)=3,"Aplica","")
C321: {=IF(ISNUMBER(VALUE(_xlfn.UNIQUE(_xlfn._xlws.FILTER(PI_SISPT_ProgramacionFisica[Cód. Prod.],PI_SISPT_ProgramacionFisica[Cód. Prod.]=Bono_2!B321,"")))),1,"")} | D321: {=IF(ISNUMBER(VALUE(_xlfn.UNIQUE(_xlfn._xlws.FILTER(EjecucionPIIP[CodigoProducto],(EjecucionPIIP[CodigoProducto]=Bono_2!B321)*(EjecucionPIIP[Vigencia]=LEFT('Reporte'!$B$1,4))*(EjecucionPIIP[AvanceEjecutado]<>0),"")))),1,"")} | E321: {=IF(ISNUMBER(VALUE(_xlfn.UNIQUE(_xlfn._xlws.FILTER(CUIPO_datos_abiertos[COD_PROGRAMATICO_MGA],(CUIPO_datos_abiertos[COD_PROGRAMATICO_MGA]=Bono_2!B321)*(CUIPO_datos_abiertos[PERIODO]='Reporte'!$B$1)*(CUIPO_datos_abiertos[OBLIGACIONES]<>0),"")))),1,"")} | F321: =IF(SUM(C321:E321)=3,"Aplica","")
C322: {=IF(ISNUMBER(VALUE(_xlfn.UNIQUE(_xlfn._xlws.FILTER(PI_SISPT_ProgramacionFisica[Cód. Prod.],PI_SISPT_ProgramacionFisica[Cód. Prod.]=Bono_2!B322,"")))),1,"")} | D322: {=IF(ISNUMBER(VALUE(_xlfn.UNIQUE(_xlfn._xlws.FILTER(EjecucionPIIP[CodigoProducto],(EjecucionPIIP[CodigoProducto]=Bono_2!B322)*(EjecucionPIIP[Vigencia]=LEFT('Reporte'!$B$1,4))*(EjecucionPIIP[AvanceEjecutado]<>0),"")))),1,"")} | E322: {=IF(ISNUMBER(VALUE(_xlfn.UNIQUE(_xlfn._xlws.FILTER(CUIPO_datos_abiertos[COD_PROGRAMATICO_MGA],(CUIPO_datos_abiertos[COD_PROGRAMATICO_MGA]=Bono_2!B322)*(CUIPO_datos_abiertos[PERIODO]='Reporte'!$B$1)*(CUIPO_datos_abiertos[OBLIGACIONES]<>0),"")))),1,"")} | F322: =IF(SUM(C322:E322)=3,"Aplica","")

Sheet PPI
A1: Código Programa presupuestal | B1: Programa Presupuestal | C1: Vigencia | D1: Programación Financiera
A2: 0401 | B2: Levantamiento y actualización de información estadística de calidad | C2: 2024 | D2: 1350000000
A3: 0401 | B3: Levantamiento y actualización de información estadística de calidad | C3: 2025 | D3: 280000000
A4: 0401 | B4: Levantamiento y actualización de información estadística de calidad | C4: 2026 | D4: 300000000
A5: 0401 | B5: Levantamiento y actualización de información estadística de calidad | C5: 2027 | D5: 320000000
A6: 1206 | B6: Sistema penitenciario y carcelario en el marco de los derechos humanos | C6: 2024 | D6: 280000000
A7: 1206 | B7: Sistema penitenciario y carcelario en el marco de los derechos humanos | C7: 2025 | D7: 280000000
A8: 1206 | B8: Sistema penitenciario y carcelario en el marco de los derechos humanos | C8: 2026 | D8: 280000000
A9: 1206 | B9: Sistema penitenciario y carcelario en el marco de los derechos humanos | C9: 2027 | D9: 280000000
A10: 1702 | B10: Inclusión productiva de pequeños productores rurales | C10: 2024 | D10: 33223000000
A11: 1702 | B11: Inclusión productiva de pequeños productores rurales | C11: 2025 | D11: 15650000000
A12: 1702 | B12: Inclusión productiva de pequeños productores rurales | C12: 2026 | D12: 2750000000
A13: 1702 | B13: Inclusión productiva de pequeños productores rurales | C13: 2027 | D13: 2750000000
... A217: 4599 | B217: Fortalecimiento a la gestión y dirección de la administración pública territorial | C217: 2027 | D217: 3.6184176e+10

Sheet Bono_3
A1: Concepto | B1: PIIP (Mill.) | C1: CUIPO (Mill.) | D1: Resultado
A2: Obligaciones totales periodo seleccionado | B2: =SUMIFS(EjecucionPIIP[ObligadoVigente],EjecucionPIIP[Periodo],'Reporte'!$B$1) -> 4.2405558e+11 | C2: =SUMIFS(CUIPO_datos_abiertos[OBLIGACIONES],CUIPO_datos_abiertos[ES_PRODUCTO_VALIDO],"VALIDO",CUIPO_datos_abiertos[PERIODO],'Reporte'!$B$1) -> 515402603034
A3: Valor mínimo | B3: =MIN(B2:C2) -> 4.2405558e+11
A4: Valor máximo | C4: =MAX(B2:C2) -> 515402603034
A5: Puntaje PIIP-CUIPO | D5: =B3/C4 -> 0.8227657

Sheet Bono_4
A1: Concepto | B1: Prog. SisPT (mill.) | C1: Oblig. CUIPO (mill.) | D1: Resultado
A2: Total vigencia analizada | B2: {=_xlfn.LET(_xlpm.productos_intersectados,_xlfn._xlws.FILTER(_xlfn.ANCHORARRAY(Bono_2!B5),Bono_2!$F$5:$F$322="Aplica"),_xlpm.agrupacion,SUMIFS(PI_SISPT_ProgramacionFisica[Prog. Fin.],PI_SISPT_ProgramacionFisica[Cód. Prod.],_xlpm.productos_intersectados,PI_SISPT_ProgramacionFisica[Vigencia],LEFT('Reporte'!$B$1,4)),SUM(_xlpm.agrupacion))} -> 0 | C2: =SUMIFS(CUIPO_datos_abiertos[OBLIGACIONES],CUIPO_datos_abiertos[ES_PRODUCTO_VALIDO],"VALIDO",CUIPO_datos_abiertos[PERIODO],'Reporte'!$B$1) -> 515402603034
A3: Valor mínimo | B3: =MIN(B2:C2) -> 0
A4: Valor máximo | C4: =MAX(B2:C2) -> 515402603034
A5: Puntaje SisPT-CUIPO | D5: =B3/C4 -> 0

Sheet ReporteDNP
A2: Producto | B2: Código del producto | C2: Indicador de producto principal | D2: Código del indicador principal | E2: Codigos Meta | F2: Prog. Cuatrienio | G2: Eje. Acum | H2: Proyectos | I2: Programación proyectos 2026 - 202XX | J2: Revisión
A3: Servicio de gestión documental | B3: 4599017 | C3: Sistema de gestión documental implementado | D3: 459901700 | E3: MT073, MT197, MT364 | F3: 3 | G3: 0 | H3: 202600000012362, 202600000012558 | I3: 2 | J3: =IF(ReporteDNP[[#This Row],[Eje. Acum]]>=ReporteDNP[[#This Row],[Prog. Cuatrienio]],"No requiere ajuste","Requiere ajuste") -> Requiere ajuste
A4: Documentos de planeación | B4: 3502047 | C4: Documentos de planeación elaborados | D4: 350204700 | E4: MT221 | F4: 1 | G4: 0 | H4: 202600000014100 | I4: 1 | J4: =IF(ReporteDNP[[#This Row],[Eje. Acum]]>=ReporteDNP[[#This Row],[Prog. Cuatrienio]],"No requiere ajuste","Requiere ajuste") -> Requiere ajuste
A5: Servicios de información implementados | B5: 4599025 | C5: Sistemas de información implementados | D5: 459902500 | E5: MT198, MT376, MT382, MT386 | F5: 20 | G5: 11.75 | H5: 202600000005350, 202500000050134 | I5: 2 | J5: =IF(ReporteDNP[[#This Row],[Eje. Acum]]>=ReporteDNP[[#This Row],[Prog. Cuatrienio]],"No requiere ajuste","Requiere ajuste") -> Requiere ajuste
A6: Servicio de restauración de ecosistemas | B6: 3202005 | C6: Áreas en proceso de restauración | D6: 320200500 | E6: MT288 | F6: 300 | G6: 96 | H6: 202500000034248 | I6: 46.1669 | J6: =IF(ReporteDNP[[#This Row],[Eje. Acum]]>=ReporteDNP[[#This Row],[Prog. Cuatrienio]],"No requiere ajuste","Requiere ajuste") -> Requiere ajuste
A7: Servicio de información actualizado | B7: 4599028 | C7: Sistemas de información actualizados | D7: 459902800 | E7: MT199 | F7: 1 | G7: 0 | H7: 202600000011474 | I7: 1 | J7: =IF(ReporteDNP[[#This Row],[Eje. Acum]]>=ReporteDNP[[#This Row],[Prog. Cuatrienio]],"No requiere ajuste","Requiere ajuste") -> Requiere ajuste
A8: Estaciones de bomberos construidas | B8: 4503015 | C8: Estaciones de bomberos construidas | D8: 450301500 | E8: MT426 | F8: 1 | G8: 0 | H8: 202600000012790 | I8: 2 | J8: =IF(ReporteDNP[[#This Row],[Eje. Acum]]>=ReporteDNP[[#This Row],[Prog. Cuatrienio]],"No requiere ajuste","Requiere ajuste") -> Requiere ajuste
A9: Servicios de información implementados | B9: 3605011 | C9: Sistemas de información implementados | D9: 360501100 | E9: MT008 | F9: 1 | G9: 1 | J9: =IF(ReporteDNP[[#This Row],[Eje. Acum]]>=ReporteDNP[[#This Row],[Prog. Cuatrienio]],"No requiere ajuste","Requiere ajuste") -> No requiere ajuste
A10: Documentos de lineamientos técnicos | B10: 4102035 | C10: Documentos de lineamientos técnicos realizados | D10: 410203500 | E10: MT032 | F10: 1 | G10: 0 | J10: =IF(ReporteDNP[[#This Row],[Eje. Acum]]>=ReporteDNP[[#This Row],[Prog. Cuatrienio]],"No requiere ajuste","Requiere ajuste") -> Requiere ajuste
A11: Documentos de planeación | B11: 2201001 | C11: Documentos de planeación para la educación inicial, preescolar, básica y media emitidos | D11: 220100100 | E11: MT035 | F11: 1 | G11: 1 | J11: =IF(ReporteDNP[[#This Row],[Eje. Acum]]>=ReporteDNP[[#This Row],[Prog. Cuatrienio]],"No requiere ajuste","Requiere ajuste") -> No requiere ajuste
A12: Documentos de lineamientos técnicos | B12: 2201005 | C12: Documentos de lineamientos técnicos en educación inicial, preescolar, básica y media expedidos | D12: 220100500 | E12: MT038 | F12: 1 | G12: 1 | J12: =IF(ReporteDNP[[#This Row],[Eje. Acum]]>=ReporteDNP[[#This Row],[Prog. Cuatrienio]],"No requiere ajuste","Requiere ajuste") -> No requiere ajuste
A13: Documentos de estudios técnicos | B13: 2202056 | C13: Documentos de estudios técnicos realizados | D13: 220205600 | E13: MT076 | F13: 1 | G13: 0 | J13: =IF(ReporteDNP[[#This Row],[Eje. Acum]]>=ReporteDNP[[#This Row],[Prog. Cuatrienio]],"No requiere ajuste","Requiere ajuste") -> Requiere ajuste
A14: Documentos de planeación | B14: 2202086 | C14: Documentos de planeación elaborados | D14: 220208600 | E14: MT081 | F14: 1 | G14: 0 | J14: =IF(ReporteDNP[[#This Row],[Eje. Acum]]>=ReporteDNP[[#This Row],[Prog. Cuatrienio]],"No requiere ajuste","Requiere ajuste") -> Requiere ajuste
A15: Sedes de instituciones de educación superior mejoradas | B15: 2202072 | C15: Sedes de instituciones de educación superior mejoradas | D15: 220207200 | E15: MT083 | F15: 1 | G15: 0 | J15: =IF(ReporteDNP[[#This Row],[Eje. Acum]]>=ReporteDNP[[#This Row],[Prog. Cuatrienio]],"No requiere ajuste","Requiere ajuste") -> Requiere ajuste
A16: Documentos de planeación | B16: 1905015 | C16: Documentos de planeación elaborados | D16: 190501500 | E16: MT086, MT433 | F16: 3 | G16: 1 | J16: =IF(ReporteDNP[[#This Row],[Eje. Acum]]>=ReporteDNP[[#This Row],[Prog. Cuatrienio]],"No requiere ajuste","Requiere ajuste") -> Requiere ajuste
A17: Servicios de información implementados | B17: 1906043 | C17: Sistemas de información implementados | D17: 190604300 | E17: MT131 | F17: 1 | G17: 0 | J17: =IF(ReporteDNP[[#This Row],[Eje. Acum]]>=ReporteDNP[[#This Row],[Prog. Cuatrienio]],"No requiere ajuste","Requiere ajuste") -> Requiere ajuste
A18: Canchas multifuncionales construidas y dotadas | B18: 4301015 | C18: Canchas multifuncionales construidas y dotadas | D18: 430101500 | E18: MT153 | F18: 2 | G18: 0 | J18: =IF(ReporteDNP[[#This Row],[Eje. Acum]]>=ReporteDNP[[#This Row],[Prog. Cuatrienio]],"No requiere ajuste","Requiere ajuste") -> Requiere ajuste
A19: Parque recreo-deportivo construido y dotado | B19: 4301030 | C19: Parque recreo-deportivo construido y dotado | D19: 430103000 | E19: MT154 | F19: 1 | G19: 2 | J19: =IF(ReporteDNP[[#This Row],[Eje. Acum]]>=ReporteDNP[[#This Row],[Prog. Cuatrienio]],"No requiere ajuste","Requiere ajuste") -> No requiere ajuste
A20: Documentos de lineamientos técnicos | B20: 4302009 | C20: Documentos de lineamientos técnicos realizados | D20: 430200900 | E20: MT163 | F20: 1 | G20: 1 | J20: =IF(ReporteDNP[[#This Row],[Eje. Acum]]>=ReporteDNP[[#This Row],[Prog. Cuatrienio]],"No requiere ajuste","Requiere ajuste") -> No requiere ajuste
... A48: Documentos de planeación | B48: 1704003 | C48: Documentos de planeación elaborados | D48: 170400300 | E48: MT460 | F48: 1 | G48: 1 | J48: =IF(ReporteDNP[[#This Row],[Eje. Acum]]>=ReporteDNP[[#This Row],[Prog. Cuatrienio]],"No requiere ajuste","Requiere ajuste") -> No requiere ajuste

Sheet CUIPO_DAbiertos
A1: PERIODO | B1: CODIGO_ENTIDAD | C1: BPIN | D1: NOM_VIGENCIA_DEL_GASTO | E1: NOM_SECCION_PRESUPUESTAL | F1: COD_PROGAMA_MGA | G1: COD_PROGRAMATICO_MGA | H1: NOM_CPC | I1: NOM_SECTORIAL | J1: NOM_FUENTES_FINANCIACION | K1: NOM_SITUACION_DE_FONDOS | L1: NOM_POLITICA_PUBLICA | M1: NOM_TERCEROS | N1: COMPROMISOS | O1: OBLIGACIONES | P1: PAGOS | Q1: ES_PRODUCTO_VALIDO
A2: 20251201 | B2: 117070000 | C2: 0,00E+00 | D2: VIGENCIA ACTUAL | E2: ENTIDADES TERRITORIALES - ASAMBLEA | F2: =LEFT(CUIPO_datos_abiertos[[#This Row],[COD_PROGRAMATICO_MGA]],4) -> 0 | G2: 0 | H2: No aplica | I2: NO APLICA | J2: INGRESOS CORRIENTES DE LIBRE DESTINACION | K2: CON SITUACION DE FONDOS | L2: NO APLICA | M2: NO APLICA | N2: 999183 | O2: 999183 | P2: 999183 | Q2: =IF(AND(LEN(CUIPO_datos_abiertos[[#This Row],[COD_PROGRAMATICO_MGA]])=7,ISNUMBER(VALUE(CUIPO_datos_abiertos[[#This Row],[COD_PROGRAMATICO_MGA]]))),"VALIDO","")
A3: 20251201 | B3: 117070000 | C3: 202500000042537 | D3: VIGENCIA ACTUAL | E3: ENTIDADES TERRITORIALES - SALUD | F3: =LEFT(CUIPO_datos_abiertos[[#This Row],[COD_PROGRAMATICO_MGA]],4) -> 1903 | G3: 1903011 | H3: No aplica | I3: OGS - DIFERENTES A LOS CONTEMPLADOS EN LAS DEMÁS SUBCUENTAS | J3: INGRESOS CORRIENTES DE DESTINACION ESPECIFICA POR ACTO ADMINISTRATIVO | K3: CON SITUACION DE FONDOS | L3: NO APLICA | M3: NO APLICA | N3: 167075447 | O3: 167075447 | P3: 167075447 | Q3: =IF(AND(LEN(CUIPO_datos_abiertos[[#This Row],[COD_PROGRAMATICO_MGA]])=7,ISNUMBER(VALUE(CUIPO_datos_abiertos[[#This Row],[COD_PROGRAMATICO_MGA]]))),"VALIDO","") -> VALIDO
A4: 20260301 | B4: 117070000 | C4: 0 | D4: VIGENCIAS FUTURAS - VIGENCIA ACTUAL | E4: ENTIDADES TERRITORIALES - ADMINISTRACION CENTRAL | F4: =LEFT(CUIPO_datos_abiertos[[#This Row],[COD_PROGRAMATICO_MGA]],4) -> NO A | G4: NO APLICA | H4: NO APLICA | I4: NO APLICA | J4: NO APLICA | K4: NO APLICA | L4: NO APLICA | M4: NO APLICA | N4: 565000000 | O4: 565000000 | P4: 565000000 | Q4: =IF(AND(LEN(CUIPO_datos_abiertos[[#This Row],[COD_PROGRAMATICO_MGA]])=7,ISNUMBER(VALUE(CUIPO_datos_abiertos[[#This Row],[COD_PROGRAMATICO_MGA]]))),"VALIDO","")
A5: 20260301 | B5: 117070000 | C5: 0 | D5: VIGENCIA ACTUAL | E5: ENTIDADES TERRITORIALES - SALUD | F5: =LEFT(CUIPO_datos_abiertos[[#This Row],[COD_PROGRAMATICO_MGA]],4) -> 1903 | G5: 1903001 | H5: No aplica | I5: SPC - E1 GOBERNABILIDAD Y GOBERNANZA - L1 DESARROLLO INSTITUCIONAL Y SECTORIAL - PLANEACIÓN INTEGRAL EN SALUD | J5: INGRESOS CORRIENTES DE DESTINACION ESPECIFICA POR ACTO ADMINISTRATIVO | K5: CON SITUACION DE FONDOS | L5: NO APLICA | M5: NO APLICA | N5: 9407100 | O5: 9407100 | P5: 6478400 | Q5: =IF(AND(LEN(CUIPO_datos_abiertos[[#This Row],[COD_PROGRAMATICO_MGA]])=7,ISNUMBER(VALUE(CUIPO_datos_abiertos[[#This Row],[COD_PROGRAMATICO_MGA]]))),"VALIDO","") -> VALIDO
A6: 20260301 | B6: 117070000 | C6: 202500000049907 | D6: VIGENCIA ACTUAL | E6: ENTIDADES TERRITORIALES - EDUCACION | F6: =LEFT(CUIPO_datos_abiertos[[#This Row],[COD_PROGRAMATICO_MGA]],4) -> 2201 | G6: 2201071 | H6: No aplica | I6: PERSONAL-DOCENTES | J6: SGP-EDUCACION-PRESTACION DE SERVICIOS | K6: CON SITUACION DE FONDOS | L6: NO APLICA | M6: NO APLICA | N6: 4265746351 | O6: 4265746351 | P6: 4265746351 | Q6: =IF(AND(LEN(CUIPO_datos_abiertos[[#This Row],[COD_PROGRAMATICO_MGA]])=7,ISNUMBER(VALUE(CUIPO_datos_abiertos[[#This Row],[COD_PROGRAMATICO_MGA]]))),"VALIDO","") -> VALIDO
A7: 20251201 | B7: 117070000 | C7: 0 | D7: VIGENCIA ACTUAL | E7: ENTIDADES TERRITORIALES - ASAMBLEA | F7: =LEFT(CUIPO_datos_abiertos[[#This Row],[COD_PROGRAMATICO_MGA]],4) -> NO A | G7: NO APLICA | H7: NO APLICA | I7: NO APLICA | J7: NO APLICA | K7: NO APLICA | L7: NO APLICA | M7: NO APLICA | N7: 4595256927 | O7: 4595256927 | P7: 4595256927 | Q7: =IF(AND(LEN(CUIPO_datos_abiertos[[#This Row],[COD_PROGRAMATICO_MGA]])=7,ISNUMBER(VALUE(CUIPO_datos_abiertos[[#This Row],[COD_PROGRAMATICO_MGA]]))),"VALIDO","")
A8: 20251201 | B8: 117070000 | C8: 0,00E+00 | D8: VIGENCIA ACTUAL | E8: ENTIDADES TERRITORIALES - SALUD | F8: =LEFT(CUIPO_datos_abiertos[[#This Row],[COD_PROGRAMATICO_MGA]],4) -> 0 | G8: 0 | H8: No aplica | I8: OGS - FUNCIONAMIENTO | J8: IMPUESTO SOBRE APUESTAS MUTUAS | K8: CON SITUACION DE FONDOS | L8: NO APLICA | M8: NO APLICA | N8: 195352588 | O8: 195056705 | P8: 195056705 | Q8: =IF(AND(LEN(CUIPO_datos_abiertos[[#This Row],[COD_PROGRAMATICO_MGA]])=7,ISNUMBER(VALUE(CUIPO_datos_abiertos[[#This Row],[COD_PROGRAMATICO_MGA]]))),"VALIDO","")
A9: 20251201 | B9: 117070000 | C9: 0 | D9: VIGENCIA ACTUAL | E9: ENTIDADES TERRITORIALES - ADMINISTRACION CENTRAL | F9: =LEFT(CUIPO_datos_abiertos[[#This Row],[COD_PROGRAMATICO_MGA]],4) -> 0 | G9: 0 | H9: No aplica | I9: NO APLICA | J9: INGRESOS CORRIENTES DE LIBRE DESTINACION | K9: CON SITUACION DE FONDOS | L9: NO APLICA | M9: NO APLICA | N9: 1047453500 | O9: 1047453500 | P9: 1047453500 | Q9: =IF(AND(LEN(CUIPO_datos_abiertos[[#This Row],[COD_PROGRAMATICO_MGA]])=7,ISNUMBER(VALUE(CUIPO_datos_abiertos[[#This Row],[COD_PROGRAMATICO_MGA]]))),"VALIDO","")
A10: 20251201 | B10: 117070000 | C10: 0 | D10: VIGENCIA ACTUAL | E10: ENTIDADES TERRITORIALES - SALUD | F10: =LEFT(CUIPO_datos_abiertos[[#This Row],[COD_PROGRAMATICO_MGA]],4) -> NO A | G10: NO APLICA | H10: NO APLICA | I10: NO APLICA | J10: NO APLICA | K10: NO APLICA | L10: NO APLICA | M10: NO APLICA | N10: 16114170865 | O10: 16114170865 | P10: 16114170865 | Q10: =IF(AND(LEN(CUIPO_datos_abiertos[[#This Row],[COD_PROGRAMATICO_MGA]])=7,ISNUMBER(VALUE(CUIPO_datos_abiertos[[#This Row],[COD_PROGRAMATICO_MGA]]))),"VALIDO","")
A11: 20260301 | B11: 117070000 | C11: 0 | D11: VIGENCIAS FUTURAS - VIGENCIA ACTUAL | E11: ENTIDADES TERRITORIALES - ADMINISTRACION CENTRAL | F11: =LEFT(CUIPO_datos_abiertos[[#This Row],[COD_PROGRAMATICO_MGA]],4) -> NO A | G11: NO APLICA | H11: NO APLICA | I11: NO APLICA | J11: NO APLICA | K11: NO APLICA | L11: NO APLICA | M11: NO APLICA | N11: 565000000 | O11: 565000000 | P11: 565000000 | Q11: =IF(AND(LEN(CUIPO_datos_abiertos[[#This Row],[COD_PROGRAMATICO_MGA]])=7,ISNUMBER(VALUE(CUIPO_datos_abiertos[[#This Row],[COD_PROGRAMATICO_MGA]]))),"VALIDO","")
A12: 20251201 | B12: 117070000 | C12: 2024002700170 | D12: VIGENCIA ACTUAL | E12: ENTIDADES TERRITORIALES - EDUCACION | F12: =LEFT(CUIPO_datos_abiertos[[#This Row],[COD_PROGRAMATICO_MGA]],4) -> 2201 | G12: 2201071 | H12: No aplica | I12: PERSONAL-DIRECTIVOS DOCENTES | J12: SGP-EDUCACION-PRESTACION DE SERVICIOS | K12: CON SITUACION DE FONDOS | L12: NO APLICA | M12: Instituto Colombiano de Bienestar Familiar | N12: 1491643600 | O12: 1491643600 | P12: 1491643600 | Q12: =IF(AND(LEN(CUIPO_datos_abiertos[[#This Row],[COD_PROGRAMATICO_MGA]])=7,ISNUMBER(VALUE(CUIPO_datos_abiertos[[#This Row],[COD_PROGRAMATICO_MGA]]))),"VALIDO","") -> VALIDO
A13: 20251201 | B13: 117070000 | C13: 202400000006014 | D13: VIGENCIA ACTUAL | E13: ENTIDADES TERRITORIALES - ADMINISTRACION CENTRAL | F13: =LEFT(CUIPO_datos_abiertos[[#This Row],[COD_PROGRAMATICO_MGA]],4) -> 4502 | G13: 4502038 | H13: Otros servicios de la administracion publica n c p | I13: NO APLICA | J13: ICLD DEPARTAMENTOS PARA FONPET | K13: CON SITUACION DE FONDOS | L13: NO APLICA | M13: NO APLICA | N13: 56000105 | O13: 56000105 | P13: 56000105 | Q13: =IF(AND(LEN(CUIPO_datos_abiertos[[#This Row],[COD_PROGRAMATICO_MGA]])=7,ISNUMBER(VALUE(CUIPO_datos_abiertos[[#This Row],[COD_PROGRAMATICO_MGA]]))),"VALIDO","") -> VALIDO
... A1649: 20260601 | B1649: 117070000 | C1649: 0 | D1649: VIGENCIA ACTUAL | E1649: ENTIDADES TERRITORIALES - SALUD | F1649: =LEFT(CUIPO_datos_abiertos[[#This Row],[COD_PROGRAMATICO_MGA]],4) -> NO A | G1649: NO APLICA | H1649: NO APLICA | I1649: NO APLICA | J1649: NO APLICA | K1649: NO APLICA | L1649: NO APLICA | M1649: NO APLICA | N1649: 8374260033 | O1649: 8374260033 | P1649: 8374260033 | Q1649: =IF(AND(LEN(CUIPO_datos_abiertos[[#This Row],[COD_PROGRAMATICO_MGA]])=7,ISNUMBER(VALUE(CUIPO_datos_abiertos[[#This Row],[COD_PROGRAMATICO_MGA]]))),"VALIDO","")

Sheet CUIPO-PIIP
A1: PROYECTOS CON COMPROMISOS EN CUIPO | D1: CRUCE PIIP - LLAVE BPIN
A2: PERIODO | B2: BPIN | C2: PRODUCTO CUIPO | D2: PRODUCTO PIIP | E2: NUM PRODUCTOS CUIPO | F2: NUM PRODUCTOS PIIP | G2: INCONSISTENCIA | H2: NUM PRODUCTOS QUE COINCIDEN | I2: TIPO DE COINCIDENCIA | K2: Notas
A3: {=_xlfn.LET(_xlpm.array_cols,_xlfn.MAP(CUIPO_datos_abiertos[#Headers],_xlfn.LAMBDA(_xlpm.col,IF(OR(_xlpm.col="PERIODO",_xlpm.col="BPIN"),COLUMN(_xlpm.col),""))),_xlpm.filtro_cols,_xlfn._xlws.FILTER(_xlpm.array_cols,_xlpm.array_cols<>""),_xlpm.base,_xlfn.UNIQUE(_xlfn._xlws.FILTER(_xlfn.CHOOSECOLS(CUIPO_datos_abiertos[],_xlpm.filtro_cols),(CUIPO_datos_abiertos[ES_PRODUCTO_VALIDO]="VALIDO")*(CUIPO_datos_abiertos[PERIODO]='Reporte'!$B$1)*(CUIPO_datos_abiertos[COMPROMISOS]<>0))),_xlpm.base)} -> 20260601 | B3: 0 | C3: {=_xlfn.TEXTJOIN(", ",TRUE,_xlfn.UNIQUE(_xlfn._xlws.FILTER(CUIPO_datos_abiertos[COD_PROGRAMATICO_MGA],(CUIPO_datos_abiertos[BPIN]=B3)*(CUIPO_datos_abiertos[PERIODO]='CUIPO-PIIP'!A3)*(CUIPO_datos_abiertos[ES_PRODUCTO_VALIDO]="VALIDO"),"")))} -> 1903001, 4599003, 2402001 | D3: {=_xlfn.TEXTJOIN(", ",TRUE,_xlfn._xlws.FILTER(EjecucionPIIP[CodigoProducto],(EjecucionPIIP[Bpin]='CUIPO-PIIP'!B3)*(EjecucionPIIP[Periodo]='CUIPO-PIIP'!A3),""))} | E3: {=_xlfn.LET(_xlpm.productos_cuipo,_xlfn.UNIQUE(_xlfn._xlws.FILTER(CUIPO_datos_abiertos[COD_PROGRAMATICO_MGA],(CUIPO_datos_abiertos[BPIN]=B3)*(CUIPO_datos_abiertos[PERIODO]=A3)*(CUIPO_datos_abiertos[ES_PRODUCTO_VALIDO]="VALIDO"),"")),_xlpm.num_productos_cuipo,COUNTA(_xlpm.productos_cuipo),_xlpm.num_productos_cuipo)} -> 3 | F3: {=_xlfn.LET(_xlpm.productos_piip,_xlfn._xlws.FILTER(EjecucionPIIP[CodigoProducto],(EjecucionPIIP[Bpin]=B3)*(EjecucionPIIP[Periodo]=A3),""),_xlpm.num_productos_piip,COUNTA(_xlpm.productos_piip),_xlpm.num_productos_piip)} -> 1 | G3: {=_xlfn.LET(_xlpm.productos_piip,_xlfn._xlws.FILTER(EjecucionPIIP[CodigoProducto],(EjecucionPIIP[Bpin]=B3)*(EjecucionPIIP[Periodo]=A3),""),_xlpm.productos_cuipo,_xlfn.UNIQUE(_xlfn._xlws.FILTER(CUIPO_datos_abiertos[COD_PROGRAMATICO_MGA],(CUIPO_datos_abiertos[BPIN]=B3)*(CUIPO_datos_abiertos[PERIODO]=A3)*(CUIPO_datos_abiertos[ES_PRODUCTO_VALIDO]="VALIDO"),"")),_xlpm.num_productos_cuipo,COUNTA(_xlpm.productos_cuipo),_xlpm.num_productos_piip,COUNTA(_xlpm.productos_piip),IF(AND(C3<>"",D3<>""),IF(_xlpm.num_productos_cuipo>_xlpm.num_productos_piip,"Inconsistencia",""),""))} | H3: {=_xlfn.LET(_xlpm.productos_piip,_xlfn._xlws.FILTER(EjecucionPIIP[CodigoProducto],(EjecucionPIIP[Bpin]=B3)*(EjecucionPIIP[Periodo]=A3),""),_xlpm.productos_cuipo,_xlfn.UNIQUE(_xlfn._xlws.FILTER(CUIPO_datos_abiertos[COD_PROGRAMATICO_MGA],(CUIPO_datos_abiertos[BPIN]=B3)*(CUIPO_datos_abiertos[PERIODO]=A3)*(CUIPO_datos_abiertos[ES_PRODUCTO_VALIDO]="VALIDO"),"")),_xlpm.eval,COUNT(_xlfn.MAP(_xlpm.productos_cuipo,_xlfn.LAMBDA(_xlpm.x,FIND(_xlpm.x,_xlfn.TEXTJOIN(",",TRUE,_xlpm.productos_piip))))),_xlpm.num_productos_cuipo,COUNTA(_xlpm.productos_cuipo),_xlpm.num_productos_piip,COUNTA(_xlpm.productos_piip),IF(AND(C3<>"",D3<>"",G3<>"Inconsistencia"),TRANSPOSE(_xlpm.eval),""))} | I3: =IF(AND(E3<>"",F3<>"",H3<>""),IF(H3=0,"No coinciden",IF(AND(E3=F3,F3=H3),"Coinciden","No coinciden todos")),"") | K3: La columna inconsistencia verifica si el número de productos reportados en CUIPO es mayor que el número de productos en PIIP
A4: 20260601 | B4: 202500000050246 | C4: {=_xlfn.TEXTJOIN(", ",TRUE,_xlfn.UNIQUE(_xlfn._xlws.FILTER(CUIPO_datos_abiertos[COD_PROGRAMATICO_MGA],(CUIPO_datos_abiertos[BPIN]=B4)*(CUIPO_datos_abiertos[PERIODO]='CUIPO-PIIP'!A4)*(CUIPO_datos_abiertos[ES_PRODUCTO_VALIDO]="VALIDO"),"")))} -> 4599023 | D4: {=_xlfn.TEXTJOIN(", ",TRUE,_xlfn._xlws.FILTER(EjecucionPIIP[CodigoProducto],(EjecucionPIIP[Bpin]='CUIPO-PIIP'!B4)*(EjecucionPIIP[Periodo]='CUIPO-PIIP'!A4),""))} -> 4599023 | E4: {=_xlfn.LET(_xlpm.productos_cuipo,_xlfn.UNIQUE(_xlfn._xlws.FILTER(CUIPO_datos_abiertos[COD_PROGRAMATICO_MGA],(CUIPO_datos_abiertos[BPIN]=B4)*(CUIPO_datos_abiertos[PERIODO]=A4)*(CUIPO_datos_abiertos[ES_PRODUCTO_VALIDO]="VALIDO"),"")),_xlpm.num_productos_cuipo,COUNTA(_xlpm.productos_cuipo),_xlpm.num_productos_cuipo)} -> 1 | F4: {=_xlfn.LET(_xlpm.productos_piip,_xlfn._xlws.FILTER(EjecucionPIIP[CodigoProducto],(EjecucionPIIP[Bpin]=B4)*(EjecucionPIIP[Periodo]=A4),""),_xlpm.num_productos_piip,COUNTA(_xlpm.productos_piip),_xlpm.num_productos_piip)} -> 1 | G4: {=_xlfn.LET(_xlpm.productos_piip,_xlfn._xlws.FILTER(EjecucionPIIP[CodigoProducto],(EjecucionPIIP[Bpin]=B4)*(EjecucionPIIP[Periodo]=A4),""),_xlpm.productos_cuipo,_xlfn.UNIQUE(_xlfn._xlws.FILTER(CUIPO_datos_abiertos[COD_PROGRAMATICO_MGA],(CUIPO_datos_abiertos[BPIN]=B4)*(CUIPO_datos_abiertos[PERIODO]=A4)*(CUIPO_datos_abiertos[ES_PRODUCTO_VALIDO]="VALIDO"),"")),_xlpm.num_productos_cuipo,COUNTA(_xlpm.productos_cuipo),_xlpm.num_productos_piip,COUNTA(_xlpm.productos_piip),IF(AND(C4<>"",D4<>""),IF(_xlpm.num_productos_cuipo>_xlpm.num_productos_piip,"Inconsistencia",""),""))} | H4: {=_xlfn.LET(_xlpm.productos_piip,_xlfn._xlws.FILTER(EjecucionPIIP[CodigoProducto],(EjecucionPIIP[Bpin]=B4)*(EjecucionPIIP[Periodo]=A4),""),_xlpm.productos_cuipo,_xlfn.UNIQUE(_xlfn._xlws.FILTER(CUIPO_datos_abiertos[COD_PROGRAMATICO_MGA],(CUIPO_datos_abiertos[BPIN]=B4)*(CUIPO_datos_abiertos[PERIODO]=A4)*(CUIPO_datos_abiertos[ES_PRODUCTO_VALIDO]="VALIDO"),"")),_xlpm.eval,COUNT(_xlfn.MAP(_xlpm.productos_cuipo,_xlfn.LAMBDA(_xlpm.x,FIND(_xlpm.x,_xlfn.TEXTJOIN(",",TRUE,_xlpm.productos_piip))))),_xlpm.num_productos_cuipo,COUNTA(_xlpm.productos_cuipo),_xlpm.num_productos_piip,COUNTA(_xlpm.productos_piip),IF(AND(C4<>"",D4<>"",G4<>"Inconsistencia"),TRANSPOSE(_xlpm.eval),""))} -> 1 | I4: =IF(AND(E4<>"",F4<>"",H4<>""),IF(H4=0,"No coinciden",IF(AND(E4=F4,F4=H4),"Coinciden","No coinciden todos")),"") -> Coinciden
A5: 20260601 | B5: 202500000042332 | C5: {=_xlfn.TEXTJOIN(", ",TRUE,_xlfn.UNIQUE(_xlfn._xlws.FILTER(CUIPO_datos_abiertos[COD_PROGRAMATICO_MGA],(CUIPO_datos_abiertos[BPIN]=B5)*(CUIPO_datos_abiertos[PERIODO]='CUIPO-PIIP'!A5)*(CUIPO_datos_abiertos[ES_PRODUCTO_VALIDO]="VALIDO"),"")))} -> 4104020 | D5: {=_xlfn.TEXTJOIN(", ",TRUE,_xlfn._xlws.FILTER(EjecucionPIIP[CodigoProducto],(EjecucionPIIP[Bpin]='CUIPO-PIIP'!B5)*(EjecucionPIIP[Periodo]='CUIPO-PIIP'!A5),""))} -> 4104020 | E5: {=_xlfn.LET(_xlpm.productos_cuipo,_xlfn.UNIQUE(_xlfn._xlws.FILTER(CUIPO_datos_abiertos[COD_PROGRAMATICO_MGA],(CUIPO_datos_abiertos[BPIN]=B5)*(CUIPO_datos_abiertos[PERIODO]=A5)*(CUIPO_datos_abiertos[ES_PRODUCTO_VALIDO]="VALIDO"),"")),_xlpm.num_productos_cuipo,COUNTA(_xlpm.productos_cuipo),_xlpm.num_productos_cuipo)} -> 1 | F5: {=_xlfn.LET(_xlpm.productos_piip,_xlfn._xlws.FILTER(EjecucionPIIP[CodigoProducto],(EjecucionPIIP[Bpin]=B5)*(EjecucionPIIP[Periodo]=A5),""),_xlpm.num_productos_piip,COUNTA(_xlpm.productos_piip),_xlpm.num_productos_piip)} -> 1 | G5: {=_xlfn.LET(_xlpm.productos_piip,_xlfn._xlws.FILTER(EjecucionPIIP[CodigoProducto],(EjecucionPIIP[Bpin]=B5)*(EjecucionPIIP[Periodo]=A5),""),_xlpm.productos_cuipo,_xlfn.UNIQUE(_xlfn._xlws.FILTER(CUIPO_datos_abiertos[COD_PROGRAMATICO_MGA],(CUIPO_datos_abiertos[BPIN]=B5)*(CUIPO_datos_abiertos[PERIODO]=A5)*(CUIPO_datos_abiertos[ES_PRODUCTO_VALIDO]="VALIDO"),"")),_xlpm.num_productos_cuipo,COUNTA(_xlpm.productos_cuipo),_xlpm.num_productos_piip,COUNTA(_xlpm.productos_piip),IF(AND(C5<>"",D5<>""),IF(_xlpm.num_productos_cuipo>_xlpm.num_productos_piip,"Inconsistencia",""),""))} | H5: {=_xlfn.LET(_xlpm.productos_piip,_xlfn._xlws.FILTER(EjecucionPIIP[CodigoProducto],(EjecucionPIIP[Bpin]=B5)*(EjecucionPIIP[Periodo]=A5),""),_xlpm.productos_cuipo,_xlfn.UNIQUE(_xlfn._xlws.FILTER(CUIPO_datos_abiertos[COD_PROGRAMATICO_MGA],(CUIPO_datos_abiertos[BPIN]=B5)*(CUIPO_datos_abiertos[PERIODO]=A5)*(CUIPO_datos_abiertos[ES_PRODUCTO_VALIDO]="VALIDO"),"")),_xlpm.eval,COUNT(_xlfn.MAP(_xlpm.productos_cuipo,_xlfn.LAMBDA(_xlpm.x,FIND(_xlpm.x,_xlfn.TEXTJOIN(",",TRUE,_xlpm.productos_piip))))),_xlpm.num_productos_cuipo,COUNTA(_xlpm.productos_cuipo),_xlpm.num_productos_piip,COUNTA(_xlpm.productos_piip),IF(AND(C5<>"",D5<>"",G5<>"Inconsistencia"),TRANSPOSE(_xlpm.eval),""))} -> 1 | I5: =IF(AND(E5<>"",F5<>"",H5<>""),IF(H5=0,"No coinciden",IF(AND(E5=F5,F5=H5),"Coinciden","No coinciden todos")),"") -> Coinciden
A6: 20260601 | B6: 2024002700156 | C6: {=_xlfn.TEXTJOIN(", ",TRUE,_xlfn.UNIQUE(_xlfn._xlws.FILTER(CUIPO_datos_abiertos[COD_PROGRAMATICO_MGA],(CUIPO_datos_abiertos[BPIN]=B6)*(CUIPO_datos_abiertos[PERIODO]='CUIPO-PIIP'!A6)*(CUIPO_datos_abiertos[ES_PRODUCTO_VALIDO]="VALIDO"),"")))} -> 4599002 | D6: {=_xlfn.TEXTJOIN(", ",TRUE,_xlfn._xlws.FILTER(EjecucionPIIP[CodigoProducto],(EjecucionPIIP[Bpin]='CUIPO-PIIP'!B6)*(EjecucionPIIP[Periodo]='CUIPO-PIIP'!A6),""))} | E6: {=_xlfn.LET(_xlpm.productos_cuipo,_xlfn.UNIQUE(_xlfn._xlws.FILTER(CUIPO_datos_abiertos[COD_PROGRAMATICO_MGA],(CUIPO_datos_abiertos[BPIN]=B6)*(CUIPO_datos_abiertos[PERIODO]=A6)*(CUIPO_datos_abiertos[ES_PRODUCTO_VALIDO]="VALIDO"),"")),_xlpm.num_productos_cuipo,COUNTA(_xlpm.productos_cuipo),_xlpm.num_productos_cuipo)} -> 1 | F6: {=_xlfn.LET(_xlpm.productos_piip,_xlfn._xlws.FILTER(EjecucionPIIP[CodigoProducto],(EjecucionPIIP[Bpin]=B6)*(EjecucionPIIP[Periodo]=A6),""),_xlpm.num_productos_piip,COUNTA(_xlpm.productos_piip),_xlpm.num_productos_piip)} -> 1 | G6: {=_xlfn.LET(_xlpm.productos_piip,_xlfn._xlws.FILTER(EjecucionPIIP[CodigoProducto],(EjecucionPIIP[Bpin]=B6)*(EjecucionPIIP[Periodo]=A6),""),_xlpm.productos_cuipo,_xlfn.UNIQUE(_xlfn._xlws.FILTER(CUIPO_datos_abiertos[COD_PROGRAMATICO_MGA],(CUIPO_datos_abiertos[BPIN]=B6)*(CUIPO_datos_abiertos[PERIODO]=A6)*(CUIPO_datos_abiertos[ES_PRODUCTO_VALIDO]="VALIDO"),"")),_xlpm.num_productos_cuipo,COUNTA(_xlpm.productos_cuipo),_xlpm.num_productos_piip,COUNTA(_xlpm.productos_piip),IF(AND(C6<>"",D6<>""),IF(_xlpm.num_productos_cuipo>_xlpm.num_productos_piip,"Inconsistencia",""),""))} | H6: {=_xlfn.LET(_xlpm.productos_piip,_xlfn._xlws.FILTER(EjecucionPIIP[CodigoProducto],(EjecucionPIIP[Bpin]=B6)*(EjecucionPIIP[Periodo]=A6),""),_xlpm.productos_cuipo,_xlfn.UNIQUE(_xlfn._xlws.FILTER(CUIPO_datos_abiertos[COD_PROGRAMATICO_MGA],(CUIPO_datos_abiertos[BPIN]=B6)*(CUIPO_datos_abiertos[PERIODO]=A6)*(CUIPO_datos_abiertos[ES_PRODUCTO_VALIDO]="VALIDO"),"")),_xlpm.eval,COUNT(_xlfn.MAP(_xlpm.productos_cuipo,_xlfn.LAMBDA(_xlpm.x,FIND(_xlpm.x,_xlfn.TEXTJOIN(",",TRUE,_xlpm.productos_piip))))),_xlpm.num_productos_cuipo,COUNTA(_xlpm.productos_cuipo),_xlpm.num_productos_piip,COUNTA(_xlpm.productos_piip),IF(AND(C6<>"",D6<>"",G6<>"Inconsistencia"),TRANSPOSE(_xlpm.eval),""))} | I6: =IF(AND(E6<>"",F6<>"",H6<>""),IF(H6=0,"No coinciden",IF(AND(E6=F6,F6=H6),"Coinciden","No coinciden todos")),"")
A7: 20260601 | B7: 202500000047500 | C7: {=_xlfn.TEXTJOIN(", ",TRUE,_xlfn.UNIQUE(_xlfn._xlws.FILTER(CUIPO_datos_abiertos[COD_PROGRAMATICO_MGA],(CUIPO_datos_abiertos[BPIN]=B7)*(CUIPO_datos_abiertos[PERIODO]='CUIPO-PIIP'!A7)*(CUIPO_datos_abiertos[ES_PRODUCTO_VALIDO]="VALIDO"),"")))} -> 1906039, 1905050, 1901007, 1903038, 1905026, 1901131, 1905028, 1905027, 1901128, 1905025, 1905021, 1905023 | D7: {=_xlfn.TEXTJOIN(", ",TRUE,_xlfn._xlws.FILTER(EjecucionPIIP[CodigoProducto],(EjecucionPIIP[Bpin]='CUIPO-PIIP'!B7)*(EjecucionPIIP[Periodo]='CUIPO-PIIP'!A7),""))} -> 1905050 | E7: {=_xlfn.LET(_xlpm.productos_cuipo,_xlfn.UNIQUE(_xlfn._xlws.FILTER(CUIPO_datos_abiertos[COD_PROGRAMATICO_MGA],(CUIPO_datos_abiertos[BPIN]=B7)*(CUIPO_datos_abiertos[PERIODO]=A7)*(CUIPO_datos_abiertos[ES_PRODUCTO_VALIDO]="VALIDO"),"")),_xlpm.num_productos_cuipo,COUNTA(_xlpm.productos_cuipo),_xlpm.num_productos_cuipo)} -> 12 | F7: {=_xlfn.LET(_xlpm.productos_piip,_xlfn._xlws.FILTER(EjecucionPIIP[CodigoProducto],(EjecucionPIIP[Bpin]=B7)*(EjecucionPIIP[Periodo]=A7),""),_xlpm.num_productos_piip,COUNTA(_xlpm.productos_piip),_xlpm.num_productos_piip)} -> 1 | G7: {=_xlfn.LET(_xlpm.productos_piip,_xlfn._xlws.FILTER(EjecucionPIIP[CodigoProducto],(EjecucionPIIP[Bpin]=B7)*(EjecucionPIIP[Periodo]=A7),""),_xlpm.productos_cuipo,_xlfn.UNIQUE(_xlfn._xlws.FILTER(CUIPO_datos_abiertos[COD_PROGRAMATICO_MGA],(CUIPO_datos_abiertos[BPIN]=B7)*(CUIPO_datos_abiertos[PERIODO]=A7)*(CUIPO_datos_abiertos[ES_PRODUCTO_VALIDO]="VALIDO"),"")),_xlpm.num_productos_cuipo,COUNTA(_xlpm.productos_cuipo),_xlpm.num_productos_piip,COUNTA(_xlpm.productos_piip),IF(AND(C7<>"",D7<>""),IF(_xlpm.num_productos_cuipo>_xlpm.num_productos_piip,"Inconsistencia",""),""))} -> Inconsistencia | H7: {=_xlfn.LET(_xlpm.productos_piip,_xlfn._xlws.FILTER(EjecucionPIIP[CodigoProducto],(EjecucionPIIP[Bpin]=B7)*(EjecucionPIIP[Periodo]=A7),""),_xlpm.productos_cuipo,_xlfn.UNIQUE(_xlfn._xlws.FILTER(CUIPO_datos_abiertos[COD_PROGRAMATICO_MGA],(CUIPO_datos_abiertos[BPIN]=B7)*(CUIPO_datos_abiertos[PERIODO]=A7)*(CUIPO_datos_abiertos[ES_PRODUCTO_VALIDO]="VALIDO"),"")),_xlpm.eval,COUNT(_xlfn.MAP(_xlpm.productos_cuipo,_xlfn.LAMBDA(_xlpm.x,FIND(_xlpm.x,_xlfn.TEXTJOIN(",",TRUE,_xlpm.productos_piip))))),_xlpm.num_productos_cuipo,COUNTA(_xlpm.productos_cuipo),_xlpm.num_productos_piip,COUNTA(_xlpm.productos_piip),IF(AND(C7<>"",D7<>"",G7<>"Inconsistencia"),TRANSPOSE(_xlpm.eval),""))} | I7: =IF(AND(E7<>"",F7<>"",H7<>""),IF(H7=0,"No coinciden",IF(AND(E7=F7,F7=H7),"Coinciden","No coinciden todos")),"")
A8: 20260601 | B8: 202500000049907 | C8: {=_xlfn.TEXTJOIN(", ",TRUE,_xlfn.UNIQUE(_xlfn._xlws.FILTER(CUIPO_datos_abiertos[COD_PROGRAMATICO_MGA],(CUIPO_datos_abiertos[BPIN]=B8)*(CUIPO_datos_abiertos[PERIODO]='CUIPO-PIIP'!A8)*(CUIPO_datos_abiertos[ES_PRODUCTO_VALIDO]="VALIDO"),"")))} -> 2201071 | D8: {=_xlfn.TEXTJOIN(", ",TRUE,_xlfn._xlws.FILTER(EjecucionPIIP[CodigoProducto],(EjecucionPIIP[Bpin]='CUIPO-PIIP'!B8)*(EjecucionPIIP[Periodo]='CUIPO-PIIP'!A8),""))} -> 2201071 | E8: {=_xlfn.LET(_xlpm.productos_cuipo,_xlfn.UNIQUE(_xlfn._xlws.FILTER(CUIPO_datos_abiertos[COD_PROGRAMATICO_MGA],(CUIPO_datos_abiertos[BPIN]=B8)*(CUIPO_datos_abiertos[PERIODO]=A8)*(CUIPO_datos_abiertos[ES_PRODUCTO_VALIDO]="VALIDO"),"")),_xlpm.num_productos_cuipo,COUNTA(_xlpm.productos_cuipo),_xlpm.num_productos_cuipo)} -> 1 | F8: {=_xlfn.LET(_xlpm.productos_piip,_xlfn._xlws.FILTER(EjecucionPIIP[CodigoProducto],(EjecucionPIIP[Bpin]=B8)*(EjecucionPIIP[Periodo]=A8),""),_xlpm.num_productos_piip,COUNTA(_xlpm.productos_piip),_xlpm.num_productos_piip)} -> 1 | G8: {=_xlfn.LET(_xlpm.productos_piip,_xlfn._xlws.FILTER(EjecucionPIIP[CodigoProducto],(EjecucionPIIP[Bpin]=B8)*(EjecucionPIIP[Periodo]=A8),""),_xlpm.productos_cuipo,_xlfn.UNIQUE(_xlfn._xlws.FILTER(CUIPO_datos_abiertos[COD_PROGRAMATICO_MGA],(CUIPO_datos_abiertos[BPIN]=B8)*(CUIPO_datos_abiertos[PERIODO]=A8)*(CUIPO_datos_abiertos[ES_PRODUCTO_VALIDO]="VALIDO"),"")),_xlpm.num_productos_cuipo,COUNTA(_xlpm.productos_cuipo),_xlpm.num_productos_piip,COUNTA(_xlpm.productos_piip),IF(AND(C8<>"",D8<>""),IF(_xlpm.num_productos_cuipo>_xlpm.num_productos_piip,"Inconsistencia",""),""))} | H8: {=_xlfn.LET(_xlpm.productos_piip,_xlfn._xlws.FILTER(EjecucionPIIP[CodigoProducto],(EjecucionPIIP[Bpin]=B8)*(EjecucionPIIP[Periodo]=A8),""),_xlpm.productos_cuipo,_xlfn.UNIQUE(_xlfn._xlws.FILTER(CUIPO_datos_abiertos[COD_PROGRAMATICO_MGA],(CUIPO_datos_abiertos[BPIN]=B8)*(CUIPO_datos_abiertos[PERIODO]=A8)*(CUIPO_datos_abiertos[ES_PRODUCTO_VALIDO]="VALIDO"),"")),_xlpm.eval,COUNT(_xlfn.MAP(_xlpm.productos_cuipo,_xlfn.LAMBDA(_xlpm.x,FIND(_xlpm.x,_xlfn.TEXTJOIN(",",TRUE,_xlpm.productos_piip))))),_xlpm.num_productos_cuipo,COUNTA(_xlpm.productos_cuipo),_xlpm.num_productos_piip,COUNTA(_xlpm.productos_piip),IF(AND(C8<>"",D8<>"",G8<>"Inconsistencia"),TRANSPOSE(_xlpm.eval),""))} -> 1 | I8: =IF(AND(E8<>"",F8<>"",H8<>""),IF(H8=0,"No coinciden",IF(AND(E8=F8,F8=H8),"Coinciden","No coinciden todos")),"") -> Coinciden
A9: 20260601 | B9: 2024002700063 | C9: {=_xlfn.TEXTJOIN(", ",TRUE,_xlfn.UNIQUE(_xlfn._xlws.FILTER(CUIPO_datos_abiertos[COD_PROGRAMATICO_MGA],(CUIPO_datos_abiertos[BPIN]=B9)*(CUIPO_datos_abiertos[PERIODO]='CUIPO-PIIP'!A9)*(CUIPO_datos_abiertos[ES_PRODUCTO_VALIDO]="VALIDO"),"")))} -> 4599025 | D9: {=_xlfn.TEXTJOIN(", ",TRUE,_xlfn._xlws.FILTER(EjecucionPIIP[CodigoProducto],(EjecucionPIIP[Bpin]='CUIPO-PIIP'!B9)*(EjecucionPIIP[Periodo]='CUIPO-PIIP'!A9),""))} | E9: {=_xlfn.LET(_xlpm.productos_cuipo,_xlfn.UNIQUE(_xlfn._xlws.FILTER(CUIPO_datos_abiertos[COD_PROGRAMATICO_MGA],(CUIPO_datos_abiertos[BPIN]=B9)*(CUIPO_datos_abiertos[PERIODO]=A9)*(CUIPO_datos_abiertos[ES_PRODUCTO_VALIDO]="VALIDO"),"")),_xlpm.num_productos_cuipo,COUNTA(_xlpm.productos_cuipo),_xlpm.num_productos_cuipo)} -> 1 | F9: {=_xlfn.LET(_xlpm.productos_piip,_xlfn._xlws.FILTER(EjecucionPIIP[CodigoProducto],(EjecucionPIIP[Bpin]=B9)*(EjecucionPIIP[Periodo]=A9),""),_xlpm.num_productos_piip,COUNTA(_xlpm.productos_piip),_xlpm.num_productos_piip)} -> 1 | G9: {=_xlfn.LET(_xlpm.productos_piip,_xlfn._xlws.FILTER(EjecucionPIIP[CodigoProducto],(EjecucionPIIP[Bpin]=B9)*(EjecucionPIIP[Periodo]=A9),""),_xlpm.productos_cuipo,_xlfn.UNIQUE(_xlfn._xlws.FILTER(CUIPO_datos_abiertos[COD_PROGRAMATICO_MGA],(CUIPO_datos_abiertos[BPIN]=B9)*(CUIPO_datos_abiertos[PERIODO]=A9)*(CUIPO_datos_abiertos[ES_PRODUCTO_VALIDO]="VALIDO"),"")),_xlpm.num_productos_cuipo,COUNTA(_xlpm.productos_cuipo),_xlpm.num_productos_piip,COUNTA(_xlpm.productos_piip),IF(AND(C9<>"",D9<>""),IF(_xlpm.num_productos_cuipo>_xlpm.num_productos_piip,"Inconsistencia",""),""))} | H9: {=_xlfn.LET(_xlpm.productos_piip,_xlfn._xlws.FILTER(EjecucionPIIP[CodigoProducto],(EjecucionPIIP[Bpin]=B9)*(EjecucionPIIP[Periodo]=A9),""),_xlpm.productos_cuipo,_xlfn.UNIQUE(_xlfn._xlws.FILTER(CUIPO_datos_abiertos[COD_PROGRAMATICO_MGA],(CUIPO_datos_abiertos[BPIN]=B9)*(CUIPO_datos_abiertos[PERIODO]=A9)*(CUIPO_datos_abiertos[ES_PRODUCTO_VALIDO]="VALIDO"),"")),_xlpm.eval,COUNT(_xlfn.MAP(_xlpm.productos_cuipo,_xlfn.LAMBDA(_xlpm.x,FIND(_xlpm.x,_xlfn.TEXTJOIN(",",TRUE,_xlpm.productos_piip))))),_xlpm.num_productos_cuipo,COUNTA(_xlpm.productos_cuipo),_xlpm.num_productos_piip,COUNTA(_xlpm.productos_piip),IF(AND(C9<>"",D9<>"",G9<>"Inconsistencia"),TRANSPOSE(_xlpm.eval),""))} | I9: =IF(AND(E9<>"",F9<>"",H9<>""),IF(H9=0,"No coinciden",IF(AND(E9=F9,F9=H9),"Coinciden","No coinciden todos")),"")
A10: 20260601 | B10: 202500000047955 | C10: {=_xlfn.TEXTJOIN(", ",TRUE,_xlfn.UNIQUE(_xlfn._xlws.FILTER(CUIPO_datos_abiertos[COD_PROGRAMATICO_MGA],(CUIPO_datos_abiertos[BPIN]=B10)*(CUIPO_datos_abiertos[PERIODO]='CUIPO-PIIP'!A10)*(CUIPO_datos_abiertos[ES_PRODUCTO_VALIDO]="VALIDO"),"")))} -> 1903035, 1903038 | D10: {=_xlfn.TEXTJOIN(", ",TRUE,_xlfn._xlws.FILTER(EjecucionPIIP[CodigoProducto],(EjecucionPIIP[Bpin]='CUIPO-PIIP'!B10)*(EjecucionPIIP[Periodo]='CUIPO-PIIP'!A10),""))} -> 1903035 | E10: {=_xlfn.LET(_xlpm.productos_cuipo,_xlfn.UNIQUE(_xlfn._xlws.FILTER(CUIPO_datos_abiertos[COD_PROGRAMATICO_MGA],(CUIPO_datos_abiertos[BPIN]=B10)*(CUIPO_datos_abiertos[PERIODO]=A10)*(CUIPO_datos_abiertos[ES_PRODUCTO_VALIDO]="VALIDO"),"")),_xlpm.num_productos_cuipo,COUNTA(_xlpm.productos_cuipo),_xlpm.num_productos_cuipo)} -> 2 | F10: {=_xlfn.LET(_xlpm.productos_piip,_xlfn._xlws.FILTER(EjecucionPIIP[CodigoProducto],(EjecucionPIIP[Bpin]=B10)*(EjecucionPIIP[Periodo]=A10),""),_xlpm.num_productos_piip,COUNTA(_xlpm.productos_piip),_xlpm.num_productos_piip)} -> 1 | G10: {=_xlfn.LET(_xlpm.productos_piip,_xlfn._xlws.FILTER(EjecucionPIIP[CodigoProducto],(EjecucionPIIP[Bpin]=B10)*(EjecucionPIIP[Periodo]=A10),""),_xlpm.productos_cuipo,_xlfn.UNIQUE(_xlfn._xlws.FILTER(CUIPO_datos_abiertos[COD_PROGRAMATICO_MGA],(CUIPO_datos_abiertos[BPIN]=B10)*(CUIPO_datos_abiertos[PERIODO]=A10)*(CUIPO_datos_abiertos[ES_PRODUCTO_VALIDO]="VALIDO"),"")),_xlpm.num_productos_cuipo,COUNTA(_xlpm.productos_cuipo),_xlpm.num_productos_piip,COUNTA(_xlpm.productos_piip),IF(AND(C10<>"",D10<>""),IF(_xlpm.num_productos_cuipo>_xlpm.num_productos_piip,"Inconsistencia",""),""))} -> Inconsistencia | H10: {=_xlfn.LET(_xlpm.productos_piip,_xlfn._xlws.FILTER(EjecucionPIIP[CodigoProducto],(EjecucionPIIP[Bpin]=B10)*(EjecucionPIIP[Periodo]=A10),""),_xlpm.productos_cuipo,_xlfn.UNIQUE(_xlfn._xlws.FILTER(CUIPO_datos_abiertos[COD_PROGRAMATICO_MGA],(CUIPO_datos_abiertos[BPIN]=B10)*(CUIPO_datos_abiertos[PERIODO]=A10)*(CUIPO_datos_abiertos[ES_PRODUCTO_VALIDO]="VALIDO"),"")),_xlpm.eval,COUNT(_xlfn.MAP(_xlpm.productos_cuipo,_xlfn.LAMBDA(_xlpm.x,FIND(_xlpm.x,_xlfn.TEXTJOIN(",",TRUE,_xlpm.productos_piip))))),_xlpm.num_productos_cuipo,COUNTA(_xlpm.productos_cuipo),_xlpm.num_productos_piip,COUNTA(_xlpm.productos_piip),IF(AND(C10<>"",D10<>"",G10<>"Inconsistencia"),TRANSPOSE(_xlpm.eval),""))} | I10: =IF(AND(E10<>"",F10<>"",H10<>""),IF(H10=0,"No coinciden",IF(AND(E10=F10,F10=H10),"Coinciden","No coinciden todos")),"")
A11: 20260601 | B11: 202500000047992 | C11: {=_xlfn.TEXTJOIN(", ",TRUE,_xlfn.UNIQUE(_xlfn._xlws.FILTER(CUIPO_datos_abiertos[COD_PROGRAMATICO_MGA],(CUIPO_datos_abiertos[BPIN]=B11)*(CUIPO_datos_abiertos[PERIODO]='CUIPO-PIIP'!A11)*(CUIPO_datos_abiertos[ES_PRODUCTO_VALIDO]="VALIDO"),"")))} -> 4502024 | D11: {=_xlfn.TEXTJOIN(", ",TRUE,_xlfn._xlws.FILTER(EjecucionPIIP[CodigoProducto],(EjecucionPIIP[Bpin]='CUIPO-PIIP'!B11)*(EjecucionPIIP[Periodo]='CUIPO-PIIP'!A11),""))} | E11: {=_xlfn.LET(_xlpm.productos_cuipo,_xlfn.UNIQUE(_xlfn._xlws.FILTER(CUIPO_datos_abiertos[COD_PROGRAMATICO_MGA],(CUIPO_datos_abiertos[BPIN]=B11)*(CUIPO_datos_abiertos[PERIODO]=A11)*(CUIPO_datos_abiertos[ES_PRODUCTO_VALIDO]="VALIDO"),"")),_xlpm.num_productos_cuipo,COUNTA(_xlpm.productos_cuipo),_xlpm.num_productos_cuipo)} -> 1 | F11: {=_xlfn.LET(_xlpm.productos_piip,_xlfn._xlws.FILTER(EjecucionPIIP[CodigoProducto],(EjecucionPIIP[Bpin]=B11)*(EjecucionPIIP[Periodo]=A11),""),_xlpm.num_productos_piip,COUNTA(_xlpm.productos_piip),_xlpm.num_productos_piip)} -> 1 | G11: {=_xlfn.LET(_xlpm.productos_piip,_xlfn._xlws.FILTER(EjecucionPIIP[CodigoProducto],(EjecucionPIIP[Bpin]=B11)*(EjecucionPIIP[Periodo]=A11),""),_xlpm.productos_cuipo,_xlfn.UNIQUE(_xlfn._xlws.FILTER(CUIPO_datos_abiertos[COD_PROGRAMATICO_MGA],(CUIPO_datos_abiertos[BPIN]=B11)*(CUIPO_datos_abiertos[PERIODO]=A11)*(CUIPO_datos_abiertos[ES_PRODUCTO_VALIDO]="VALIDO"),"")),_xlpm.num_productos_cuipo,COUNTA(_xlpm.productos_cuipo),_xlpm.num_productos_piip,COUNTA(_xlpm.productos_piip),IF(AND(C11<>"",D11<>""),IF(_xlpm.num_productos_cuipo>_xlpm.num_productos_piip,"Inconsistencia",""),""))} | H11: {=_xlfn.LET(_xlpm.productos_piip,_xlfn._xlws.FILTER(EjecucionPIIP[CodigoProducto],(EjecucionPIIP[Bpin]=B11)*(EjecucionPIIP[Periodo]=A11),""),_xlpm.productos_cuipo,_xlfn.UNIQUE(_xlfn._xlws.FILTER(CUIPO_datos_abiertos[COD_PROGRAMATICO_MGA],(CUIPO_datos_abiertos[BPIN]=B11)*(CUIPO_datos_abiertos[PERIODO]=A11)*(CUIPO_datos_abiertos[ES_PRODUCTO_VALIDO]="VALIDO"),"")),_xlpm.eval,COUNT(_xlfn.MAP(_xlpm.productos_cuipo,_xlfn.LAMBDA(_xlpm.x,FIND(_xlpm.x,_xlfn.TEXTJOIN(",",TRUE,_xlpm.productos_piip))))),_xlpm.num_productos_cuipo,COUNTA(_xlpm.productos_cuipo),_xlpm.num_productos_piip,COUNTA(_xlpm.productos_piip),IF(AND(C11<>"",D11<>"",G11<>"Inconsistencia"),TRANSPOSE(_xlpm.eval),""))} | I11: =IF(AND(E11<>"",F11<>"",H11<>""),IF(H11=0,"No coinciden",IF(AND(E11=F11,F11=H11),"Coinciden","No coinciden todos")),"")
A12: 20260601 | B12: 202600000000479 | C12: {=_xlfn.TEXTJOIN(", ",TRUE,_xlfn.UNIQUE(_xlfn._xlws.FILTER(CUIPO_datos_abiertos[COD_PROGRAMATICO_MGA],(CUIPO_datos_abiertos[BPIN]=B12)*(CUIPO_datos_abiertos[PERIODO]='CUIPO-PIIP'!A12)*(CUIPO_datos_abiertos[ES_PRODUCTO_VALIDO]="VALIDO"),"")))} -> 4502030 | D12: {=_xlfn.TEXTJOIN(", ",TRUE,_xlfn._xlws.FILTER(EjecucionPIIP[CodigoProducto],(EjecucionPIIP[Bpin]='CUIPO-PIIP'!B12)*(EjecucionPIIP[Periodo]='CUIPO-PIIP'!A12),""))} -> 4502001, 4502039, 4502024 | E12: {=_xlfn.LET(_xlpm.productos_cuipo,_xlfn.UNIQUE(_xlfn._xlws.FILTER(CUIPO_datos_abiertos[COD_PROGRAMATICO_MGA],(CUIPO_datos_abiertos[BPIN]=B12)*(CUIPO_datos_abiertos[PERIODO]=A12)*(CUIPO_datos_abiertos[ES_PRODUCTO_VALIDO]="VALIDO"),"")),_xlpm.num_productos_cuipo,COUNTA(_xlpm.productos_cuipo),_xlpm.num_productos_cuipo)} -> 1 | F12: {=_xlfn.LET(_xlpm.productos_piip,_xlfn._xlws.FILTER(EjecucionPIIP[CodigoProducto],(EjecucionPIIP[Bpin]=B12)*(EjecucionPIIP[Periodo]=A12),""),_xlpm.num_productos_piip,COUNTA(_xlpm.productos_piip),_xlpm.num_productos_piip)} -> 3 | G12: {=_xlfn.LET(_xlpm.productos_piip,_xlfn._xlws.FILTER(EjecucionPIIP[CodigoProducto],(EjecucionPIIP[Bpin]=B12)*(EjecucionPIIP[Periodo]=A12),""),_xlpm.productos_cuipo,_xlfn.UNIQUE(_xlfn._xlws.FILTER(CUIPO_datos_abiertos[COD_PROGRAMATICO_MGA],(CUIPO_datos_abiertos[BPIN]=B12)*(CUIPO_datos_abiertos[PERIODO]=A12)*(CUIPO_datos_abiertos[ES_PRODUCTO_VALIDO]="VALIDO"),"")),_xlpm.num_productos_cuipo,COUNTA(_xlpm.productos_cuipo),_xlpm.num_productos_piip,COUNTA(_xlpm.productos_piip),IF(AND(C12<>"",D12<>""),IF(_xlpm.num_productos_cuipo>_xlpm.num_productos_piip,"Inconsistencia",""),""))} | H12: {=_xlfn.LET(_xlpm.productos_piip,_xlfn._xlws.FILTER(EjecucionPIIP[CodigoProducto],(EjecucionPIIP[Bpin]=B12)*(EjecucionPIIP[Periodo]=A12),""),_xlpm.productos_cuipo,_xlfn.UNIQUE(_xlfn._xlws.FILTER(CUIPO_datos_abiertos[COD_PROGRAMATICO_MGA],(CUIPO_datos_abiertos[BPIN]=B12)*(CUIPO_datos_abiertos[PERIODO]=A12)*(CUIPO_datos_abiertos[ES_PRODUCTO_VALIDO]="VALIDO"),"")),_xlpm.eval,COUNT(_xlfn.MAP(_xlpm.productos_cuipo,_xlfn.LAMBDA(_xlpm.x,FIND(_xlpm.x,_xlfn.TEXTJOIN(",",TRUE,_xlpm.productos_piip))))),_xlpm.num_productos_cuipo,COUNTA(_xlpm.productos_cuipo),_xlpm.num_productos_piip,COUNTA(_xlpm.productos_piip),IF(AND(C12<>"",D12<>"",G12<>"Inconsistencia"),TRANSPOSE(_xlpm.eval),""))} -> 0 | I12: =IF(AND(E12<>"",F12<>"",H12<>""),IF(H12=0,"No coinciden",IF(AND(E12=F12,F12=H12),"Coinciden","No coinciden todos")),"") -> No coinciden
A13: 20260601 | B13: 2024002700130 | C13: {=_xlfn.TEXTJOIN(", ",TRUE,_xlfn.UNIQUE(_xlfn._xlws.FILTER(CUIPO_datos_abiertos[COD_PROGRAMATICO_MGA],(CUIPO_datos_abiertos[BPIN]=B13)*(CUIPO_datos_abiertos[PERIODO]='CUIPO-PIIP'!A13)*(CUIPO_datos_abiertos[ES_PRODUCTO_VALIDO]="VALIDO"),"")))} -> 4503023 | D13: {=_xlfn.TEXTJOIN(", ",TRUE,_xlfn._xlws.FILTER(EjecucionPIIP[CodigoProducto],(EjecucionPIIP[Bpin]='CUIPO-PIIP'!B13)*(EjecucionPIIP[Periodo]='CUIPO-PIIP'!A13),""))} | E13: {=_xlfn.LET(_xlpm.productos_cuipo,_xlfn.UNIQUE(_xlfn._xlws.FILTER(CUIPO_datos_abiertos[COD_PROGRAMATICO_MGA],(CUIPO_datos_abiertos[BPIN]=B13)*(CUIPO_datos_abiertos[PERIODO]=A13)*(CUIPO_datos_abiertos[ES_PRODUCTO_VALIDO]="VALIDO"),"")),_xlpm.num_productos_cuipo,COUNTA(_xlpm.productos_cuipo),_xlpm.num_productos_cuipo)} -> 1 | F13: {=_xlfn.LET(_xlpm.productos_piip,_xlfn._xlws.FILTER(EjecucionPIIP[CodigoProducto],(EjecucionPIIP[Bpin]=B13)*(EjecucionPIIP[Periodo]=A13),""),_xlpm.num_productos_piip,COUNTA(_xlpm.productos_piip),_xlpm.num_productos_piip)} -> 1 | G13: {=_xlfn.LET(_xlpm.productos_piip,_xlfn._xlws.FILTER(EjecucionPIIP[CodigoProducto],(EjecucionPIIP[Bpin]=B13)*(EjecucionPIIP[Periodo]=A13),""),_xlpm.productos_cuipo,_xlfn.UNIQUE(_xlfn._xlws.FILTER(CUIPO_datos_abiertos[COD_PROGRAMATICO_MGA],(CUIPO_datos_abiertos[BPIN]=B13)*(CUIPO_datos_abiertos[PERIODO]=A13)*(CUIPO_datos_abiertos[ES_PRODUCTO_VALIDO]="VALIDO"),"")),_xlpm.num_productos_cuipo,COUNTA(_xlpm.productos_cuipo),_xlpm.num_productos_piip,COUNTA(_xlpm.productos_piip),IF(AND(C13<>"",D13<>""),IF(_xlpm.num_productos_cuipo>_xlpm.num_productos_piip,"Inconsistencia",""),""))} | H13: {=_xlfn.LET(_xlpm.productos_piip,_xlfn._xlws.FILTER(EjecucionPIIP[CodigoProducto],(EjecucionPIIP[Bpin]=B13)*(EjecucionPIIP[Periodo]=A13),""),_xlpm.productos_cuipo,_xlfn.UNIQUE(_xlfn._xlws.FILTER(CUIPO_datos_abiertos[COD_PROGRAMATICO_MGA],(CUIPO_datos_abiertos[BPIN]=B13)*(CUIPO_datos_abiertos[PERIODO]=A13)*(CUIPO_datos_abiertos[ES_PRODUCTO_VALIDO]="VALIDO"),"")),_xlpm.eval,COUNT(_xlfn.MAP(_xlpm.productos_cuipo,_xlfn.LAMBDA(_xlpm.x,FIND(_xlpm.x,_xlfn.TEXTJOIN(",",TRUE,_xlpm.productos_piip))))),_xlpm.num_productos_cuipo,COUNTA(_xlpm.productos_cuipo),_xlpm.num_productos_piip,COUNTA(_xlpm.productos_piip),IF(AND(C13<>"",D13<>"",G13<>"Inconsistencia"),TRANSPOSE(_xlpm.eval),""))} | I13: =IF(AND(E13<>"",F13<>"",H13<>""),IF(H13=0,"No coinciden",IF(AND(E13=F13,F13=H13),"Coinciden","No coinciden todos")),"")
A14: 20260601 | B14: 202600000012764 | C14: {=_xlfn.TEXTJOIN(", ",TRUE,_xlfn.UNIQUE(_xlfn._xlws.FILTER(CUIPO_datos_abiertos[COD_PROGRAMATICO_MGA],(CUIPO_datos_abiertos[BPIN]=B14)*(CUIPO_datos_abiertos[PERIODO]='CUIPO-PIIP'!A14)*(CUIPO_datos_abiertos[ES_PRODUCTO_VALIDO]="VALIDO"),"")))} -> 4301001 | D14: {=_xlfn.TEXTJOIN(", ",TRUE,_xlfn._xlws.FILTER(EjecucionPIIP[CodigoProducto],(EjecucionPIIP[Bpin]='CUIPO-PIIP'!B14)*(EjecucionPIIP[Periodo]='CUIPO-PIIP'!A14),""))} -> 4301001 | E14: {=_xlfn.LET(_xlpm.productos_cuipo,_xlfn.UNIQUE(_xlfn._xlws.FILTER(CUIPO_datos_abiertos[COD_PROGRAMATICO_MGA],(CUIPO_datos_abiertos[BPIN]=B14)*(CUIPO_datos_abiertos[PERIODO]=A14)*(CUIPO_datos_abiertos[ES_PRODUCTO_VALIDO]="VALIDO"),"")),_xlpm.num_productos_cuipo,COUNTA(_xlpm.productos_cuipo),_xlpm.num_productos_cuipo)} -> 1 | F14: {=_xlfn.LET(_xlpm.productos_piip,_xlfn._xlws.FILTER(EjecucionPIIP[CodigoProducto],(EjecucionPIIP[Bpin]=B14)*(EjecucionPIIP[Periodo]=A14),""),_xlpm.num_productos_piip,COUNTA(_xlpm.productos_piip),_xlpm.num_productos_piip)} -> 1 | G14: {=_xlfn.LET(_xlpm.productos_piip,_xlfn._xlws.FILTER(EjecucionPIIP[CodigoProducto],(EjecucionPIIP[Bpin]=B14)*(EjecucionPIIP[Periodo]=A14),""),_xlpm.productos_cuipo,_xlfn.UNIQUE(_xlfn._xlws.FILTER(CUIPO_datos_abiertos[COD_PROGRAMATICO_MGA],(CUIPO_datos_abiertos[BPIN]=B14)*(CUIPO_datos_abiertos[PERIODO]=A14)*(CUIPO_datos_abiertos[ES_PRODUCTO_VALIDO]="VALIDO"),"")),_xlpm.num_productos_cuipo,COUNTA(_xlpm.productos_cuipo),_xlpm.num_productos_piip,COUNTA(_xlpm.productos_piip),IF(AND(C14<>"",D14<>""),IF(_xlpm.num_productos_cuipo>_xlpm.num_productos_piip,"Inconsistencia",""),""))} | H14: {=_xlfn.LET(_xlpm.productos_piip,_xlfn._xlws.FILTER(EjecucionPIIP[CodigoProducto],(EjecucionPIIP[Bpin]=B14)*(EjecucionPIIP[Periodo]=A14),""),_xlpm.productos_cuipo,_xlfn.UNIQUE(_xlfn._xlws.FILTER(CUIPO_datos_abiertos[COD_PROGRAMATICO_MGA],(CUIPO_datos_abiertos[BPIN]=B14)*(CUIPO_datos_abiertos[PERIODO]=A14)*(CUIPO_datos_abiertos[ES_PRODUCTO_VALIDO]="VALIDO"),"")),_xlpm.eval,COUNT(_xlfn.MAP(_xlpm.productos_cuipo,_xlfn.LAMBDA(_xlpm.x,FIND(_xlpm.x,_xlfn.TEXTJOIN(",",TRUE,_xlpm.productos_piip))))),_xlpm.num_productos_cuipo,COUNTA(_xlpm.productos_cuipo),_xlpm.num_productos_piip,COUNTA(_xlpm.productos_piip),IF(AND(C14<>"",D14<>"",G14<>"Inconsistencia"),TRANSPOSE(_xlpm.eval),""))} -> 1 | I14: =IF(AND(E14<>"",F14<>"",H14<>""),IF(H14=0,"No coinciden",IF(AND(E14=F14,F14=H14),"Coinciden","No coinciden todos")),"") -> Coinciden
A15: 20260601 | B15: 202600000008787 | C15: {=_xlfn.TEXTJOIN(", ",TRUE,_xlfn.UNIQUE(_xlfn._xlws.FILTER(CUIPO_datos_abiertos[COD_PROGRAMATICO_MGA],(CUIPO_datos_abiertos[BPIN]=B15)*(CUIPO_datos_abiertos[PERIODO]='CUIPO-PIIP'!A15)*(CUIPO_datos_abiertos[ES_PRODUCTO_VALIDO]="VALIDO"),"")))} -> 4301001 | D15: {=_xlfn.TEXTJOIN(", ",TRUE,_xlfn._xlws.FILTER(EjecucionPIIP[CodigoProducto],(EjecucionPIIP[Bpin]='CUIPO-PIIP'!B15)*(EjecucionPIIP[Periodo]='CUIPO-PIIP'!A15),""))} -> 4301001 | E15: {=_xlfn.LET(_xlpm.productos_cuipo,_xlfn.UNIQUE(_xlfn._xlws.FILTER(CUIPO_datos_abiertos[COD_PROGRAMATICO_MGA],(CUIPO_datos_abiertos[BPIN]=B15)*(CUIPO_datos_abiertos[PERIODO]=A15)*(CUIPO_datos_abiertos[ES_PRODUCTO_VALIDO]="VALIDO"),"")),_xlpm.num_productos_cuipo,COUNTA(_xlpm.productos_cuipo),_xlpm.num_productos_cuipo)} -> 1 | F15: {=_xlfn.LET(_xlpm.productos_piip,_xlfn._xlws.FILTER(EjecucionPIIP[CodigoProducto],(EjecucionPIIP[Bpin]=B15)*(EjecucionPIIP[Periodo]=A15),""),_xlpm.num_productos_piip,COUNTA(_xlpm.productos_piip),_xlpm.num_productos_piip)} -> 1 | G15: {=_xlfn.LET(_xlpm.productos_piip,_xlfn._xlws.FILTER(EjecucionPIIP[CodigoProducto],(EjecucionPIIP[Bpin]=B15)*(EjecucionPIIP[Periodo]=A15),""),_xlpm.productos_cuipo,_xlfn.UNIQUE(_xlfn._xlws.FILTER(CUIPO_datos_abiertos[COD_PROGRAMATICO_MGA],(CUIPO_datos_abiertos[BPIN]=B15)*(CUIPO_datos_abiertos[PERIODO]=A15)*(CUIPO_datos_abiertos[ES_PRODUCTO_VALIDO]="VALIDO"),"")),_xlpm.num_productos_cuipo,COUNTA(_xlpm.productos_cuipo),_xlpm.num_productos_piip,COUNTA(_xlpm.productos_piip),IF(AND(C15<>"",D15<>""),IF(_xlpm.num_productos_cuipo>_xlpm.num_productos_piip,"Inconsistencia",""),""))} | H15: {=_xlfn.LET(_xlpm.productos_piip,_xlfn._xlws.FILTER(EjecucionPIIP[CodigoProducto],(EjecucionPIIP[Bpin]=B15)*(EjecucionPIIP[Periodo]=A15),""),_xlpm.productos_cuipo,_xlfn.UNIQUE(_xlfn._xlws.FILTER(CUIPO_datos_abiertos[COD_PROGRAMATICO_MGA],(CUIPO_datos_abiertos[BPIN]=B15)*(CUIPO_datos_abiertos[PERIODO]=A15)*(CUIPO_datos_abiertos[ES_PRODUCTO_VALIDO]="VALIDO"),"")),_xlpm.eval,COUNT(_xlfn.MAP(_xlpm.productos_cuipo,_xlfn.LAMBDA(_xlpm.x,FIND(_xlpm.x,_xlfn.TEXTJOIN(",",TRUE,_xlpm.productos_piip))))),_xlpm.num_productos_cuipo,COUNTA(_xlpm.productos_cuipo),_xlpm.num_productos_piip,COUNTA(_xlpm.productos_piip),IF(AND(C15<>"",D15<>"",G15<>"Inconsistencia"),TRANSPOSE(_xlpm.eval),""))} -> 1 | I15: =IF(AND(E15<>"",F15<>"",H15<>""),IF(H15=0,"No coinciden",IF(AND(E15=F15,F15=H15),"Coinciden","No coinciden todos")),"") -> Coinciden
... A80: 20260601 | B80: 202600000007252 | C80: {=_xlfn.TEXTJOIN(", ",TRUE,_xlfn.UNIQUE(_xlfn._xlws.FILTER(CUIPO_datos_abiertos[COD_PROGRAMATICO_MGA],(CUIPO_datos_abiertos[BPIN]=B80)*(CUIPO_datos_abiertos[PERIODO]='CUIPO-PIIP'!A80)*(CUIPO_datos_abiertos[ES_PRODUCTO_VALIDO]="VALIDO"),"")))} -> 3301053 | D80: {=_xlfn.TEXTJOIN(", ",TRUE,_xlfn._xlws.FILTER(EjecucionPIIP[CodigoProducto],(EjecucionPIIP[Bpin]='CUIPO-PIIP'!B80)*(EjecucionPIIP[Periodo]='CUIPO-PIIP'!A80),""))} -> 3301065 | E80: {=_xlfn.LET(_xlpm.productos_cuipo,_xlfn.UNIQUE(_xlfn._xlws.FILTER(CUIPO_datos_abiertos[COD_PROGRAMATICO_MGA],(CUIPO_datos_abiertos[BPIN]=B80)*(CUIPO_datos_abiertos[PERIODO]=A80)*(CUIPO_datos_abiertos[ES_PRODUCTO_VALIDO]="VALIDO"),"")),_xlpm.num_productos_cuipo,COUNTA(_xlpm.productos_cuipo),_xlpm.num_productos_cuipo)} -> 1 | F80: {=_xlfn.LET(_xlpm.productos_piip,_xlfn._xlws.FILTER(EjecucionPIIP[CodigoProducto],(EjecucionPIIP[Bpin]=B80)*(EjecucionPIIP[Periodo]=A80),""),_xlpm.num_productos_piip,COUNTA(_xlpm.productos_piip),_xlpm.num_productos_piip)} -> 1 | G80: {=_xlfn.LET(_xlpm.productos_piip,_xlfn._xlws.FILTER(EjecucionPIIP[CodigoProducto],(EjecucionPIIP[Bpin]=B80)*(EjecucionPIIP[Periodo]=A80),""),_xlpm.productos_cuipo,_xlfn.UNIQUE(_xlfn._xlws.FILTER(CUIPO_datos_abiertos[COD_PROGRAMATICO_MGA],(CUIPO_datos_abiertos[BPIN]=B80)*(CUIPO_datos_abiertos[PERIODO]=A80)*(CUIPO_datos_abiertos[ES_PRODUCTO_VALIDO]="VALIDO"),"")),_xlpm.num_productos_cuipo,COUNTA(_xlpm.productos_cuipo),_xlpm.num_productos_piip,COUNTA(_xlpm.productos_piip),IF(AND(C80<>"",D80<>""),IF(_xlpm.num_productos_cuipo>_xlpm.num_productos_piip,"Inconsistencia",""),""))} | H80: {=_xlfn.LET(_xlpm.productos_piip,_xlfn._xlws.FILTER(EjecucionPIIP[CodigoProducto],(EjecucionPIIP[Bpin]=B80)*(EjecucionPIIP[Periodo]=A80),""),_xlpm.productos_cuipo,_xlfn.UNIQUE(_xlfn._xlws.FILTER(CUIPO_datos_abiertos[COD_PROGRAMATICO_MGA],(CUIPO_datos_abiertos[BPIN]=B80)*(CUIPO_datos_abiertos[PERIODO]=A80)*(CUIPO_datos_abiertos[ES_PRODUCTO_VALIDO]="VALIDO"),"")),_xlpm.eval,COUNT(_xlfn.MAP(_xlpm.productos_cuipo,_xlfn.LAMBDA(_xlpm.x,FIND(_xlpm.x,_xlfn.TEXTJOIN(",",TRUE,_xlpm.productos_piip))))),_xlpm.num_productos_cuipo,COUNTA(_xlpm.productos_cuipo),_xlpm.num_productos_piip,COUNTA(_xlpm.productos_piip),IF(AND(C80<>"",D80<>"",G80<>"Inconsistencia"),TRANSPOSE(_xlpm.eval),""))} -> 0 | I80: =IF(AND(E80<>"",F80<>"",H80<>""),IF(H80=0,"No coinciden",IF(AND(E80=F80,F80=H80),"Coinciden","No coinciden todos")),"") -> No coinciden
D227: {=_xlfn.TEXTJOIN(", ",TRUE,_xlfn._xlws.FILTER(EjecucionPIIP[CodigoProducto],(EjecucionPIIP[Bpin]='CUIPO-PIIP'!B227)*(EjecucionPIIP[Periodo]='CUIPO-PIIP'!A227),""))} | H227: =IF(AND(ISNUMBER(VALUE(C227)),ISNUMBER(VALUE(D227)),C227<>"",D227<>""),IF(C227=D227,"Coincide","No coincide"),"")

Sheet IndicadoresProyectosPI
A1: INDICADORES PI | E1: PROYECTOS PI
A2: Código del indicador principal | B2: Código de Meta | C2: Está en Plan Indicativo | E2: Codigo Meta | F2: Código del indicador principal | G2: BPIN | H2: VIGENCIA PI
A3: 410205200 | B3: MT001 | C3: Si | E3: MT001 | F3: 410205200 | G3: 202500000050658 | H3: 2026
A4: 450203400 | B4: MT002, MT023, MT414, MT467 | C4: Si | E4: MT005 | F4: 410204100 | G4: 202500000050658 | H4: 2026
A5: 360200300 | B5: MT003, MT222 | C5: Si | E5: MT006 | F5: 410200100 | G5: 2024002700095 | H5: 2025
A6: 410204100 | B6: MT004, MT005 | C6: Si | E6: MT006 | F6: 410200100 | G6: 202400000004298 | H6: 2025
A7: 410200100 | B7: MT006 | C7: Si | E7: MT006 | F7: 410200100 | G7: 2024002700041 | H7: 2024
A8: 450200100 | B8: MT007, MT024, MT030, MT380, MT400, MT403, MT413, MT439, MT455, MT458, MT462 | C8: Si | E8: MT006 | F8: 410200100 | G8: 202500000050596 | H8: 2026
A9: 360501100 | B9: MT008 | C9: Si | E9: MT007 | F9: 450200100 | G9: 202600000003201 | H9: 2026
A10: 410204500 | B10: MT009, MT010, MT027, MT028 | C10: Si | E10: MT007 | F10: 450200100 | G10: 202500000028886 | H10: 2025
A11: 410204300 | B11: MT011 | C11: Si | E11: MT007 | F11: 450200100 | G11: 202500000028900 | H11: 2025
A12: 450202100 | B12: MT012, MT404 | C12: Si | E12: MT007 | F12: 450200100 | G12: 2024002700096 | H12: 2024
A13: 410400800 | B13: MT013 | C13: Si | E13: MT007 | F13: 450200100 | G13: 202400000001355 | H13: 2025
A14: 410401000 | B14: MT014, MT017 | C14: Si | E14: MT007 | F14: 450200100 | G14: 202600000003201 | H14: 2026
... A379: 410100100 | B379: MT468 | C379: Si | E379: MT278 | F379: 400302000 | G379: 2023002700164 | H379: 2025
E380: MT278 | F380: 400302000 | G380: 202600000008749 | H380: 2026
E381: MT279 | F381: 400305200 | G381: 202400000004840 | H381: 2025
E382: MT279 | F382: 400305200 | G382: 202600000008749 | H382: 2026
E383: MT280 | F383: 400301200 | G383: 2021Er0054485 | H383: 2026
E384: MT281 | F384: 400302100 | G384: 202600000008749 | H384: 2026
E385: MT283 | F385: 320100300 | G385: 2021000100520 | H385: 2025
E386: MT285 | F386: 350209500 | G386: 202500000041804 | H386: 2025
E387: MT288 | F387: 320200500 | G387: 2024002700071 | H387: 2024
E388: MT288 | F388: 320200500 | G388: 202400000007089 | H388: 2026
E389: MT288 | F389: 320200500 | G389: 2021702650040 | H389: 2027
E390: MT288 | F390: 320200500 | G390: 202500000034248 | H390: 2026
E391: MT289 | F391: 320201400 | G391: 202400000007089 | H391: 2026
... E483: MT329 | F483: 240204100 | G483: 2018000020059 | H483: 2025
E484: MT329 | F484: 240204100 | G484: 2022002700068
E485: MT329 | F485: 240204100 | G485: 2019011000264 | H485: 2026
E486: MT329 | F486: 240204100 | G486: 2019011000264 | H486: 2027
E487: MT329 | F487: 240204100 | G487: 2020000020053 | H487: 2026
E488: MT329 | F488: 240204100 | G488: 2025000020037 | H488: 2027
E489: MT329 | F489: 240204100 | G489: 20210214000126 | H489: 2026
E490: MT329 | F490: 240204100 | G490: 20221301010191 | H490: 2026
E491: MT329 | F491: 240204100 | G491: 2021000020052 | H491: 2026
E492: MT329 | F492: 240204100 | G492: 2022000020021 | H492: 2026
E493: MT329 | F493: 240204100 | G493: 2019011000264 | H493: 2026
E494: MT329 | F494: 240204100 | G494: 2025000020006 | H494: 2027
E495: MT329 | F495: 240204100 | G495: 20250214000247 | H495: 2027
E496: MT329 | F496: 240204100 | G496: 20250214000249 | H496: 2027
... E660: MT129MS | F660: 190502600 | G660: 202500000038325 | H660: 2026

Sheet CUIPO_CHIP
A1: Periodo | B1: VIGENCIA GASTO | C1: SECCION PRESUPUESTAL | D1: CODIGO | E1: NOMBRE | F1: CPC | G1: DETALLE SECTORIAL | H1: FUENTES DE FINANCIACION | I1: BPIN | J1: SITUACION DE FONDOS | K1: POLITICA PUBLICA | L1: TERCEROS | M1: COMPROMISOS | N1: OBLIGACIONES | O1: PAGOS | P1: PRODUCTO MGA | Q1: CODIGO PRODUCTO MGA | R1: ES BPIN
A2: 202606 | B2: VIGENCIA ACTUAL | C2: ENTIDADES TERRITORIALES - ADMINISTRACION CENTRAL | D2: 2.3.2.01.01.001.02.08 | E2: EDIFICIOS RELACIONADOS CON SALUD | F2: No aplica | G2: NO APLICA | H2: OTRAS TRANSFERENCIAS CORRIENTES DE OTRAS ENTIDADES CON DESTINACION ESPECIFICA LEGAL DEL GOBIERNO GENERAL | I2: 2023002700021 | J2: CON SITUACION DE FONDOS | K2: NO APLICA | L2: NO APLICA | M2: 21267795435 | N2: 9991793731 | O2: 9991793731 | P2: hospitales de primer nivel de atencion construidos y dotados | R2: =IF(AND(ISNUMBER(VALUE(LEFT(CUIPO_chip[[#This Row],[BPIN]],4))),LEN(CUIPO_chip[[#This Row],[BPIN]])>7),"VALIDO","") -> VALIDO
A3: 202606 | B3: VIGENCIA ACTUAL | C3: ENTIDADES TERRITORIALES - ADMINISTRACION CENTRAL | D3: 2.3.2.01.01.001.03.02 | E3: AUTOPISTAS, CARRETERAS, CALLES | F3: No aplica | G3: NO APLICA | H3: OTRAS TRANSFERENCIAS CORRIENTES DE OTRAS ENTIDADES CON DESTINACION ESPECIFICA LEGAL DEL GOBIERNO GENERAL | I3: N/A | J3: CON SITUACION DE FONDOS | K3: NO APLICA | L3: NO APLICA | M3: 33431816466 | N3: 15280589499 | O3: 15280589499 | P3: via secundaria rehabilitada | R3: =IF(AND(ISNUMBER(VALUE(LEFT(CUIPO_chip[[#This Row],[BPIN]],4))),LEN(CUIPO_chip[[#This Row],[BPIN]])>7),"VALIDO","")
A4: 202606 | B4: VIGENCIA ACTUAL | C4: ENTIDADES TERRITORIALES - ADMINISTRACION CENTRAL | D4: 2.3.2.01.01.001.03.02 | E4: AUTOPISTAS, CARRETERAS, CALLES | F4: No aplica | G4: NO APLICA | H4: ICLD DEPARTAMENTOS PARA FONPET | I4: 202500000044154 | J4: CON SITUACION DE FONDOS | K4: NO APLICA | L4: NO APLICA | M4: 200001830 | N4: 93503249 | O4: 93503249 | P4: via terciaria con mantenimiento periodico o rutinario | Q4: 2402112 | R4: =IF(AND(ISNUMBER(VALUE(LEFT(CUIPO_chip[[#This Row],[BPIN]],4))),LEN(CUIPO_chip[[#This Row],[BPIN]])>7),"VALIDO","") -> VALIDO
A5: 202606 | B5: VIGENCIA ACTUAL | C5: ENTIDADES TERRITORIALES - ADMINISTRACION CENTRAL | D5: 2.3.2.01.01.001.03.02 | E5: AUTOPISTAS, CARRETERAS, CALLES | F5: No aplica | G5: NO APLICA | H5: R.B. OTRAS TRANSFERENCIAS CORRIENTES DE OTRAS ENTIDADES DEL GOBIERNO GENERAL | I5: NA | J5: CON SITUACION DE FONDOS | K5: NO APLICA | L5: NO APLICA | M5: 8822738512 | N5: 0 | O5: 0 | P5: via secundaria mejorada | R5: =IF(AND(ISNUMBER(VALUE(LEFT(CUIPO_chip[[#This Row],[BPIN]],4))),LEN(CUIPO_chip[[#This Row],[BPIN]])>7),"VALIDO","")
A6: 202606 | B6: VIGENCIA ACTUAL | C6: ENTIDADES TERRITORIALES - ADMINISTRACION CENTRAL | D6: 2.3.2.01.01.001.03.02 | E6: AUTOPISTAS, CARRETERAS, CALLES | F6: No aplica | G6: NO APLICA | H6: R.B. OTRAS TRANSFERENCIAS CORRIENTES DE OTRAS ENTIDADES DEL GOBIERNO GENERAL | I6: NA | J6: CON SITUACION DE FONDOS | K6: NO APLICA | L6: NO APLICA | M6: 16403279675 | N6: 7181289801 | O6: 7181289801 | P6: via secundaria construida | Q6: 2402001 | R6: =IF(AND(ISNUMBER(VALUE(LEFT(CUIPO_chip[[#This Row],[BPIN]],4))),LEN(CUIPO_chip[[#This Row],[BPIN]])>7),"VALIDO","")
A7: 202606 | B7: VIGENCIA ACTUAL | C7: ENTIDADES TERRITORIALES - ADMINISTRACION CENTRAL | D7: 2.3.2.01.01.001.03.13 | E7: OBRAS PARA LA COMUNICACION DE LARGA DISTANCIA Y LAS LINEAS ELECTRICAS CABLES | F7: No aplica | G7: NO APLICA | H7: ESTAMPILLAS | I7: 2024002700131 | J7: CON SITUACION DE FONDOS | K7: NO APLICA | L7: NO APLICA | M7: 428625645 | N7: 0 | O7: 0 | P7: unidades de generacion fotovoltaica de energia electrica instaladas | R7: =IF(AND(ISNUMBER(VALUE(LEFT(CUIPO_chip[[#This Row],[BPIN]],4))),LEN(CUIPO_chip[[#This Row],[BPIN]])>7),"VALIDO","") -> VALIDO
A8: 202606 | B8: VIGENCIA ACTUAL | C8: ENTIDADES TERRITORIALES - ADMINISTRACION CENTRAL | D8: 2.3.2.01.01.001.03.19 | E8: OTRAS OBRAS DE INGENIERIA CIVIL | F8: No aplica | G8: NO APLICA | H8: R.B. TRANSFERENCIAS DE CAPITAL DE OTRAS ENTIDADES DEL GOBIERNO GENERAL | I8: 2021002700364 | J8: CON SITUACION DE FONDOS | K8: NO APLICA | L8: NO APLICA | M8: 2534579874 | N8: 2158642029 | O8: 2158642029 | P8: ecoparque turistico construido | R8: =IF(AND(ISNUMBER(VALUE(LEFT(CUIPO_chip[[#This Row],[BPIN]],4))),LEN(CUIPO_chip[[#This Row],[BPIN]])>7),"VALIDO","") -> VALIDO
A9: 202606 | B9: VIGENCIA ACTUAL | C9: ENTIDADES TERRITORIALES - ADMINISTRACION CENTRAL | D9: 2.3.2.01.01.003.03.02 | E9: MAQUINARIA DE INFORMATICA Y SUS PARTES, PIEZAS Y ACCESORIOS | F9: No aplica | G9: NO APLICA | H9: OTRAS TRANSFERENCIAS CORRIENTES DE OTRAS ENTIDADES CON DESTINACION ESPECIFICA LEGAL DEL GOBIERNO GENERAL | I9: 202500000038150 | J9: CON SITUACION DE FONDOS | K9: NO APLICA | L9: NO APLICA | M9: 24000000 | N9: 12000000 | O9: 0 | P9: servicio de saneamiento fiscal y financiero | R9: =IF(AND(ISNUMBER(VALUE(LEFT(CUIPO_chip[[#This Row],[BPIN]],4))),LEN(CUIPO_chip[[#This Row],[BPIN]])>7),"VALIDO","") -> VALIDO
A10: 202606 | B10: VIGENCIA ACTUAL | C10: ENTIDADES TERRITORIALES - ADMINISTRACION CENTRAL | D10: 2.3.2.01.01.003.05.03 | E10: RADIORRECEPTORES Y RECEPTORES DE TELEVISION APARATOS PARA LA GRABACION Y REPRODUCCION DE SONIDO Y VIDEO, MICROFONOS, ALTAVOCES, AMPLIFICADORES, ETC | F10: No aplica | G10: NO APLICA | H10: CONTRIBUCION SOBRE CONTRATOS DE OBRA PUBLICA | I10: 202500000041895 | J10: CON SITUACION DE FONDOS | K10: NO APLICA | L10: NO APLICA | M10: 3599987763 | N10: 0 | O10: 0 | P10: servicio de inteligencia tecnica | Q10: 4501052 | R10: =IF(AND(ISNUMBER(VALUE(LEFT(CUIPO_chip[[#This Row],[BPIN]],4))),LEN(CUIPO_chip[[#This Row],[BPIN]])>7),"VALIDO","") -> VALIDO
A11: 202606 | B11: VIGENCIA ACTUAL | C11: ENTIDADES TERRITORIALES - ADMINISTRACION CENTRAL | D11: 2.3.2.01.01.005.02.03.01.01 | E11: PAQUETES DE SOFTWARE | F11: No aplica | G11: NO APLICA | H11: ICLD DEPARTAMENTOS PARA FONPET | I11: 202600000005350 | J11: CON SITUACION DE FONDOS | K11: NO APLICA | L11: NO APLICA | M11: 187000000 | N11: 124666666 | O11: 124666666 | P11: servicios de informacion implementados | Q11: 4599025 | R11: =IF(AND(ISNUMBER(VALUE(LEFT(CUIPO_chip[[#This Row],[BPIN]],4))),LEN(CUIPO_chip[[#This Row],[BPIN]])>7),"VALIDO","") -> VALIDO
A12: 202606 | B12: VIGENCIA ACTUAL | C12: ENTIDADES TERRITORIALES - ADMINISTRACION CENTRAL | D12: 2.3.2.02.01.002 | E12: PRODUCTOS ALIMENTICIOS, BEBIDAS Y TABACO, TEXTILES, PRENDAS DE VESTIR Y PRODUCTOS DE CUERO | F12: Uniformes de trabajo | G12: NO APLICA | H12: OTRAS TRANSFERENCIAS CORRIENTES DE OTRAS ENTIDADES CON DESTINACION ESPECIFICA LEGAL DEL GOBIERNO GENERAL | I12: 202500000038150 | J12: CON SITUACION DE FONDOS | K12: NO APLICA | L12: NO APLICA | M12: 31851785 | N12: 0 | O12: 0 | P12: servicios de informacion implementados | Q12: 4599025 | R12: =IF(AND(ISNUMBER(VALUE(LEFT(CUIPO_chip[[#This Row],[BPIN]],4))),LEN(CUIPO_chip[[#This Row],[BPIN]])>7),"VALIDO","") -> VALIDO
A13: 202606 | B13: VIGENCIA ACTUAL | C13: ENTIDADES TERRITORIALES - ADMINISTRACION CENTRAL | D13: 2.3.2.02.02.008 | E13: SERVICIOS PRESTADOS A LAS EMPRESAS Y SERVICIOS DE PRODUCCION | F13: Otros servicios de la administracion publica n c p | G13: NO APLICA | H13: INGRESOS CORRIENTES DE LIBRE DESTINACION | I13: 202500000050507 | J13: CON SITUACION DE FONDOS | K13: NO APLICA | L13: NO APLICA | M13: 300000000 | N13: 178528568 | O13: 171428568 | P13: servicio de gestion para el emprendimiento solidario | R13: =IF(AND(ISNUMBER(VALUE(LEFT(CUIPO_chip[[#This Row],[BPIN]],4))),LEN(CUIPO_chip[[#This Row],[BPIN]])>7),"VALIDO","") -> VALIDO
A14: 202606 | B14: VIGENCIA ACTUAL | C14: ENTIDADES TERRITORIALES - ADMINISTRACION CENTRAL | D14: 2.3.2.02.02.008 | E14: SERVICIOS PRESTADOS A LAS EMPRESAS Y SERVICIOS DE PRODUCCION | F14: Otros servicios de la administracion publica n c p | G14: NO APLICA | H14: ICLD DEPARTAMENTOS PARA FONPET | I14: 202500000049928 | J14: CON SITUACION DE FONDOS | K14: NO APLICA | L14: NO APLICA | M14: 67000875 | N14: 36815958 | O14: 36815958 | P14: servicio de asistencia tecnica para la implementacion de la estrategia de gobierno digital | Q14: 2302024 | R14: =IF(AND(ISNUMBER(VALUE(LEFT(CUIPO_chip[[#This Row],[BPIN]],4))),LEN(CUIPO_chip[[#This Row],[BPIN]])>7),"VALIDO","") -> VALIDO
A15: 202606 | B15: VIGENCIA ACTUAL | C15: ENTIDADES TERRITORIALES - ADMINISTRACION CENTRAL | D15: 2.3.2.02.02.009 | E15: SERVICIOS PARA LA COMUNIDAD, SOCIALES Y PERSONALES | F15: Otros servicios de la administracion publica n c p | G15: NO APLICA | H15: INGRESOS CORRIENTES DE LIBRE DESTINACION | I15: 202600000005926 | J15: CON SITUACION DE FONDOS | K15: NO APLICA | L15: NO APLICA | M15: 165000000 | N15: 165000000 | O15: 165000000 | P15: servicio de promocion turistica | R15: =IF(AND(ISNUMBER(VALUE(LEFT(CUIPO_chip[[#This Row],[BPIN]],4))),LEN(CUIPO_chip[[#This Row],[BPIN]])>7),"VALIDO","") -> VALIDO
A16: 202606 | B16: VIGENCIA ACTUAL | C16: ENTIDADES TERRITORIALES - ADMINISTRACION CENTRAL | D16: 2.3.2.02.02.009 | E16: SERVICIOS PARA LA COMUNIDAD, SOCIALES Y PERSONALES | F16: Otros servicios de la administracion publica n c p | G16: NO APLICA | H16: INGRESOS CORRIENTES DE LIBRE DESTINACION | I16: 202500000048328 | J16: CON SITUACION DE FONDOS | K16: NO APLICA | L16: NO APLICA | M16: 250000000 | N16: 125000000 | O16: 125000000 | P16: servicio de apoyo y consolidacion de las comisiones regionales de competitividad crc | R16: =IF(AND(ISNUMBER(VALUE(LEFT(CUIPO_chip[[#This Row],[BPIN]],4))),LEN(CUIPO_chip[[#This Row],[BPIN]])>7),"VALIDO","") -> VALIDO
A17: 202606 | B17: VIGENCIA ACTUAL | C17: ENTIDADES TERRITORIALES - ADMINISTRACION CENTRAL | D17: 2.3.2.02.02.009 | E17: SERVICIOS PARA LA COMUNIDAD, SOCIALES Y PERSONALES | F17: Otros servicios de la administracion publica n c p | G17: NO APLICA | H17: INGRESOS CORRIENTES DE LIBRE DESTINACION | I17: 202500000050246 | J17: CON SITUACION DE FONDOS | K17: NO APLICA | L17: NO APLICA | M17: 666400000 | N17: 356700000 | O17: 340000000 | P17: servicio de implementacion sistemas de gestion | Q17: 4599023 | R17: =IF(AND(ISNUMBER(VALUE(LEFT(CUIPO_chip[[#This Row],[BPIN]],4))),LEN(CUIPO_chip[[#This Row],[BPIN]])>7),"VALIDO","") -> VALIDO
A18: 202606 | B18: VIGENCIA ACTUAL | C18: ENTIDADES TERRITORIALES - ADMINISTRACION CENTRAL | D18: 2.3.2.02.02.009 | E18: SERVICIOS PARA LA COMUNIDAD, SOCIALES Y PERSONALES | F18: Otros servicios de la administracion publica n c p | G18: NO APLICA | H18: INGRESOS CORRIENTES DE LIBRE DESTINACION | I18: 202600000005933 | J18: CON SITUACION DE FONDOS | K18: NO APLICA | L18: NO APLICA | M18: 50000000 | N18: 0 | O18: 0 | P18: servicio de asistencia tecnica | Q18: 4599031 | R18: =IF(AND(ISNUMBER(VALUE(LEFT(CUIPO_chip[[#This Row],[BPIN]],4))),LEN(CUIPO_chip[[#This Row],[BPIN]])>7),"VALIDO","") -> VALIDO
A19: 202606 | B19: VIGENCIA ACTUAL | C19: ENTIDADES TERRITORIALES - ADMINISTRACION CENTRAL | D19: 2.3.2.02.02.009 | E19: SERVICIOS PARA LA COMUNIDAD, SOCIALES Y PERSONALES | F19: Otros servicios de la administracion publica n c p | G19: NO APLICA | H19: INGRESOS CORRIENTES DE LIBRE DESTINACION | I19: 202500000047734 | J19: CON SITUACION DE FONDOS | K19: NO APLICA | L19: NO APLICA | M19: 148236000 | N19: 98824001 | O19: 98824001 | P19: servicio de promocion de la garantia de derechos | R19: =IF(AND(ISNUMBER(VALUE(LEFT(CUIPO_chip[[#This Row],[BPIN]],4))),LEN(CUIPO_chip[[#This Row],[BPIN]])>7),"VALIDO","") -> VALIDO
A20: 202606 | B20: VIGENCIA ACTUAL | C20: ENTIDADES TERRITORIALES - ADMINISTRACION CENTRAL | D20: 2.3.2.02.02.009 | E20: SERVICIOS PARA LA COMUNIDAD, SOCIALES Y PERSONALES | F20: Otros servicios de la administracion publica n c p | G20: NO APLICA | H20: INGRESOS CORRIENTES DE LIBRE DESTINACION | I20: 202500000050596 | J20: CON SITUACION DE FONDOS | K20: NO APLICA | L20: NO APLICA | M20: 61999116 | N20: 61999116 | O20: 61999116 | P20: servicio de atencion integral a la primera infancia | R20: =IF(AND(ISNUMBER(VALUE(LEFT(CUIPO_chip[[#This Row],[BPIN]],4))),LEN(CUIPO_chip[[#This Row],[BPIN]])>7),"VALIDO","") -> VALIDO
A21: 202606 | B21: VIGENCIA ACTUAL | C21: ENTIDADES TERRITORIALES - ADMINISTRACION CENTRAL | D21: 2.3.2.02.02.009 | E21: SERVICIOS PARA LA COMUNIDAD, SOCIALES Y PERSONALES | F21: Otros servicios de la administracion publica n c p | G21: NO APLICA | H21: OTRAS TRANSFERENCIAS CORRIENTES DE OTRAS ENTIDADES CON DESTINACION ESPECIFICA LEGAL DEL GOBIERNO GENERAL | I21: 202500000038150 | J21: CON SITUACION DE FONDOS | K21: NO APLICA | L21: NO APLICA | M21: 371200000 | N21: 155200000 | O21: 149900000 | P21: servicio de saneamiento fiscal y financiero | R21: =IF(AND(ISNUMBER(VALUE(LEFT(CUIPO_chip[[#This Row],[BPIN]],4))),LEN(CUIPO_chip[[#This Row],[BPIN]])>7),"VALIDO","") -> VALIDO
A22: 202606 | B22: VIGENCIA ACTUAL | C22: ENTIDADES TERRITORIALES - ADMINISTRACION CENTRAL | D22: 2.3.2.02.02.009 | E22: SERVICIOS PARA LA COMUNIDAD, SOCIALES Y PERSONALES | F22: Otros servicios de la administracion publica n c p | G22: NO APLICA | H22: RECURSOS DEL BALANCE DE LIBRE DESTINACION | I22: NA | J22: CON SITUACION DE FONDOS | K22: NO APLICA | L22: NO APLICA | M22: 1005850071 | N22: 783152820 | O22: 750994820 | P22: servicio de asistencia tecnica | Q22: 4599004 | R22: =IF(AND(ISNUMBER(VALUE(LEFT(CUIPO_chip[[#This Row],[BPIN]],4))),LEN(CUIPO_chip[[#This Row],[BPIN]])>7),"VALIDO","")
A23: 202606 | B23: VIGENCIA ACTUAL | C23: ENTIDADES TERRITORIALES - ADMINISTRACION CENTRAL | D23: 2.3.2.02.02.009 | E23: SERVICIOS PARA LA COMUNIDAD, SOCIALES Y PERSONALES | F23: Otros servicios de la administracion publica n c p | G23: NO APLICA | H23: ICLD DEPARTAMENTOS PARA FONPET | I23: 202500000050078 | J23: CON SITUACION DE FONDOS | K23: NO APLICA | L23: NO APLICA | M23: 4995015886 | N23: 4617215884 | O23: 4583715884 | P23: servicio de asistencia tecnica | Q23: 4599031 | R23: =IF(AND(ISNUMBER(VALUE(LEFT(CUIPO_chip[[#This Row],[BPIN]],4))),LEN(CUIPO_chip[[#This Row],[BPIN]])>7),"VALIDO","") -> VALIDO
A24: 202606 | B24: VIGENCIA ACTUAL | C24: ENTIDADES TERRITORIALES - ADMINISTRACION CENTRAL | D24: 2.3.2.02.02.009 | E24: SERVICIOS PARA LA COMUNIDAD, SOCIALES Y PERSONALES | F24: Otros servicios de la administracion publica n c p | G24: NO APLICA | H24: ICLD DEPARTAMENTOS PARA FONPET | I24: 2023002700172 | J24: CON SITUACION DE FONDOS | K24: NO APLICA | L24: NO APLICA | M24: 80459466 | N24: 80459466 | O24: 80459466 | P24: servicio de ayuda y atencion humanitaria | R24: =IF(AND(ISNUMBER(VALUE(LEFT(CUIPO_chip[[#This Row],[BPIN]],4))),LEN(CUIPO_chip[[#This Row],[BPIN]])>7),"VALIDO","") -> VALIDO
A25: 202606 | B25: VIGENCIA ACTUAL | C25: ENTIDADES TERRITORIALES - ADMINISTRACION CENTRAL | D25: 2.3.2.02.02.009 | E25: SERVICIOS PARA LA COMUNIDAD, SOCIALES Y PERSONALES | F25: Otros servicios de la administracion publica n c p | G25: NO APLICA | H25: ICLD DEPARTAMENTOS PARA FONPET | I25: 202500000050658 | J25: CON SITUACION DE FONDOS | K25: NO APLICA | L25: NO APLICA | M25: 386725425 | N25: 130364925 | O25: 107097939 | P25: servicio de asistencia tecnica en el ciclo de politicas publicas de familia y otras relacionadas | R25: =IF(AND(ISNUMBER(VALUE(LEFT(CUIPO_chip[[#This Row],[BPIN]],4))),LEN(CUIPO_chip[[#This Row],[BPIN]])>7),"VALIDO","") -> VALIDO
A26: 202606 | B26: VIGENCIA ACTUAL | C26: ENTIDADES TERRITORIALES - ADMINISTRACION CENTRAL | D26: 2.3.2.02.02.009 | E26: SERVICIOS PARA LA COMUNIDAD, SOCIALES Y PERSONALES | F26: Otros servicios de la administracion publica n c p | G26: NO APLICA | H26: ICLD DEPARTAMENTOS PARA FONPET | I26: N/A | J26: CON SITUACION DE FONDOS | K26: NO APLICA | L26: NO APLICA | M26: 1591333000 | N26: 350430000 | O26: 350430000 | P26: obras de infraestructura para la reduccion del riesgo de desastres | R26: =IF(AND(ISNUMBER(VALUE(LEFT(CUIPO_chip[[#This Row],[BPIN]],4))),LEN(CUIPO_chip[[#This Row],[BPIN]])>7),"VALIDO","")
A27: 202606 | B27: VIGENCIA ACTUAL | C27: ENTIDADES TERRITORIALES - ADMINISTRACION CENTRAL | D27: 2.3.2.02.02.009 | E27: SERVICIOS PARA LA COMUNIDAD, SOCIALES Y PERSONALES | F27: Otros servicios de la administracion publica n c p | G27: NO APLICA | H27: ICLD DEPARTAMENTOS PARA FONPET | I27: 202500000049928 | J27: CON SITUACION DE FONDOS | K27: NO APLICA | L27: NO APLICA | M27: 90873863 | N27: 55653628 | O27: 55653628 | P27: servicio de asistencia tecnica para la implementacion de la estrategia de gobierno digital | Q27: 2302024 | R27: =IF(AND(ISNUMBER(VALUE(LEFT(CUIPO_chip[[#This Row],[BPIN]],4))),LEN(CUIPO_chip[[#This Row],[BPIN]])>7),"VALIDO","") -> VALIDO
A28: 202606 | B28: VIGENCIA ACTUAL | C28: ENTIDADES TERRITORIALES - ADMINISTRACION CENTRAL | D28: 2.3.2.02.02.009 | E28: SERVICIOS PARA LA COMUNIDAD, SOCIALES Y PERSONALES | F28: Otros servicios de la administracion publica n c p | G28: NO APLICA | H28: R.B. CONTRIBUCION SOBRE CONTRATOS DE OBRA PUBLICA | I28: 202500000029628 | J28: CON SITUACION DE FONDOS | K28: NO APLICA | L28: NO APLICA | M28: 4405094852 | N28: 1052661110 | O28: 1052661110 | P28: servicio de promocion de la garantia de derechos | R28: =IF(AND(ISNUMBER(VALUE(LEFT(CUIPO_chip[[#This Row],[BPIN]],4))),LEN(CUIPO_chip[[#This Row],[BPIN]])>7),"VALIDO","") -> VALIDO
A29: 202606 | B29: VIGENCIA ACTUAL | C29: ENTIDADES TERRITORIALES - ADMINISTRACION CENTRAL | D29: 2.3.2.02.02.009 | E29: SERVICIOS PARA LA COMUNIDAD, SOCIALES Y PERSONALES | F29: Otros servicios de la administracion publica n c p | G29: NO APLICA | H29: OTROS RENDIMIENTOS FINANCIEROS | I29: 202500000042332 | J29: CON SITUACION DE FONDOS | K29: NO APLICA | L29: NO APLICA | M29: 90000000 | N29: 90000000 | O29: 90000000 | P29: servicio de atencion integral a poblacion en condicion de discapacidad | R29: =IF(AND(ISNUMBER(VALUE(LEFT(CUIPO_chip[[#This Row],[BPIN]],4))),LEN(CUIPO_chip[[#This Row],[BPIN]])>7),"VALIDO","") -> VALIDO
A30: 202606 | B30: VIGENCIA ACTUAL | C30: ENTIDADES TERRITORIALES - ADMINISTRACION CENTRAL | D30: 2.3.2.02.02.009 | E30: SERVICIOS PARA LA COMUNIDAD, SOCIALES Y PERSONALES | F30: Otros servicios de la administracion publica n c p | G30: NO APLICA | H30: OTROS RENDIMIENTOS FINANCIEROS | I30: 202500000047992 | J30: CON SITUACION DE FONDOS | K30: NO APLICA | L30: NO APLICA | M30: 15500000 | N30: 12400000 | O30: 12400000 | P30: servicio de apoyo para la implementacion de medidas en derechos humanos y derecho internacional humanitario | Q30: 4502024 | R30: =IF(AND(ISNUMBER(VALUE(LEFT(CUIPO_chip[[#This Row],[BPIN]],4))),LEN(CUIPO_chip[[#This Row],[BPIN]])>7),"VALIDO","") -> VALIDO
A31: 202606 | B31: VIGENCIA ACTUAL | C31: ENTIDADES TERRITORIALES - ADMINISTRACION CENTRAL | D31: 2.3.2.02.02.009 | E31: SERVICIOS PARA LA COMUNIDAD, SOCIALES Y PERSONALES | F31: Otros servicios de la administracion publica n c p | G31: NO APLICA | H31: INGRESOS CORRIENTES DE LIBRE DESTINACION | I31: 202600000000479 | J31: CON SITUACION DE FONDOS | K31: NO APLICA | L31: NO APLICA | M31: 63999031 | N31: 63999031 | O31: 0 | P31: documentos de investigacion | Q31: 4502030 | R31: =IF(AND(ISNUMBER(VALUE(LEFT(CUIPO_chip[[#This Row],[BPIN]],4))),LEN(CUIPO_chip[[#This Row],[BPIN]])>7),"VALIDO","") -> VALIDO
A32: 202606 | B32: VIGENCIA ACTUAL | C32: ENTIDADES TERRITORIALES - ADMINISTRACION CENTRAL | D32: 2.3.2.02.02.009 | E32: SERVICIOS PARA LA COMUNIDAD, SOCIALES Y PERSONALES | F32: Otros servicios de la administracion publica n c p | G32: NO APLICA | H32: CONTRIBUCION SOBRE CONTRATOS DE OBRA PUBLICA | I32: 202500000029628 | J32: CON SITUACION DE FONDOS | K32: NO APLICA | L32: NO APLICA | M32: 1000000000 | N32: 0 | O32: 0 | P32: servicio de promocion de la garantia de derechos | R32: =IF(AND(ISNUMBER(VALUE(LEFT(CUIPO_chip[[#This Row],[BPIN]],4))),LEN(CUIPO_chip[[#This Row],[BPIN]])>7),"VALIDO","") -> VALIDO
A33: 202606 | B33: VIGENCIA ACTUAL | C33: ENTIDADES TERRITORIALES - ADMINISTRACION CENTRAL | D33: 2.3.2.02.02.009 | E33: SERVICIOS PARA LA COMUNIDAD, SOCIALES Y PERSONALES | F33: Otros servicios de la administracion publica n c p | G33: NO APLICA | H33: CONTRIBUCION SOBRE CONTRATOS DE OBRA PUBLICA | I33: 202500000039546 | J33: CON SITUACION DE FONDOS | K33: NO APLICA | L33: NO APLICA | M33: 193965492 | N33: 106935960 | O33: 90542721 | P33: servicio de apoyo financiero para proyectos de convivencia y seguridad ciudadana | Q33: 4501029 | R33: =IF(AND(ISNUMBER(VALUE(LEFT(CUIPO_chip[[#This Row],[BPIN]],4))),LEN(CUIPO_chip[[#This Row],[BPIN]])>7),"VALIDO","") -> VALIDO
A34: 202606 | B34: VIGENCIA ACTUAL | C34: ENTIDADES TERRITORIALES - ADMINISTRACION CENTRAL | D34: 2.3.2.02.02.009 | E34: SERVICIOS PARA LA COMUNIDAD, SOCIALES Y PERSONALES | F34: Otros servicios de la administracion publica n c p | G34: NO APLICA | H34: RECURSOS DEL BALANCE DE DESTINACION ESPECIFICA POR ACTO ADMINISTRATIVO | I34: 202500000050078 | J34: CON SITUACION DE FONDOS | K34: NO APLICA | L34: NO APLICA | M34: 1482713701 | N34: 1247510136 | O34: 1200783257 | P34: servicio de asistencia tecnica | Q34: 4599031 | R34: =IF(AND(ISNUMBER(VALUE(LEFT(CUIPO_chip[[#This Row],[BPIN]],4))),LEN(CUIPO_chip[[#This Row],[BPIN]])>7),"VALIDO","") -> VALIDO
A35: 202606 | B35: VIGENCIA ACTUAL | C35: ENTIDADES TERRITORIALES - ADMINISTRACION CENTRAL | D35: 2.3.2.02.02.009 | E35: SERVICIOS PARA LA COMUNIDAD, SOCIALES Y PERSONALES | F35: Otros servicios de la administracion publica n c p | G35: NO APLICA | H35: OTRAS TRANSFERENCIAS CORRIENTES DE OTRAS ENTIDADES CON DESTINACION ESPECIFICA LEGAL DEL GOBIERNO GENERAL | I35: 202500000033863 | J35: CON SITUACION DE FONDOS | K35: NO APLICA | L35: NO APLICA | M35: 1509302501 | N35: 1509302501 | O35: 1509302501 | P35: servicio de asistencia tecnica para proyectos en tecnologias de la informacion y las comunicaciones | R35: =IF(AND(ISNUMBER(VALUE(LEFT(CUIPO_chip[[#This Row],[BPIN]],4))),LEN(CUIPO_chip[[#This Row],[BPIN]])>7),"VALIDO","") -> VALIDO
A36: 202606 | B36: VIGENCIA ACTUAL | C36: ENTIDADES TERRITORIALES - ADMINISTRACION CENTRAL | D36: 2.3.2.02.02.010 | E36: VIATICOS DE LOS FUNCIONARIOS EN COMISION | F36: No aplica | G36: NO APLICA | H36: OTRAS TRANSFERENCIAS CORRIENTES DE OTRAS ENTIDADES CON DESTINACION ESPECIFICA LEGAL DEL GOBIERNO GENERAL | I36: 202500000038150 | J36: CON SITUACION DE FONDOS | K36: NO APLICA | L36: NO APLICA | M36: 24784500 | N36: 24784500 | O36: 24784500 | P36: servicio de saneamiento fiscal y financiero | R36: =IF(AND(ISNUMBER(VALUE(LEFT(CUIPO_chip[[#This Row],[BPIN]],4))),LEN(CUIPO_chip[[#This Row],[BPIN]])>7),"VALIDO","") -> VALIDO
A37: 202606 | B37: VIGENCIA ACTUAL | C37: ENTIDADES TERRITORIALES - ADMINISTRACION CENTRAL | D37: 2.3.3.05.09.099 | E37: APORTES A ESTABLECIMIENTOS PUBLICOS Y UNIDADES ADMINISTRATIVAS ESPECIALES | F37: No aplica | G37: NO APLICA | H37: INGRESOS CORRIENTES DE LIBRE DESTINACION | I37: 202600000001143 | J37: CON SITUACION DE FONDOS | K37: NO APLICA | L37: Instituto Departamental de Deportes y Recreación de Sucre | M37: 211200000 | N37: 211200000 | O37: 211200000 | P37: servicio de apoyo a la actividad fisica la recreacion y el deporte | R37: =IF(AND(ISNUMBER(VALUE(LEFT(CUIPO_chip[[#This Row],[BPIN]],4))),LEN(CUIPO_chip[[#This Row],[BPIN]])>7),"VALIDO","") -> VALIDO
A38: 202606 | B38: VIGENCIA ACTUAL | C38: ENTIDADES TERRITORIALES - ADMINISTRACION CENTRAL | D38: 2.3.3.05.09.099 | E38: APORTES A ESTABLECIMIENTOS PUBLICOS Y UNIDADES ADMINISTRATIVAS ESPECIALES | F38: No aplica | G38: NO APLICA | H38: INGRESOS CORRIENTES DE DESTINACION ESPECIFICA POR ACTO ADMINISTRATIVO | I38: 202500000050554 | J38: CON SITUACION DE FONDOS | K38: NO APLICA | L38: Instituto Departamental de Deportes y Recreación de Sucre | M38: 498199350 | N38: 498199350 | O38: 498199350 | P38: servicio de apoyo a la actividad fisica la recreacion y el deporte | R38: =IF(AND(ISNUMBER(VALUE(LEFT(CUIPO_chip[[#This Row],[BPIN]],4))),LEN(CUIPO_chip[[#This Row],[BPIN]])>7),"VALIDO","") -> VALIDO
A39: 202606 | B39: VIGENCIA ACTUAL | C39: ENTIDADES TERRITORIALES - ADMINISTRACION CENTRAL | D39: 2.3.3.05.09.099 | E39: APORTES A ESTABLECIMIENTOS PUBLICOS Y UNIDADES ADMINISTRATIVAS ESPECIALES | F39: No aplica | G39: NO APLICA | H39: TASA PRODEPORTE Y RECREACION | I39: 202600000001143 | J39: CON SITUACION DE FONDOS | K39: NO APLICA | L39: Instituto Departamental de Deportes y Recreación de Sucre | M39: 424200000 | N39: 424200000 | O39: 424200000 | P39: servicio de apoyo a la actividad fisica la recreacion y el deporte | R39: =IF(AND(ISNUMBER(VALUE(LEFT(CUIPO_chip[[#This Row],[BPIN]],4))),LEN(CUIPO_chip[[#This Row],[BPIN]])>7),"VALIDO","") -> VALIDO
A40: 202606 | B40: VIGENCIA ACTUAL | C40: ENTIDADES TERRITORIALES - ADMINISTRACION CENTRAL | D40: 2.3.3.05.09.099 | E40: APORTES A ESTABLECIMIENTOS PUBLICOS Y UNIDADES ADMINISTRATIVAS ESPECIALES | F40: No aplica | G40: NO APLICA | H40: TASA PRODEPORTE Y RECREACION | I40: 202600000007861 | J40: CON SITUACION DE FONDOS | K40: NO APLICA | L40: Instituto Departamental de Deportes y Recreación de Sucre | M40: 168000000 | N40: 168000000 | O40: 168000000 | P40: servicio de apoyo a la actividad fisica la recreacion y el deporte | R40: =IF(AND(ISNUMBER(VALUE(LEFT(CUIPO_chip[[#This Row],[BPIN]],4))),LEN(CUIPO_chip[[#This Row],[BPIN]])>7),"VALIDO","") -> VALIDO
A41: 202606 | B41: VIGENCIA ACTUAL | C41: ENTIDADES TERRITORIALES - ADMINISTRACION CENTRAL | D41: 2.3.3.05.09.099 | E41: APORTES A ESTABLECIMIENTOS PUBLICOS Y UNIDADES ADMINISTRATIVAS ESPECIALES | F41: No aplica | G41: NO APLICA | H41: TASA PRODEPORTE Y RECREACION | I41: 202600000008787 | J41: CON SITUACION DE FONDOS | K41: NO APLICA | L41: Instituto Departamental de Deportes y Recreación de Sucre | M41: 1410000000 | N41: 1410000000 | O41: 1410000000 | P41: servicio de apoyo a la actividad fisica la recreacion y el deporte | R41: =IF(AND(ISNUMBER(VALUE(LEFT(CUIPO_chip[[#This Row],[BPIN]],4))),LEN(CUIPO_chip[[#This Row],[BPIN]])>7),"VALIDO","") -> VALIDO
A42: 202606 | B42: VIGENCIA ACTUAL | C42: ENTIDADES TERRITORIALES - ADMINISTRACION CENTRAL | D42: 2.3.3.05.09.099 | E42: APORTES A ESTABLECIMIENTOS PUBLICOS Y UNIDADES ADMINISTRATIVAS ESPECIALES | F42: No aplica | G42: NO APLICA | H42: RECURSOS DEL BALANCE DE DESTINACION ESPECIFICA POR ACTO ADMINISTRATIVO | I42: N/A | J42: CON SITUACION DE FONDOS | K42: NO APLICA | L42: Instituto Departamental de Deportes y Recreación de Sucre | M42: 355537570 | N42: 355537570 | O42: 355537570 | P42: servicio de apoyo a la actividad fisica la recreacion y el deporte | R42: =IF(AND(ISNUMBER(VALUE(LEFT(CUIPO_chip[[#This Row],[BPIN]],4))),LEN(CUIPO_chip[[#This Row],[BPIN]])>7),"VALIDO","")
A43: 202606 | B43: VIGENCIA ACTUAL | C43: ENTIDADES TERRITORIALES - ADMINISTRACION CENTRAL | D43: 2.3.3.05.09.099 | E43: APORTES A ESTABLECIMIENTOS PUBLICOS Y UNIDADES ADMINISTRATIVAS ESPECIALES | F43: No aplica | G43: NO APLICA | H43: R.B. TASA PRO DEPORTE | I43: N/A | J43: CON SITUACION DE FONDOS | K43: NO APLICA | L43: Instituto Departamental de Deportes y Recreación de Sucre | M43: 338300944 | N43: 338300944 | O43: 338300944 | P43: servicio de apoyo a la actividad fisica la recreacion y el deporte | R43: =IF(AND(ISNUMBER(VALUE(LEFT(CUIPO_chip[[#This Row],[BPIN]],4))),LEN(CUIPO_chip[[#This Row],[BPIN]])>7),"VALIDO","")
A44: 202606 | B44: VIGENCIA ACTUAL | C44: ENTIDADES TERRITORIALES - ADMINISTRACION CENTRAL | D44: 2.3.3.05.09.099 | E44: APORTES A ESTABLECIMIENTOS PUBLICOS Y UNIDADES ADMINISTRATIVAS ESPECIALES | F44: No aplica | G44: NO APLICA | H44: R.B. ESTAMPILLAS | I44: N/A | J44: CON SITUACION DE FONDOS | K44: NO APLICA | L44: Instituto Departamental de Deportes y Recreación de Sucre | M44: 54329091 | N44: 54329091 | O44: 54329091 | P44: servicio de apoyo a la actividad fisica la recreacion y el deporte | R44: =IF(AND(ISNUMBER(VALUE(LEFT(CUIPO_chip[[#This Row],[BPIN]],4))),LEN(CUIPO_chip[[#This Row],[BPIN]])>7),"VALIDO","")
A45: 202606 | B45: VIGENCIA ACTUAL | C45: ENTIDADES TERRITORIALES - ADMINISTRACION CENTRAL | D45: 2.3.3.05.09.099 | E45: APORTES A ESTABLECIMIENTOS PUBLICOS Y UNIDADES ADMINISTRATIVAS ESPECIALES | F45: No aplica | G45: NO APLICA | H45: INGRESOS CORRIENTES DE LIBRE DESTINACION | I45: 202500000049935 | J45: CON SITUACION DE FONDOS | K45: NO APLICA | L45: Fondo Mixto de Promoción de la Cultura y las Artes de Sucre | M45: 375000000 | N45: 375000000 | O45: 375000000 | P45: servicio de apoyo financiero al sector artistico y cultural | R45: =IF(AND(ISNUMBER(VALUE(LEFT(CUIPO_chip[[#This Row],[BPIN]],4))),LEN(CUIPO_chip[[#This Row],[BPIN]])>7),"VALIDO","") -> VALIDO
A46: 202606 | B46: VIGENCIA ACTUAL | C46: ENTIDADES TERRITORIALES - ADMINISTRACION CENTRAL | D46: 2.3.3.05.09.099 | E46: APORTES A ESTABLECIMIENTOS PUBLICOS Y UNIDADES ADMINISTRATIVAS ESPECIALES | F46: No aplica | G46: NO APLICA | H46: ESTAMPILLAS | I46: N/A | J46: CON SITUACION DE FONDOS | K46: NO APLICA | L46: Fondo Mixto de Promoción de la Cultura y las Artes de Sucre | M46: 735181387 | N46: 735181387 | O46: 735181387 | P46: servicio de asistenciatecnica en procesos de comunicacion cultural | R46: =IF(AND(ISNUMBER(VALUE(LEFT(CUIPO_chip[[#This Row],[BPIN]],4))),LEN(CUIPO_chip[[#This Row],[BPIN]])>7),"VALIDO","")
... A48: 202606 | B48: VIGENCIA ACTUAL | C48: ENTIDADES TERRITORIALES - ADMINISTRACION CENTRAL | D48: 2.3.3.05.09.099 | E48: APORTES A ESTABLECIMIENTOS PUBLICOS Y UNIDADES ADMINISTRATIVAS ESPECIALES | F48: No aplica | G48: NO APLICA | H48: ESTAMPILLAS | I48: 202600000005643 | J48: CON SITUACION DE FONDOS | K48: NO APLICA | L48: Fondo Mixto de Promoción de la Cultura y las Artes de Sucre | M48: 413917696 | N48: 413917696 | O48: 413917696 | P48: servicio de asistenciatecnica en procesos de comunicacion cultural | R48: =IF(AND(ISNUMBER(VALUE(LEFT(CUIPO_chip[[#This Row],[BPIN]],4))),LEN(CUIPO_chip[[#This Row],[BPIN]])>7),"VALIDO","") -> VALIDO
A49: 202606 | B49: VIGENCIA ACTUAL | C49: ENTIDADES TERRITORIALES - ADMINISTRACION CENTRAL | D49: 2.3.3.05.09.099 | E49: APORTES A ESTABLECIMIENTOS PUBLICOS Y UNIDADES ADMINISTRATIVAS ESPECIALES | F49: No aplica | G49: NO APLICA | H49: ESTAMPILLAS | I49: 202600000001594 | J49: CON SITUACION DE FONDOS | K49: NO APLICA | L49: Fondo Mixto de Promoción de la Cultura y las Artes de Sucre | M49: 721243321 | N49: 721243321 | O49: 721243321 | P49: servicio de promocion de actividades culturales | Q49: 3301053 | R49: =IF(AND(ISNUMBER(VALUE(LEFT(CUIPO_chip[[#This Row],[BPIN]],4))),LEN(CUIPO_chip[[#This Row],[BPIN]])>7),"VALIDO","") -> VALIDO
A50: 202606 | B50: VIGENCIA ACTUAL | C50: ENTIDADES TERRITORIALES - ADMINISTRACION CENTRAL | D50: 2.3.3.05.09.099 | E50: APORTES A ESTABLECIMIENTOS PUBLICOS Y UNIDADES ADMINISTRATIVAS ESPECIALES | F50: No aplica | G50: NO APLICA | H50: ESTAMPILLAS | I50: 202600000007252 | J50: CON SITUACION DE FONDOS | K50: NO APLICA | L50: Fondo Mixto de Promoción de la Cultura y las Artes de Sucre | M50: 49574149 | N50: 49574149 | O50: 49574149 | P50: servicio de promocion de actividades culturales | Q50: 3301053 | R50: =IF(AND(ISNUMBER(VALUE(LEFT(CUIPO_chip[[#This Row],[BPIN]],4))),LEN(CUIPO_chip[[#This Row],[BPIN]])>7),"VALIDO","") -> VALIDO
A51: 202606 | B51: VIGENCIA ACTUAL | C51: ENTIDADES TERRITORIALES - ADMINISTRACION CENTRAL | D51: 2.3.3.05.09.099 | E51: APORTES A ESTABLECIMIENTOS PUBLICOS Y UNIDADES ADMINISTRATIVAS ESPECIALES | F51: No aplica | G51: NO APLICA | H51: RECURSOS DEL BALANCE DE LIBRE DESTINACION | I51: 202600000013525 | J51: CON SITUACION DE FONDOS | K51: NO APLICA | L51: Fondo Mixto de Promoción de la Cultura y las Artes de Sucre | M51: 500000000 | N51: 500000000 | O51: 500000000 | P51: servicio de promocion de actividades culturales | Q51: 3301053 | R51: =IF(AND(ISNUMBER(VALUE(LEFT(CUIPO_chip[[#This Row],[BPIN]],4))),LEN(CUIPO_chip[[#This Row],[BPIN]])>7),"VALIDO","") -> VALIDO
A52: 202606 | B52: VIGENCIA ACTUAL | C52: ENTIDADES TERRITORIALES - ADMINISTRACION CENTRAL | D52: 2.3.3.05.09.099 | E52: APORTES A ESTABLECIMIENTOS PUBLICOS Y UNIDADES ADMINISTRATIVAS ESPECIALES | F52: No aplica | G52: NO APLICA | H52: R.B. ESTAMPILLAS | I52: 202600000010949 | J52: CON SITUACION DE FONDOS | K52: NO APLICA | L52: Fondo Mixto de Promoción de la Cultura y las Artes de Sucre | M52: 211605142 | N52: 211605142 | O52: 211605142 | P52: servicio de promocion de actividades culturales | Q52: 3301053 | R52: =IF(AND(ISNUMBER(VALUE(LEFT(CUIPO_chip[[#This Row],[BPIN]],4))),LEN(CUIPO_chip[[#This Row],[BPIN]])>7),"VALIDO","") -> VALIDO
A53: 202606 | B53: VIGENCIA ACTUAL | C53: ENTIDADES TERRITORIALES - ADMINISTRACION CENTRAL | D53: 2.3.3.05.09.099 | E53: APORTES A ESTABLECIMIENTOS PUBLICOS Y UNIDADES ADMINISTRATIVAS ESPECIALES | F53: No aplica | G53: NO APLICA | H53: R.B. ESTAMPILLAS | I53: 202600000011466 | J53: CON SITUACION DE FONDOS | K53: NO APLICA | L53: Fondo Mixto de Promoción de la Cultura y las Artes de Sucre | M53: 267224950 | N53: 267224950 | O53: 267224950 | P53: servicio de promocion de actividades culturales | Q53: 3301053 | R53: =IF(AND(ISNUMBER(VALUE(LEFT(CUIPO_chip[[#This Row],[BPIN]],4))),LEN(CUIPO_chip[[#This Row],[BPIN]])>7),"VALIDO","") -> VALIDO
A54: 202606 | B54: VIGENCIA ACTUAL | C54: ENTIDADES TERRITORIALES - ADMINISTRACION CENTRAL | D54: 2.3.3.05.09.099 | E54: APORTES A ESTABLECIMIENTOS PUBLICOS Y UNIDADES ADMINISTRATIVAS ESPECIALES | F54: No aplica | G54: NO APLICA | H54: R.B. ESTAMPILLAS | I54: 202600000011619 | J54: CON SITUACION DE FONDOS | K54: NO APLICA | L54: Fondo Mixto de Promoción de la Cultura y las Artes de Sucre | M54: 840179004 | N54: 840179004 | O54: 840179004 | P54: servicio de promocion de actividades culturales | Q54: 3301053 | R54: =IF(AND(ISNUMBER(VALUE(LEFT(CUIPO_chip[[#This Row],[BPIN]],4))),LEN(CUIPO_chip[[#This Row],[BPIN]])>7),"VALIDO","") -> VALIDO
A55: 202606 | B55: VIGENCIA ACTUAL | C55: ENTIDADES TERRITORIALES - ADMINISTRACION CENTRAL | D55: 2.3.3.05.09.099 | E55: APORTES A ESTABLECIMIENTOS PUBLICOS Y UNIDADES ADMINISTRATIVAS ESPECIALES | F55: No aplica | G55: NO APLICA | H55: SGP-AGUA POTABLE Y SANEAMIENTO BASICO | I55: 202600000008749 | J55: CON SITUACION DE FONDOS | K55: NO APLICA | L55: E.S.P. Empresa Aguas de Sucre S.A. | M55: 17103388502 | N55: 2185764639 | O55: 2185764639 | P55: servicio de apoyo financiero para capitalizacion de empresas | R55: =IF(AND(ISNUMBER(VALUE(LEFT(CUIPO_chip[[#This Row],[BPIN]],4))),LEN(CUIPO_chip[[#This Row],[BPIN]])>7),"VALIDO","") -> VALIDO
A56: 202606 | B56: VIGENCIA ACTUAL | C56: ENTIDADES TERRITORIALES - ADMINISTRACION CENTRAL | D56: 2.3.3.05.09.099 | E56: APORTES A ESTABLECIMIENTOS PUBLICOS Y UNIDADES ADMINISTRATIVAS ESPECIALES | F56: No aplica | G56: NO APLICA | H56: ICLD DEPARTAMENTOS PARA FONPET | I56: 202600000012017 | J56: CON SITUACION DE FONDOS | K56: NO APLICA | L56: NO APLICA | M56: 150000000 | N56: 150000000 | O56: 150000000 | P56: servicio educativos de promocion del bilingismo | Q56: 2201034 | R56: =IF(AND(ISNUMBER(VALUE(LEFT(CUIPO_chip[[#This Row],[BPIN]],4))),LEN(CUIPO_chip[[#This Row],[BPIN]])>7),"VALIDO","") -> VALIDO
A57: 202606 | B57: VIGENCIA ACTUAL | C57: ENTIDADES TERRITORIALES - ADMINISTRACION CENTRAL | D57: 2.3.3.05.09.099 | E57: APORTES A ESTABLECIMIENTOS PUBLICOS Y UNIDADES ADMINISTRATIVAS ESPECIALES | F57: No aplica | G57: NO APLICA | H57: TASA PRODEPORTE Y RECREACION | I57: 202600000012764 | J57: CON SITUACION DE FONDOS | K57: NO APLICA | L57: Instituto Departamental de Deportes y Recreación de Sucre | M57: 236174575 | N57: 236174575 | O57: 236174575 | P57: servicio de apoyo a la actividad fisica la recreacion y el deporte | R57: =IF(AND(ISNUMBER(VALUE(LEFT(CUIPO_chip[[#This Row],[BPIN]],4))),LEN(CUIPO_chip[[#This Row],[BPIN]])>7),"VALIDO","") -> VALIDO
A58: 202606 | B58: VIGENCIA ACTUAL | C58: ENTIDADES TERRITORIALES - ADMINISTRACION CENTRAL | D58: 2.3.3.05.09.099 | E58: APORTES A ESTABLECIMIENTOS PUBLICOS Y UNIDADES ADMINISTRATIVAS ESPECIALES | F58: No aplica | G58: NO APLICA | H58: R.B. TASA PRO DEPORTE | I58: 202600000012764 | J58: CON SITUACION DE FONDOS | K58: NO APLICA | L58: Instituto Departamental de Deportes y Recreación de Sucre | M58: 718400002 | N58: 718400002 | O58: 718400002 | P58: servicio de apoyo a la actividad fisica la recreacion y el deporte | R58: =IF(AND(ISNUMBER(VALUE(LEFT(CUIPO_chip[[#This Row],[BPIN]],4))),LEN(CUIPO_chip[[#This Row],[BPIN]])>7),"VALIDO","") -> VALIDO
A59: 202606 | B59: VIGENCIA ACTUAL | C59: ENTIDADES TERRITORIALES - ADMINISTRACION CENTRAL | D59: 2.3.7.05.03 | E59: PAGO DE DEFICIT FISCAL, DE PASIVO LABORAL Y PRESTACIONAL EN PROGRAMAS DE SANEAMIENTO FISCAL Y FINANCIERO | F59: No aplica | G59: NO APLICA | H59: INGRESOS CORRIENTES DE LIBRE DESTINACION | I59: 2025 | J59: CON SITUACION DE FONDOS | K59: NO APLICA | L59: NO APLICA | M59: 2390132344 | N59: 2013255837 | O59: 1941335936 | P59: servicio de reeestructuracion de pasivos | R59: =IF(AND(ISNUMBER(VALUE(LEFT(CUIPO_chip[[#This Row],[BPIN]],4))),LEN(CUIPO_chip[[#This Row],[BPIN]])>7),"VALIDO","")
A60: 202606 | B60: VIGENCIA ACTUAL | C60: ENTIDADES TERRITORIALES - ADMINISTRACION CENTRAL | D60: 2.3.7.05.03 | E60: PAGO DE DEFICIT FISCAL, DE PASIVO LABORAL Y PRESTACIONAL EN PROGRAMAS DE SANEAMIENTO FISCAL Y FINANCIERO | F60: No aplica | G60: NO APLICA | H60: ESTAMPILLAS | I60: 2025 | J60: CON SITUACION DE FONDOS | K60: NO APLICA | L60: NO APLICA | M60: 3043771828 | N60: 3043771828 | O60: 3043771828 | P60: servicio de saneamiento fiscal y financiero | R60: =IF(AND(ISNUMBER(VALUE(LEFT(CUIPO_chip[[#This Row],[BPIN]],4))),LEN(CUIPO_chip[[#This Row],[BPIN]])>7),"VALIDO","")
A61: 202606 | B61: VIGENCIA ACTUAL | C61: ENTIDADES TERRITORIALES - ADMINISTRACION CENTRAL | D61: 2.3.7.05.03 | E61: PAGO DE DEFICIT FISCAL, DE PASIVO LABORAL Y PRESTACIONAL EN PROGRAMAS DE SANEAMIENTO FISCAL Y FINANCIERO | F61: No aplica | G61: NO APLICA | H61: R.B. ESTAMPILLAS | I61: 0 | J61: CON SITUACION DE FONDOS | K61: NO APLICA | L61: NO APLICA | M61: 10519412336 | N61: 10519412336 | O61: 10519412336 | P61: servicio de reeestructuracion de pasivos | R61: =IF(AND(ISNUMBER(VALUE(LEFT(CUIPO_chip[[#This Row],[BPIN]],4))),LEN(CUIPO_chip[[#This Row],[BPIN]])>7),"VALIDO","")
A62: 202606 | B62: VIGENCIA ACTUAL | C62: ENTIDADES TERRITORIALES - SALUD | D62: 2.3.1.01.01.001.01 | E62: SUELDO BASICO | F62: No aplica | G62: OGS - DIFERENTES A LOS CONTEMPLADOS EN LAS DEMÁS SUBCUENTAS | H62: RECURSOS DEL BALANCE DE DESTINACION ESPECIFICA POR ACTO ADMINISTRATIVO | I62: 202500000048147 | J62: CON SITUACION DE FONDOS | K62: NO APLICA | L62: NO APLICA | M62: 42864517 | N62: 42864517 | O62: 0 | P62: servicio de inspeccion vigilancia y control | Q62: 1903011 | R62: =IF(AND(ISNUMBER(VALUE(LEFT(CUIPO_chip[[#This Row],[BPIN]],4))),LEN(CUIPO_chip[[#This Row],[BPIN]])>7),"VALIDO","") -> VALIDO
A63: 202606 | B63: VIGENCIA ACTUAL | C63: ENTIDADES TERRITORIALES - SALUD | D63: 2.3.1.01.02.001 | E63: APORTES A LA SEGURIDAD SOCIAL EN PENSIONES | F63: No aplica | G63: SPC - E1 GOBERNABILIDAD Y GOBERNANZA - L1 DESARROLLO INSTITUCIONAL Y SECTORIAL - PLANEACIÓN INTEGRAL EN SALUD | H63: INGRESOS CORRIENTES DE DESTINACION ESPECIFICA POR ACTO ADMINISTRATIVO | I63: 0 | J63: CON SITUACION DE FONDOS | K63: NO APLICA | L63: NO APLICA | M63: 62699144 | N63: 62699144 | O63: 62699144 | P63: documentos de lineamientos tecnicos | Q63: 1903001 | R63: =IF(AND(ISNUMBER(VALUE(LEFT(CUIPO_chip[[#This Row],[BPIN]],4))),LEN(CUIPO_chip[[#This Row],[BPIN]])>7),"VALIDO","")
A64: 202606 | B64: VIGENCIA ACTUAL | C64: ENTIDADES TERRITORIALES - SALUD | D64: 2.3.1.01.02.002 | E64: APORTES A LA SEGURIDAD SOCIAL EN SALUD | F64: No aplica | G64: SPC - E1 GOBERNABILIDAD Y GOBERNANZA - L1 DESARROLLO INSTITUCIONAL Y SECTORIAL - PLANEACIÓN INTEGRAL EN SALUD | H64: INGRESOS CORRIENTES DE DESTINACION ESPECIFICA POR ACTO ADMINISTRATIVO | I64: 0 | J64: CON SITUACION DE FONDOS | K64: NO APLICA | L64: NO APLICA | M64: 44468271 | N64: 44468271 | O64: 44468271 | P64: documentos de lineamientos tecnicos | Q64: 1903001 | R64: =IF(AND(ISNUMBER(VALUE(LEFT(CUIPO_chip[[#This Row],[BPIN]],4))),LEN(CUIPO_chip[[#This Row],[BPIN]])>7),"VALIDO","")
A65: 202606 | B65: VIGENCIA ACTUAL | C65: ENTIDADES TERRITORIALES - SALUD | D65: 2.3.1.01.02.003 | E65: APORTES DE CESANTIAS | F65: No aplica | G65: SPC - E1 GOBERNABILIDAD Y GOBERNANZA - L1 DESARROLLO INSTITUCIONAL Y SECTORIAL - PLANEACIÓN INTEGRAL EN SALUD | H65: INGRESOS CORRIENTES DE DESTINACION ESPECIFICA POR ACTO ADMINISTRATIVO | I65: 0 | J65: CON SITUACION DE FONDOS | K65: NO APLICA | L65: NO APLICA | M65: 119504672 | N65: 119504672 | O65: 119504672 | P65: documentos de lineamientos tecnicos | Q65: 1903001 | R65: =IF(AND(ISNUMBER(VALUE(LEFT(CUIPO_chip[[#This Row],[BPIN]],4))),LEN(CUIPO_chip[[#This Row],[BPIN]])>7),"VALIDO","")
A66: 202606 | B66: VIGENCIA ACTUAL | C66: ENTIDADES TERRITORIALES - SALUD | D66: 2.3.1.01.02.004 | E66: APORTES A CAJAS DE COMPENSACION FAMILIAR | F66: No aplica | G66: SPC - E1 GOBERNABILIDAD Y GOBERNANZA - L1 DESARROLLO INSTITUCIONAL Y SECTORIAL - PLANEACIÓN INTEGRAL EN SALUD | H66: INGRESOS CORRIENTES DE DESTINACION ESPECIFICA POR ACTO ADMINISTRATIVO | I66: 0 | J66: CON SITUACION DE FONDOS | K66: NO APLICA | L66: NO APLICA | M66: 20985100 | N66: 20985100 | O66: 20985100 | P66: documentos de lineamientos tecnicos | Q66: 1903001 | R66: =IF(AND(ISNUMBER(VALUE(LEFT(CUIPO_chip[[#This Row],[BPIN]],4))),LEN(CUIPO_chip[[#This Row],[BPIN]])>7),"VALIDO","")
A67: 202606 | B67: VIGENCIA ACTUAL | C67: ENTIDADES TERRITORIALES - SALUD | D67: 2.3.1.01.02.005 | E67: APORTES GENERALES AL SISTEMA DE RIESGOS LABORALES | F67: No aplica | G67: SPC - E1 GOBERNABILIDAD Y GOBERNANZA - L1 DESARROLLO INSTITUCIONAL Y SECTORIAL - PLANEACIÓN INTEGRAL EN SALUD | H67: INGRESOS CORRIENTES DE DESTINACION ESPECIFICA POR ACTO ADMINISTRATIVO | I67: 0 | J67: CON SITUACION DE FONDOS | K67: NO APLICA | L67: NO APLICA | M67: 16341600 | N67: 16341600 | O67: 16341600 | P67: documentos de lineamientos tecnicos | Q67: 1903001 | R67: =IF(AND(ISNUMBER(VALUE(LEFT(CUIPO_chip[[#This Row],[BPIN]],4))),LEN(CUIPO_chip[[#This Row],[BPIN]])>7),"VALIDO","")
A68: 202606 | B68: VIGENCIA ACTUAL | C68: ENTIDADES TERRITORIALES - SALUD | D68: 2.3.1.01.02.006 | E68: APORTES AL ICBF | F68: No aplica | G68: SPC - E1 GOBERNABILIDAD Y GOBERNANZA - L1 DESARROLLO INSTITUCIONAL Y SECTORIAL - PLANEACIÓN INTEGRAL EN SALUD | H68: INGRESOS CORRIENTES DE DESTINACION ESPECIFICA POR ACTO ADMINISTRATIVO | I68: 0 | J68: CON SITUACION DE FONDOS | K68: NO APLICA | L68: Instituto Colombiano de Bienestar Familiar | M68: 15733500 | N68: 15733500 | O68: 15733500 | P68: documentos de lineamientos tecnicos | Q68: 1903001 | R68: =IF(AND(ISNUMBER(VALUE(LEFT(CUIPO_chip[[#This Row],[BPIN]],4))),LEN(CUIPO_chip[[#This Row],[BPIN]])>7),"VALIDO","")
A69: 202606 | B69: VIGENCIA ACTUAL | C69: ENTIDADES TERRITORIALES - SALUD | D69: 2.3.1.01.02.007 | E69: APORTES AL SENA | F69: No aplica | G69: SPC - E1 GOBERNABILIDAD Y GOBERNANZA - L1 DESARROLLO INSTITUCIONAL Y SECTORIAL - PLANEACIÓN INTEGRAL EN SALUD | H69: INGRESOS CORRIENTES DE DESTINACION ESPECIFICA POR ACTO ADMINISTRATIVO | I69: 0 | J69: CON SITUACION DE FONDOS | K69: NO APLICA | L69: Servicio Nacional de Aprendizaje | M69: 2634200 | N69: 2634200 | O69: 2634200 | P69: documentos de lineamientos tecnicos | Q69: 1903001 | R69: =IF(AND(ISNUMBER(VALUE(LEFT(CUIPO_chip[[#This Row],[BPIN]],4))),LEN(CUIPO_chip[[#This Row],[BPIN]])>7),"VALIDO","")
A70: 202606 | B70: VIGENCIA ACTUAL | C70: ENTIDADES TERRITORIALES - SALUD | D70: 2.3.1.01.02.008 | E70: APORTES A LA ESAP | F70: No aplica | G70: SPC - E1 GOBERNABILIDAD Y GOBERNANZA - L1 DESARROLLO INSTITUCIONAL Y SECTORIAL - PLANEACIÓN INTEGRAL EN SALUD | H70: INGRESOS CORRIENTES DE DESTINACION ESPECIFICA POR ACTO ADMINISTRATIVO | I70: 0 | J70: CON SITUACION DE FONDOS | K70: NO APLICA | L70: Escuela Superior de Administración Pública | M70: 2634200 | N70: 2634200 | O70: 2634200 | P70: documentos de lineamientos tecnicos | Q70: 1903001 | R70: =IF(AND(ISNUMBER(VALUE(LEFT(CUIPO_chip[[#This Row],[BPIN]],4))),LEN(CUIPO_chip[[#This Row],[BPIN]])>7),"VALIDO","")
A71: 202606 | B71: VIGENCIA ACTUAL | C71: ENTIDADES TERRITORIALES - SALUD | D71: 2.3.1.01.02.009 | E71: APORTES A ESCUELAS INDUSTRIALES E INSTITUTOS TECNICOS | F71: No aplica | G71: SPC - E1 GOBERNABILIDAD Y GOBERNANZA - L1 DESARROLLO INSTITUCIONAL Y SECTORIAL - PLANEACIÓN INTEGRAL EN SALUD | H71: INGRESOS CORRIENTES DE DESTINACION ESPECIFICA POR ACTO ADMINISTRATIVO | I71: 0 | J71: CON SITUACION DE FONDOS | K71: NO APLICA | L71: Ministerio de Educación Nacional | M71: 5254100 | N71: 5254100 | O71: 5254100 | P71: documentos de lineamientos tecnicos | Q71: 1903001 | R71: =IF(AND(ISNUMBER(VALUE(LEFT(CUIPO_chip[[#This Row],[BPIN]],4))),LEN(CUIPO_chip[[#This Row],[BPIN]])>7),"VALIDO","")
A72: 202606 | B72: VIGENCIA ACTUAL | C72: ENTIDADES TERRITORIALES - SALUD | D72: 2.3.2.01.01.001.02.08 | E72: EDIFICIOS RELACIONADOS CON SALUD | F72: No aplica | G72: OGS - DIFERENTES A LOS CONTEMPLADOS EN LAS DEMÁS SUBCUENTAS | H72: RECURSOS DEL BALANCE DE DESTINACION ESPECIFICA POR ACTO ADMINISTRATIVO | I72: 2023002700021 | J72: CON SITUACION DE FONDOS | K72: NO APLICA | L72: NO APLICA | M72: 1027664538 | N72: 0 | O72: 0 | P72: hospitales de primer nivel de atencion construidos y dotados | R72: =IF(AND(ISNUMBER(VALUE(LEFT(CUIPO_chip[[#This Row],[BPIN]],4))),LEN(CUIPO_chip[[#This Row],[BPIN]])>7),"VALIDO","") -> VALIDO
A73: 202606 | B73: VIGENCIA ACTUAL | C73: ENTIDADES TERRITORIALES - SALUD | D73: 2.3.2.02.01.003 | E73: OTROS BIENES TRANSPORTABLES EXCEPTO PRODUCTOS METALICOS, MAQUINARIA Y EQUIPO | F73: Servicios de la administracion publica relacionados con la salud | G73: SPC - E1 GOBERNABILIDAD Y GOBERNANZA - L1 DESARROLLO INSTITUCIONAL Y SECTORIAL - VIGILANCIA EN SALUD PÚBLICA Y FORTALECIMIENTO DE LOS LABORATORIOS EN SALUD PÚBLICA | H73: SGP-SALUD-SALUD PUBLICA | I73: 202500000047955 | J73: CON SITUACION DE FONDOS | K73: NO APLICA | L73: NO APLICA | M73: 930286149 | N73: 0 | O73: 0 | P73: servicio de inspeccion vigilancia y control de los factores del riesgo del ambiente que afectan la salud humana | R73: =IF(AND(ISNUMBER(VALUE(LEFT(CUIPO_chip[[#This Row],[BPIN]],4))),LEN(CUIPO_chip[[#This Row],[BPIN]])>7),"VALIDO","") -> VALIDO
A74: 202606 | B74: VIGENCIA ACTUAL | C74: ENTIDADES TERRITORIALES - SALUD | D74: 2.3.2.02.02.006 | E74: COMERCIO Y DISTRIBUCION; ALOJAMIENTO; SERVICIOS DE SUMINISTRO DE COMIDAS Y BEBIDAS; SERVICIOS DE TRANSPORTE; Y SERVICIOS DE DISTRIBUCION DE ELECTRICIDAD, GAS Y AGUA | F74: Servicios de la administracion publica relacionados con la salud | G74: SPC - E1 GOBERNABILIDAD Y GOBERNANZA - L1 DESARROLLO INSTITUCIONAL Y SECTORIAL - INSPECCIÓN, VIGILANCIA Y CONTROL SANITARIOS | H74: SGP-SALUD-SALUD PUBLICA | I74: 202500000047955 | J74: CON SITUACION DE FONDOS | K74: NO APLICA | L74: NO APLICA | M74: 27000000 | N74: 0 | O74: 0 | P74: servicio de promocion prevencion vigilancia y control de vectores y zoonosis | Q74: 1903038 | R74: =IF(AND(ISNUMBER(VALUE(LEFT(CUIPO_chip[[#This Row],[BPIN]],4))),LEN(CUIPO_chip[[#This Row],[BPIN]])>7),"VALIDO","") -> VALIDO
A75: 202606 | B75: VIGENCIA ACTUAL | C75: ENTIDADES TERRITORIALES - SALUD | D75: 2.3.2.02.02.006 | E75: COMERCIO Y DISTRIBUCION; ALOJAMIENTO; SERVICIOS DE SUMINISTRO DE COMIDAS Y BEBIDAS; SERVICIOS DE TRANSPORTE; Y SERVICIOS DE DISTRIBUCION DE ELECTRICIDAD, GAS Y AGUA | F75: Servicios de la administracion publica relacionados con la salud | G75: SPC - E1 GOBERNABILIDAD Y GOBERNANZA - L1 DESARROLLO INSTITUCIONAL Y SECTORIAL - INSPECCIÓN, VIGILANCIA Y CONTROL SANITARIOS | H75: SGP-SALUD-SALUD PUBLICA | I75: 202500000047955 | J75: CON SITUACION DE FONDOS | K75: NO APLICA | L75: NO APLICA | M75: 483300000 | N75: 26850000 | O75: 26850000 | P75: servicio de inspeccion vigilancia y control de los factores del riesgo del ambiente que afectan la salud humana | R75: =IF(AND(ISNUMBER(VALUE(LEFT(CUIPO_chip[[#This Row],[BPIN]],4))),LEN(CUIPO_chip[[#This Row],[BPIN]])>7),"VALIDO","") -> VALIDO
A76: 202606 | B76: VIGENCIA ACTUAL | C76: ENTIDADES TERRITORIALES - SALUD | D76: 2.3.2.02.02.006 | E76: COMERCIO Y DISTRIBUCION; ALOJAMIENTO; SERVICIOS DE SUMINISTRO DE COMIDAS Y BEBIDAS; SERVICIOS DE TRANSPORTE; Y SERVICIOS DE DISTRIBUCION DE ELECTRICIDAD, GAS Y AGUA | F76: Servicios de la administracion publica relacionados con la salud | G76: SPC - E1 GOBERNABILIDAD Y GOBERNANZA - L1 DESARROLLO INSTITUCIONAL Y SECTORIAL - VIGILANCIA EN SALUD PÚBLICA Y FORTALECIMIENTO DE LOS LABORATORIOS EN SALUD PÚBLICA | H76: SGP-SALUD-SALUD PUBLICA | I76: 202500000047955 | J76: CON SITUACION DE FONDOS | K76: NO APLICA | L76: NO APLICA | M76: 57000000 | N76: 5700000 | O76: 3420000 | P76: servicio de inspeccion vigilancia y control de los factores del riesgo del ambiente que afectan la salud humana | R76: =IF(AND(ISNUMBER(VALUE(LEFT(CUIPO_chip[[#This Row],[BPIN]],4))),LEN(CUIPO_chip[[#This Row],[BPIN]])>7),"VALIDO","") -> VALIDO
A77: 202606 | B77: VIGENCIA ACTUAL | C77: ENTIDADES TERRITORIALES - SALUD | D77: 2.3.2.02.02.008 | E77: SERVICIOS PRESTADOS A LAS EMPRESAS Y SERVICIOS DE PRODUCCION | F77: Servicios de la administracion publica relacionados con la salud | G77: SPC - E4 ATENCIÓN PRIMARIA SALUD - L1 DESARROLLO INSTITUCIONAL Y SECTORIAL - DESARROLLO DE CAPACIDADES EN SALUD PÚBLICA PARA LA IMPLEMENTACIÓN DE LA ESTRATEGIA DE ATENCIÓN PRIMARIA EN SALUD | H77: SGP-SALUD-SALUD PUBLICA | I77: 202500000047500 | J77: CON SITUACION DE FONDOS | K77: NO APLICA | L77: NO APLICA | M77: 45880450 | N77: 0 | O77: 0 | P77: servicio de asistencia tecnica | Q77: 1905050 | R77: =IF(AND(ISNUMBER(VALUE(LEFT(CUIPO_chip[[#This Row],[BPIN]],4))),LEN(CUIPO_chip[[#This Row],[BPIN]])>7),"VALIDO","") -> VALIDO
A78: 202606 | B78: VIGENCIA ACTUAL | C78: ENTIDADES TERRITORIALES - SALUD | D78: 2.3.2.02.02.009 | E78: SERVICIOS PARA LA COMUNIDAD, SOCIALES Y PERSONALES | F78: Servicios de la administracion publica relacionados con la salud | G78: SPC - E7 PERSONAL SALUD - L2 ACUERDOS SOCIALES Y COMUNITARIOS - COORDINACIÓN INTERSECTORIAL EN EL MARCO DE LA POLÍTICA NACIONAL DE TALENTO HUMANO EN SALUD. | H78: R.B. SGP-SALUD-SALUD PUBLICA | I78: 2025 | J78: CON SITUACION DE FONDOS | K78: NO APLICA | L78: NO APLICA | M78: 1627085386 | N78: 1619603286 | O78: 1619603286 | P78: servicio de inspeccion vigilancia y control de los factores del riesgo del ambiente que afectan la salud humana | R78: =IF(AND(ISNUMBER(VALUE(LEFT(CUIPO_chip[[#This Row],[BPIN]],4))),LEN(CUIPO_chip[[#This Row],[BPIN]])>7),"VALIDO","")
A79: 202606 | B79: VIGENCIA ACTUAL | C79: ENTIDADES TERRITORIALES - SALUD | D79: 2.3.2.02.02.009 | E79: SERVICIOS PARA LA COMUNIDAD, SOCIALES Y PERSONALES | F79: Servicios de la administracion publica relacionados con la salud | G79: OGS - E2 PUEBLOS Y COMUNIDADES - L3 CUIDADO DE LA SALUD - PERSONAS CON DISCAPACIDAD | H79: R.B. TRANSFERENCIAS DE CAPITAL DE OTRAS ENTIDADES DEL GOBIERNO GENERAL | I79: 2026 | J79: CON SITUACION DE FONDOS | K79: NO APLICA | L79: NO APLICA | M79: 357479451 | N79: 357479451 | O79: 253223370 | P79: servicio de gestion del riesgo para enfermedades emergentes reemergentes y desatendidas | Q79: 1905026 | R79: =IF(AND(ISNUMBER(VALUE(LEFT(CUIPO_chip[[#This Row],[BPIN]],4))),LEN(CUIPO_chip[[#This Row],[BPIN]])>7),"VALIDO","")
A80: 202606 | B80: VIGENCIA ACTUAL | C80: ENTIDADES TERRITORIALES - SALUD | D80: 2.3.2.02.02.009 | E80: SERVICIOS PARA LA COMUNIDAD, SOCIALES Y PERSONALES | F80: Servicios de la administracion publica relacionados con la salud | G80: SPC - E4 ATENCIÓN PRIMARIA SALUD - L1 DESARROLLO INSTITUCIONAL Y SECTORIAL - DESARROLLO DE CAPACIDADES EN SALUD PÚBLICA PARA LA IMPLEMENTACIÓN DE LA ESTRATEGIA DE ATENCIÓN PRIMARIA EN SALUD | H80: SGP-SALUD-SALUD PUBLICA | I80: 202500000047500 | J80: CON SITUACION DE FONDOS | K80: NO APLICA | L80: NO APLICA | M80: 38640150 | N80: 25760100 | O80: 25760100 | P80: servicio de promocion de vida saludable y condiciones no transmisibles | R80: =IF(AND(ISNUMBER(VALUE(LEFT(CUIPO_chip[[#This Row],[BPIN]],4))),LEN(CUIPO_chip[[#This Row],[BPIN]])>7),"VALIDO","") -> VALIDO
A81: 202606 | B81: VIGENCIA ACTUAL | C81: ENTIDADES TERRITORIALES - SALUD | D81: 2.3.2.02.02.009 | E81: SERVICIOS PARA LA COMUNIDAD, SOCIALES Y PERSONALES | F81: Servicios de la administracion publica relacionados con la salud | G81: SPC - E4 ATENCIÓN PRIMARIA SALUD - L2 ACUERDOS SOCIALES Y COMUNITARIOS - COORDINACIÓN INTERSECTORIAL PARA EL CUIDADO DE LA SALUD EN LOS TERRITORIOS EN EL MARCO DE LA ATENCIÓN PRIMARIA EN SALUD. | H81: SGP-SALUD-SALUD PUBLICA | I81: 202500000047500 | J81: CON SITUACION DE FONDOS | K81: NO APLICA | L81: NO APLICA | M81: 12880050 | N81: 2146675 | O81: 2146675 | P81: servicio de asistencia tecnica | Q81: 1905050 | R81: =IF(AND(ISNUMBER(VALUE(LEFT(CUIPO_chip[[#This Row],[BPIN]],4))),LEN(CUIPO_chip[[#This Row],[BPIN]])>7),"VALIDO","") -> VALIDO
A82: 202606 | B82: VIGENCIA ACTUAL | C82: ENTIDADES TERRITORIALES - SALUD | D82: 2.3.2.02.02.009 | E82: SERVICIOS PARA LA COMUNIDAD, SOCIALES Y PERSONALES | F82: Servicios de la administracion publica relacionados con la salud | G82: SPC - E2 PUEBLOS Y COMUNIDADES - L1 DESARROLLO INSTITUCIONAL Y SECTORIAL - DESARROLLO DE CAPACIDADES EN SALUD PÚBLICA PARA LA TRANSVERSALIZACIÓN DEL ENFOQUE DIFERENCIAL E INTERSECCIONAL. | H82: SGP-SALUD-SALUD PUBLICA | I82: 202500000047500 | J82: CON SITUACION DE FONDOS | K82: NO APLICA | L82: NO APLICA | M82: 359771820 | N82: 252727930 | O82: 239905852 | P82: servicio de asistencia tecnica | Q82: 1905050 | R82: =IF(AND(ISNUMBER(VALUE(LEFT(CUIPO_chip[[#This Row],[BPIN]],4))),LEN(CUIPO_chip[[#This Row],[BPIN]])>7),"VALIDO","") -> VALIDO
A83: 202606 | B83: VIGENCIA ACTUAL | C83: ENTIDADES TERRITORIALES - SALUD | D83: 2.3.2.02.02.009 | E83: SERVICIOS PARA LA COMUNIDAD, SOCIALES Y PERSONALES | F83: Servicios de la administracion publica relacionados con la salud | G83: SPC - E2 PUEBLOS Y COMUNIDADES - L2 ACUERDOS SOCIALES Y COMUNITARIOS - PARTICIPACIÓN SOCIAL DE PUEBLOS Y COMUNIDADES ÉTNICAS Y CAMPESINAS, MUJERES, SECTORES LGBTIQ+ Y OTRAS POBLACIONES POR CONDICIÓN Y | H83: SGP-SALUD-SALUD PUBLICA | I83: 202500000047500 | J83: CON SITUACION DE FONDOS | K83: NO APLICA | L83: NO APLICA | M83: 51520200 | N83: 32772571 | O83: 32772571 | P83: servicio de asistencia tecnica | Q83: 1905050 | R83: =IF(AND(ISNUMBER(VALUE(LEFT(CUIPO_chip[[#This Row],[BPIN]],4))),LEN(CUIPO_chip[[#This Row],[BPIN]])>7),"VALIDO","") -> VALIDO
